Workbook

Sheet Sheet1
C1: Text | D1: Number | E1: Decimal | F1: Date | G1: Time | H1: List
C2: amit | D2: 55 | E2: 1 | L2: A
C3: rohit | D3: 67 | E3: 4.7 | H3: B | L3: B
D4: 89 | E4: 4.2 | F4: 46152 | H4: C | L4: C
D5: 6 | E5: 4 | H5: A | L5: F
H6: B | L6: E
H7: F | L7: A+
L8: B+

Sheet Sheet2
A1: Branch | B1: Country | C1: TransactionType | D1: Category | E1: Currency | F1: Amount | G1: AmountUSD
A2: London | B2: UK | C2: Withdrawal | D2: Dining | E2: EUR | F2: 955.8 | G2: =F2*VLOOKUP(E2,{"USD",1;"EUR",1.08;"GBP",1.27;"JPY",0.0067;"CNY",0.14;"INR",0.012},2,FALSE) -> 1032.264
A3: Tokyo | B3: Japan | C3: Fee | D3: Other | E3: USD | F3: 1200.41 | G3: =F3*VLOOKUP(E3,{"USD",1;"EUR",1.08;"GBP",1.27;"JPY",0.0067;"CNY",0.14;"INR",0.012},2,FALSE) -> 1200.41
A4: Toronto | B4: Canada | C4: Withdrawal | D4: Dining | E4: USD | F4: 1842.59 | G4: =F4*VLOOKUP(E4,{"USD",1;"EUR",1.08;"GBP",1.27;"JPY",0.0067;"CNY",0.14;"INR",0.012},2,FALSE) -> 1842.59 | J4: #VALUE!
A5: New York | B5: USA | C5: Withdrawal | D5: Entertainment | E5: EUR | F5: 522.01 | G5: =F5*VLOOKUP(E5,{"USD",1;"EUR",1.08;"GBP",1.27;"JPY",0.0067;"CNY",0.14;"INR",0.012},2,FALSE) -> 563.7708
A6: New York | B6: USA | C6: Withdrawal | D6: Shopping | E6: USD | F6: 874.91 | G6: =F6*VLOOKUP(E6,{"USD",1;"EUR",1.08;"GBP",1.27;"JPY",0.0067;"CNY",0.14;"INR",0.012},2,FALSE) -> 874.91
A7: Sydney | B7: Australia | C7: Payment | D7: Education | E7: USD | F7: 4131.94 | G7: =F7*VLOOKUP(E7,{"USD",1;"EUR",1.08;"GBP",1.27;"JPY",0.0067;"CNY",0.14;"INR",0.012},2,FALSE) -> 4131.94
A8: Singapore | B8: Singapore | C8: Deposit | D8: Salary | E8: CNY | F8: 10999.85 | G8: =F8*VLOOKUP(E8,{"USD",1;"EUR",1.08;"GBP",1.27;"JPY",0.0067;"CNY",0.14;"INR",0.012},2,FALSE) -> 1539.979
A9: New York | B9: USA | C9: Deposit | D9: Salary | E9: CNY | F9: 4276.34 | G9: =F9*VLOOKUP(E9,{"USD",1;"EUR",1.08;"GBP",1.27;"JPY",0.0067;"CNY",0.14;"INR",0.012},2,FALSE) -> 598.6876
A10: Frankfurt | B10: Germany | C10: Payment | D10: Insurance | E10: USD | F10: 3986.97 | G10: =F10*VLOOKUP(E10,{"USD",1;"EUR",1.08;"GBP",1.27;"JPY",0.0067;"CNY",0.14;"INR",0.012},2,FALSE) -> 3986.97
A11: Toronto | B11: Canada | C11: Payment | D11: Shopping | E11: USD | F11: 836 | G11: =F11*VLOOKUP(E11,{"USD",1;"EUR",1.08;"GBP",1.27;"JPY",0.0067;"CNY",0.14;"INR",0.012},2,FALSE) -> 836
A12: Toronto | B12: Canada | C12: Fee | D12: Other | E12: USD | F12: 600 | G12: =F12*VLOOKUP(E12,{"USD",1;"EUR",1.08;"GBP",1.27;"JPY",0.0067;"CNY",0.14;"INR",0.012},2,FALSE) -> 600
A13: Singapore | B13: Singapore | C13: Withdrawal | D13: Dining | E13: USD | F13: 1514.19 | G13: =F13*VLOOKUP(E13,{"USD",1;"EUR",1.08;"GBP",1.27;"JPY",0.0067;"CNY",0.14;"INR",0.012},2,FALSE) -> 1514.19
A14: Frankfurt | B14: Germany | C14: Transfer | D14: Other | E14: USD | F14: 1113.46 | G14: =F14*VLOOKUP(E14,{"USD",1;"EUR",1.08;"GBP",1.27;"JPY",0.0067;"CNY",0.14;"INR",0.012},2,FALSE) -> 1113.46
A15: Sydney | B15: Australia | C15: Deposit | D15: Investment | E15: CNY | F15: 6320.1 | G15: =F15*VLOOKUP(E15,{"USD",1;"EUR",1.08;"GBP",1.27;"JPY",0.0067;"CNY",0.14;"INR",0.012},2,FALSE) -> 884.814
A16: Frankfurt | B16: Germany | C16: Transfer | D16: Other | E16: USD | F16: 1597.27 | G16: =F16*VLOOKUP(E16,{"USD",1;"EUR",1.08;"GBP",1.27;"JPY",0.0067;"CNY",0.14;"INR",0.012},2,FALSE) -> 1597.27
... A20: Mumbai | B20: India | C20: Payment | D20: Other | E20: USD | F20: 3732.24 | G20: =F20*VLOOKUP(E20,{"USD",1;"EUR",1.08;"GBP",1.27;"JPY",0.0067;"CNY",0.14;"INR",0.012},2,FALSE) -> 3732.24

Sheet Sheet14
A1: Branch | B1: Country | C1: TransactionType | D1: Category | E1: Currency | F1: Amount | G1: AmountUSD
A2: London | B2: UK | C2: Withdrawal | D2: Dining | E2: EUR | F2: 955.8 | G2: =F2*VLOOKUP(E2,{"USD",1;"EUR",1.08;"GBP",1.27;"JPY",0.0067;"CNY",0.14;"INR",0.012},2,FALSE) -> 1032.264
A3: Tokyo | B3: Japan | C3: Fee | D3: Other | E3: USD | F3: 1200.41 | G3: =F3*VLOOKUP(E3,{"USD",1;"EUR",1.08;"GBP",1.27;"JPY",0.0067;"CNY",0.14;"INR",0.012},2,FALSE) -> 1200.41
A4: Toronto | B4: Canada | C4: Withdrawal | D4: Dining | E4: USD | F4: 1842.59 | G4: =F4*VLOOKUP(E4,{"USD",1;"EUR",1.08;"GBP",1.27;"JPY",0.0067;"CNY",0.14;"INR",0.012},2,FALSE) -> 1842.59
A5: New York | B5: USA | C5: Withdrawal | D5: Entertainment | E5: EUR | F5: 522.01 | G5: =F5*VLOOKUP(E5,{"USD",1;"EUR",1.08;"GBP",1.27;"JPY",0.0067;"CNY",0.14;"INR",0.012},2,FALSE) -> 563.7708
A6: New York | B6: USA | C6: Withdrawal | D6: Shopping | E6: USD | F6: 874.91 | G6: =F6*VLOOKUP(E6,{"USD",1;"EUR",1.08;"GBP",1.27;"JPY",0.0067;"CNY",0.14;"INR",0.012},2,FALSE) -> 874.91
A7: Sydney | B7: Australia | C7: Payment | D7: Education | E7: USD | F7: 4131.94 | G7: =F7*VLOOKUP(E7,{"USD",1;"EUR",1.08;"GBP",1.27;"JPY",0.0067;"CNY",0.14;"INR",0.012},2,FALSE) -> 4131.94
A8: Singapore | B8: Singapore | C8: Deposit | D8: Salary | E8: CNY | F8: 10999.85 | G8: =F8*VLOOKUP(E8,{"USD",1;"EUR",1.08;"GBP",1.27;"JPY",0.0067;"CNY",0.14;"INR",0.012},2,FALSE) -> 1539.979
A9: New York | B9: USA | C9: Deposit | D9: Salary | E9: CNY | F9: 4276.34 | G9: =F9*VLOOKUP(E9,{"USD",1;"EUR",1.08;"GBP",1.27;"JPY",0.0067;"CNY",0.14;"INR",0.012},2,FALSE) -> 598.6876
A10: Frankfurt | B10: Germany | C10: Payment | D10: Insurance | E10: USD | F10: 3986.97 | G10: =F10*VLOOKUP(E10,{"USD",1;"EUR",1.08;"GBP",1.27;"JPY",0.0067;"CNY",0.14;"INR",0.012},2,FALSE) -> 3986.97
A11: Toronto | B11: Canada | C11: Payment | D11: Shopping | E11: USD | F11: 836 | G11: =F11*VLOOKUP(E11,{"USD",1;"EUR",1.08;"GBP",1.27;"JPY",0.0067;"CNY",0.14;"INR",0.012},2,FALSE) -> 836
A12: Toronto | B12: Canada | C12: Fee | D12: Other | E12: USD | F12: 600 | G12: =F12*VLOOKUP(E12,{"USD",1;"EUR",1.08;"GBP",1.27;"JPY",0.0067;"CNY",0.14;"INR",0.012},2,FALSE) -> 600

Sheet Sheet3
A1: Branch | B1: Country | C1: TransactionType | D1: Category | E1: Currency | F1: Amount | G1: AmountUSD
A2: London | B2: UK | C2: Withdrawal | D2: Dining | E2: EUR | F2: 955.8 | G2: 1032.264 | H2: =F2*G2 -> 986637.93
A3: Tokyo | B3: Japan | C3: Fee | D3: Other | E3: USD | F3: 1200.41 | G3: 1200.41 | H3: =F3*G3 -> 1440984.2
A5: Toronto | B5: Canada | C5: Withdrawal | D5: Dining | E5: USD | F5: 1842.59 | G5: 1842.59 | H5: =F5*G5 -> 3395137.9
A6: New York | B6: USA | C6: Withdrawal | D6: Entertainment | E6: EUR | F6: 522.01 | G6: 563.7708 | H6: =F6*G6 -> 294294
A7: New York | B7: USA | C7: Withdrawal | D7: Shopping | E7: USD | F7: 874.91 | G7: 874.91 | H7: =F7*G7 -> 765467.51
A8: Sydney | B8: Australia | C8: Payment | D8: Education | E8: USD | F8: 4131.94 | G8: 4131.94 | H8: =F8*G8 -> 17072928
A9: Singapore | B9: Singapore | C9: Deposit | D9: Salary | E9: CNY | F9: 10999.85 | G9: 1539.979 | H9: =F9*G9 -> 16939538
A11: New York | B11: USA | C11: Deposit | D11: Salary | E11: CNY | F11: 4276.34 | G11: 598.6876 | H11: =F11*G11 -> 2560191.7
A12: Frankfurt | B12: Germany | C12: Payment | D12: Insurance | E12: USD | F12: 3986.97 | G12: 3986.97 | H12: =F12*G12 -> 15895930
A15: Toronto | B15: Canada | C15: Payment | D15: Shopping | E15: USD | F15: 836 | G15: 836 | H15: =F15*G15 -> 698896
A16: Toronto | B16: Canada | C16: Fee | D16: Other | E16: USD | F16: 600 | G16: 600 | H16: =F16*G16 -> 360000
A17: Singapore | B17: Singapore | C17: Withdrawal | D17: Dining | E17: USD | F17: 1514.19 | G17: 1514.19 | H17: =F17*G17 -> 2292771.4
... A25: Mumbai | B25: India | C25: Payment | D25: Other | E25: USD | F25: 3732.24 | G25: 3732.24 | H25: =F25*G25 -> 13929615

Sheet Sheet4
A1: Branch | B1: Country | C1: TransactionType | D1: Category | E1: Currency | F1: Amount | G1: AmountUSD
A2: London | B2: UK | C2: Withdrawal | D2: Dining | E2: EUR | F2: 955.8 | G2: 1032.264
A3: Tokyo | B3: Japan | C3: Fee | D3: Other | E3: USD | F3: 1200.41 | G3: 1200.41
A4: Toronto | B4: Canada | C4: Withdrawal | D4: Dining | E4: USD | F4: 1842.59 | G4: 1842.59
A5: New York | B5: USA | C5: Withdrawal | D5: Entertainment | E5: EUR | F5: 522.01 | G5: 563.7708
A6: New York | B6: USA | C6: Withdrawal | D6: Shopping | E6: USD | F6: 874.91 | G6: 874.91
A7: Sydney | B7: Australia | C7: Payment | D7: Education | E7: USD | F7: 4131.94 | G7: 4131.94
A8: Singapore | B8: Singapore | C8: Deposit | D8: Salary | E8: CNY | F8: 10999.85 | G8: 1539.979
A9: New York | B9: USA | C9: Deposit | D9: Salary | E9: CNY | F9: 4276.34 | G9: 598.6876
A10: Frankfurt | B10: Germany | C10: Payment | D10: Insurance | E10: USD | F10: 3986.97 | G10: 3986.97
A11: Toronto | B11: Canada | C11: Payment | D11: Shopping | E11: USD | F11: 836 | G11: 836
A12: Toronto | B12: Canada | C12: Fee | D12: Other | E12: USD | F12: 600 | G12: 600
A13: Singapore | B13: Singapore | C13: Withdrawal | D13: Dining | E13: USD | F13: 1514.19 | G13: 1514.19
... A20: Mumbai | B20: India | C20: Payment | D20: Other | E20: USD | F20: 3732.24 | G20: 3732.24

Sheet Sheet5
A1: Country | B1: Amount | C1: AmountUSD
A2: UK | B2: 2000 | C2: 1032.264
A3: Japan | B3: 1200.41 | C3: 4000
A4: Canada | B4: 1842.59 | C4: 1842.59
A5: USA | B5: 522.01 | C5: 563.7708
A6: USA | B6: 874.91 | C6: 874.91
A7: Australia | B7: 4131.94 | C7: 4131.94
A8: Singapore | B8: 10999.85 | C8: 1539.979
A9: USA | B9: 4276.34 | C9: 598.6876
A10: Germany | B10: 3986.97 | C10: 3986.97
A11: Canada | B11: 836 | C11: 836
B12: =SUM(B2:B11) -> 30671.02 | C12: =SUM(C2:C11) -> 19407.111

Sheet Sheet6
A1: Country | B1: Amount | C1: AmountUSD
A2: UK | B2: 955.8 | C2: 1032.264
A3: Japan | B3: 1200.41 | C3: 1200.41
A4: Canada | B4: 1842.59 | C4: 1842.59
A5: USA | B5: 522.01 | C5: 563.7708
A6: USA | B6: 874.91 | C6: 874.91
A7: Australia | B7: 4131.94 | C7: 4131.94
A8: Singapore | B8: 10999.85 | C8: 1539.979
A9: USA | B9: 4276.34 | C9: 598.6876
A10: Germany | B10: 3986.97 | C10: 3986.97
A11: Canada | B11: 836 | C11: 836
B12: =SUM(B2:B11) -> 29626.82 | C12: =SUM(C2:C11) -> 16607.521

Sheet Sheet7
A1: Country | B1: Amount | C1: AmountUSD
A2: UK | B2: 955.8 | C2: 1032.264
A3: Japan | B3: 1200.41 | C3: 1200.41
A4: Canada | B4: 1842.59 | C4: 1842.59
A5: USA | B5: 522.01 | C5: 563.7708
A6: USA | B6: 874.91 | C6: 874.91
A7: Australia | B7: 4131.94 | C7: 4131.94
A8: Singapore | B8: 10999.85 | C8: 1539.979
A9: USA | B9: 4276.34 | C9: 598.6876
A10: Germany | B10: 3986.97 | C10: 3986.97
A11: Canada | B11: 836 | C11: 836
B12: =SUM(B2:B11) -> 29626.82 | C12: =SUM(C2:C11) -> 16607.521

Sheet Sheet8
A1: Country | B1: Amount | C1: AmountUSD
A2: UK | B2: =SUM(Sheet5!B2,Sheet6!B2,Sheet7!B2) -> 3911.6 | C2: =SUM(Sheet5!C2,Sheet6!C2,Sheet7!C2) -> 3096.792
A3: Japan | B3: =SUM(Sheet5!B3,Sheet6!B3,Sheet7!B3) -> 3601.23 | C3: =SUM(Sheet5!C3,Sheet6!C3,Sheet7!C3) -> 6400.82
A4: Canada | B4: =SUM(Sheet5!B4,Sheet6!B4,Sheet7!B4) -> 5527.77 | C4: =SUM(Sheet5!C4,Sheet6!C4,Sheet7!C4) -> 5527.77
A5: USA | B5: =SUM(Sheet5!B5,Sheet6!B5,Sheet7!B5) -> 1566.03 | C5: =SUM(Sheet5!C5,Sheet6!C5,Sheet7!C5) -> 1691.3124
A6: USA | B6: =SUM(Sheet5!B6,Sheet6!B6,Sheet7!B6) -> 2624.73 | C6: =SUM(Sheet5!C6,Sheet6!C6,Sheet7!C6) -> 2624.73
A7: Australia | B7: =SUM(Sheet5!B7,Sheet6!B7,Sheet7!B7) -> 12395.82 | C7: =SUM(Sheet5!C7,Sheet6!C7,Sheet7!C7) -> 12395.82
A8: Singapore | B8: =SUM(Sheet5!B8,Sheet6!B8,Sheet7!B8) -> 32999.55 | C8: =SUM(Sheet5!C8,Sheet6!C8,Sheet7!C8) -> 4619.937
A9: USA | B9: =SUM(Sheet5!B9,Sheet6!B9,Sheet7!B9) -> 12829.02 | C9: =SUM(Sheet5!C9,Sheet6!C9,Sheet7!C9) -> 1796.0628
A10: Germany | B10: =SUM(Sheet5!B10,Sheet6!B10,Sheet7!B10) -> 11960.91 | C10: =SUM(Sheet5!C10,Sheet6!C10,Sheet7!C10) -> 11960.91
A11: Canada | B11: =SUM(Sheet5!B11,Sheet6!B11,Sheet7!B11) -> 2508 | C11: =SUM(Sheet5!C11,Sheet6!C11,Sheet7!C11) -> 2508
C13: =SUM(Sheet5:Sheet7!C12) -> 52622.154

Sheet Sheet9
D6: Country | E6: Amount | F6: AmountUSD
D7: UK | E7: 955.8 | F7: 1032.264
D8: Japan | E8: 1200.41 | F8: 1200.41
D9: Canada | E9: 1842.59 | F9: 1842.59
D10: USA | E10: 522.01 | F10: 563.7708
D11: USA | E11: 874.91 | F11: 874.91
D12: Australia | E12: 4131.94 | F12: 4131.94
D13: Singapore | E13: 10999.85 | F13: 1539.979
D14: USA | E14: 4276.34 | F14: 598.6876
D15: Germany | E15: 3986.97 | F15: 3986.97
D16: Canada | E16: 836 | F16: 836

Sheet Sheet10
N4: Country | O4: Amount | P4: AmountUSD
N5: UK | O5: 955.8 | P5: 1032.264
N6: Japan | O6: 1200.41 | P6: 1200.41
N7: Canada | O7: 1842.59 | P7: 1842.59
N8: USA | O8: 522.01 | P8: 563.7708
N9: USA | O9: 874.91 | P9: 874.91
N10: Australia | O10: 4131.94 | P10: 4131.94
N11: Singapore | O11: 10999.85 | P11: 1539.979
N12: USA | O12: 4276.34 | P12: 598.6876
N13: Germany | O13: 3986.97 | P13: 3986.97
N14: Canada | O14: 836 | P14: 836

Sheet Sheet11
C16: Country | D16: Amount | E16: AmountUSD
C17: UK | D17: 955.8 | E17: 1032.264
C18: Japan | D18: 1200.41 | E18: 1200.41
C19: Canada | D19: 1842.59 | E19: 1842.59
C20: USA | D20: 522.01 | E20: 563.7708
C21: USA | D21: 874.91 | E21: 874.91
C22: Australia | D22: 4131.94 | E22: 4131.94
C23: Singapore | D23: 10999.85 | E23: 1539.979
C24: USA | D24: 4276.34 | E24: 598.6876
C25: Germany | D25: 3986.97 | E25: 3986.97
C26: Canada | D26: 836 | E26: 836

Sheet Sheet13
A1: 955.8 | B1: 1032.264 | C1: =A1*B1 -> 986637.93 | E1: 986637.93
A2: 1200.41 | B2: 1200.41 | C2: =A2*B2 -> 1440984.2 | E2: 1440984.2
A3: 1842.59 | B3: 1842.59 | C3: =A3*B3 -> 3395137.9 | E3: 3395137.9
A4: 522.01 | B4: 563.7708 | C4: =A4*B4 -> 294294 | E4: 294294 | J4: 238645468723
A5: 874.91 | B5: 874.91 | C5: =A5*B5 -> 765467.51 | E5: 765467.51
A6: 4131.94 | B6: 4131.94 | C6: =A6*B6 -> 17072928 | E6: 17072928
A7: 10999.85 | B7: 1539.979 | C7: =A7*B7 -> 16939538 | E7: 16939538
A8: 4276.34 | B8: 598.6876 | C8: =A8*B8 -> 2560191.7 | E8: 2560191.7
A9: 3986.97 | B9: 3986.97 | C9: =A9*B9 -> 15895930 | E9: 15895930
A10: 836 | B10: 836 | C10: =A10*B10 -> 698896 | E10: 698896
A11: 600 | B11: 600 | C11: =A11*B11 -> 360000 | E11: 360000
A12: 1514.19 | B12: 1514.19 | C12: =A12*B12 -> 2292771.4 | E12: 2292771.4
A13: 1113.46 | B13: 1113.46 | C13: =A13*B13 -> 1239793.2 | E13: 1239793.2
A14: 6320.1 | B14: 884.814 | C14: =A14*B14 -> 5592113 | E14: 5592113
A15: 1597.27 | B15: 1597.27 | C15: =A15*B15 -> 2551271.5 | E15: 2551271.5
A16: 80002.33 | B16: 80002.33 | C16: =A16*B16 -> 6.4003728e+09 | E16: 6.4003728e+09
... A19: 3732.24 | B19: 3732.24 | C19: =A19*B19 -> 13929615 | E19: 13929615

Sheet Sheet12
E4: Amount | F4: AmountUSD
D5: Book1 | E5: =Sheet10!$O$5 -> 955.8 | F5: =Sheet10!$P$5 -> 1032.264
D6: Book1 | E6: =Sheet11!$D$17 -> 955.8 | F6: =Sheet11!$E$17 -> 1032.264
D7: Book1 | E7: =Sheet9!$E$7 -> 955.8 | F7: =Sheet9!$F$7 -> 1032.264
C8: UK | E8: =SUM(E5:E7) -> 2867.4 | F8: =SUM(F5:F7) -> 3096.792
D9: Book1 | E9: =Sheet10!$O$6 -> 1200.41 | F9: =Sheet10!$P$6 -> 1200.41
D10: Book1 | E10: =Sheet11!$D$18 -> 1200.41 | F10: =Sheet11!$E$18 -> 1200.41
D11: Book1 | E11: =Sheet9!$E$8 -> 1200.41 | F11: =Sheet9!$F$8 -> 1200.41
C12: Japan | E12: =SUM(E9:E11) -> 3601.23 | F12: =SUM(F9:F11) -> 3601.23
D13: Book1 | E13: =Sheet10!$O$7 -> 1842.59 | F13: =Sheet10!$P$7 -> 1842.59
E14: =Sheet10!$O$14 -> 836 | F14: =Sheet10!$P$14 -> 836
D15: Book1 | E15: =Sheet11!$D$19 -> 1842.59 | F15: =Sheet11!$E$19 -> 1842.59
E16: =Sheet11!$D$26 -> 836 | F16: =Sheet11!$E$26 -> 836
D17: Book1 | E17: =Sheet9!$E$9 -> 1842.59 | F17: =Sheet9!$F$9 -> 1842.59
E18: =Sheet9!$E$16 -> 836 | F18: =Sheet9!$F$16 -> 836
C19: Canada | E19: =SUM(E13:E18) -> 8035.77 | F19: =SUM(F13:F18) -> 8035.77
D20: Book1 | E20: =Sheet10!$O$8 -> 522.01 | F20: =Sheet10!$P$8 -> 563.7708
E21: =Sheet10!$O$9 -> 874.91 | F21: =Sheet10!$P$9 -> 874.91
E22: =Sheet10!$O$12 -> 4276.34 | F22: =Sheet10!$P$12 -> 598.6876
D23: Book1 | E23: =Sheet11!$D$20 -> 522.01 | F23: =Sheet11!$E$20 -> 563.7708
E24: =Sheet11!$D$21 -> 874.91 | F24: =Sheet11!$E$21 -> 874.91
E25: =Sheet11!$D$24 -> 4276.34 | F25: =Sheet11!$E$24 -> 598.6876
D26: Book1 | E26: =Sheet9!$E$10 -> 522.01 | F26: =Sheet9!$F$10 -> 563.7708
E27: =Sheet9!$E$11 -> 874.91 | F27: =Sheet9!$F$11 -> 874.91
E28: =Sheet9!$E$14 -> 4276.34 | F28: =Sheet9!$F$14 -> 598.6876
C29: USA | E29: =SUM(E20:E28) -> 17019.78 | F29: =SUM(F20:F28) -> 6112.1052
D30: Book1 | E30: =Sheet10!$O$10 -> 4131.94 | F30: =Sheet10!$P$10 -> 4131.94
D31: Book1 | E31: =Sheet11!$D$22 -> 4131.94 | F31: =Sheet11!$E$22 -> 4131.94
D32: Book1 | E32: =Sheet9!$E$12 -> 4131.94 | F32: =Sheet9!$F$12 -> 4131.94
C33: Australia | E33: =SUM(E30:E32) -> 12395.82 | F33: =SUM(F30:F32) -> 12395.82
D34: Book1 | E34: =Sheet10!$O$11 -> 10999.85 | F34: =Sheet10!$P$11 -> 1539.979
D35: Book1 | E35: =Sheet11!$D$23 -> 10999.85 | F35: =Sheet11!$E$23 -> 1539.979
D36: Book1 | E36: =Sheet9!$E$13 -> 10999.85 | F36: =Sheet9!$F$13 -> 1539.979
C37: Singapore | E37: =SUM(E34:E36) -> 32999.55 | F37: =SUM(F34:F36) -> 4619.937
D38: Book1 | E38: =Sheet10!$O$13 -> 3986.97 | F38: =Sheet10!$P$13 -> 3986.97
D39: Book1 | E39: =Sheet11!$D$25 -> 3986.97 | F39: =Sheet11!$E$25 -> 3986.97
D40: Book1 | E40: =Sheet9!$E$15 -> 3986.97 | F40: =Sheet9!$F$15 -> 3986.97
C41: Germany | E41: =SUM(E38:E40) -> 11960.91 | F41: =SUM(F38:F40) -> 11960.91
