Workbook

Sheet Sheet1
A1: TransactionID | B1: TransactionDate | C1: AccountID | D1: CustomerID | E1: CustomerName | F1: Branch | G1: Country | H1: TransactionType | I1: Category | J1: Currency | K1: Amount | L1: AmountUSD | M1: Balance
A2: TXN0000001 | B2: 2022-08-01 | C2: ACC100253 | D2: CUST10125 | E2: Aisha Singh | F2: London | G2: UK | H2: Withdrawal | I2: Dining | J2: EUR | K2: 955.8 | L2: =K2*VLOOKUP(J2,{"USD",1;"EUR",1.08;"GBP",1.27;"JPY",0.0067;"CNY",0.14;"INR",0.012},2,FALSE) -> 1032.264 | M2: 240457.01
A3: TXN0000002 | B3: 2022-07-14 | C3: ACC100275 | D3: CUST10137 | E3: David Mueller | F3: Tokyo | G3: Japan | H3: Fee | I3: Other | J3: USD | K3: 12.41 | L3: =K3*VLOOKUP(J3,{"USD",1;"EUR",1.08;"GBP",1.27;"JPY",0.0067;"CNY",0.14;"INR",0.012},2,FALSE) -> 12.41 | M3: 109657.63
A4: TXN0000003 | B4: 2024-01-23 | C4: ACC100012 | D4: CUST10006 | E4: Mohammed Sato | F4: Toronto | G4: Canada | H4: Withdrawal | I4: Dining | J4: USD | K4: 1842.59 | L4: =K4*VLOOKUP(J4,{"USD",1;"EUR",1.08;"GBP",1.27;"JPY",0.0067;"CNY",0.14;"INR",0.012},2,FALSE) -> 1842.59 | M4: 438961.01
A5: TXN0000004 | B5: 2023-06-17 | C5: ACC100307 | D5: CUST10152 | E5: Richard Harris | F5: New York | G5: USA | H5: Withdrawal | I5: Entertainment | J5: EUR | K5: 522.01 | L5: =K5*VLOOKUP(J5,{"USD",1;"EUR",1.08;"GBP",1.27;"JPY",0.0067;"CNY",0.14;"INR",0.012},2,FALSE) -> 563.7708 | M5: 245250.85
A6: TXN0000005 | B6: 2024-03-30 | C6: ACC100160 | D6: CUST10076 | E6: Susan Miller | F6: New York | G6: USA | H6: Withdrawal | I6: Shopping | J6: USD | K6: 874.91 | L6: =K6*VLOOKUP(J6,{"USD",1;"EUR",1.08;"GBP",1.27;"JPY",0.0067;"CNY",0.14;"INR",0.012},2,FALSE) -> 874.91 | M6: 412084.25
A7: TXN0000006 | B7: 2024-07-25 | C7: ACC100204 | D7: CUST10099 | E7: Kenji Sato | F7: Sydney | G7: Australia | H7: Payment | I7: Education | J7: USD | K7: 4131.94 | L7: =K7*VLOOKUP(J7,{"USD",1;"EUR",1.08;"GBP",1.27;"JPY",0.0067;"CNY",0.14;"INR",0.012},2,FALSE) -> 4131.94 | M7: 311006.01
A8: TXN0000007 | B8: 2025-07-02 | C8: ACC100094 | D8: CUST10045 | E8: Joseph Wilson | F8: Singapore | G8: Singapore | H8: Deposit | I8: Salary | J8: CNY | K8: 10999.85 | L8: =K8*VLOOKUP(J8,{"USD",1;"EUR",1.08;"GBP",1.27;"JPY",0.0067;"CNY",0.14;"INR",0.012},2,FALSE) -> 1539.979 | M8: 241947.91
A9: TXN0000008 | B9: 2025-09-25 | C9: ACC100367 | D9: CUST10178 | E9: Charles Park | F9: New York | G9: USA | H9: Deposit | I9: Salary | J9: CNY | K9: 4276.34 | L9: =K9*VLOOKUP(J9,{"USD",1;"EUR",1.08;"GBP",1.27;"JPY",0.0067;"CNY",0.14;"INR",0.012},2,FALSE) -> 598.6876 | M9: 53409.85
A10: TXN0000009 | B10: 2024-05-29 | C10: ACC100169 | D10: CUST10080 | E10: Wei White | F10: Frankfurt | G10: Germany | H10: Payment | I10: Insurance | J10: USD | K10: 3986.97 | L10: =K10*VLOOKUP(J10,{"USD",1;"EUR",1.08;"GBP",1.27;"JPY",0.0067;"CNY",0.14;"INR",0.012},2,FALSE) -> 3986.97 | M10: 365856.11
A11: TXN0000010 | B11: 2022-05-22 | C11: ACC100465 | D11: CUST10226 | E11: David Wilson | F11: Toronto | G11: Canada | H11: Payment | I11: Shopping | J11: USD | K11: 836 | L11: =K11*VLOOKUP(J11,{"USD",1;"EUR",1.08;"GBP",1.27;"JPY",0.0067;"CNY",0.14;"INR",0.012},2,FALSE) -> 836 | M11: 27106.88
A12: TXN0000011 | B12: 2024-11-29 | C12: ACC100370 | D12: CUST10179 | E12: Michael Lopez | F12: Toronto | G12: Canada | H12: Fee | I12: Other | J12: USD | K12: 24.12 | L12: =K12*VLOOKUP(J12,{"USD",1;"EUR",1.08;"GBP",1.27;"JPY",0.0067;"CNY",0.14;"INR",0.012},2,FALSE) -> 24.12 | M12: 188024.67
A13: TXN0000012 | B13: 2025-12-30 | C13: ACC100359 | D13: CUST10175 | E13: Deepa Mueller | F13: Singapore | G13: Singapore | H13: Withdrawal | I13: Dining | J13: USD | K13: 1514.19 | L13: =K13*VLOOKUP(J13,{"USD",1;"EUR",1.08;"GBP",1.27;"JPY",0.0067;"CNY",0.14;"INR",0.012},2,FALSE) -> 1514.19 | M13: 58401.69
... A10001: TXN0010000 | B10001: 2025-03-03 | C10001: ACC100355 | D10001: CUST10174 | E10001: Mary Harris | F10001: Hong Kong | G10001: China | H10001: Payment | I10001: Healthcare | J10001: EUR | K10001: 4739.34 | L10001: =K10001*VLOOKUP(J10001,{"USD",1;"EUR",1.08;"GBP",1.27;"JPY",0.0067;"CNY",0.14;"INR",0.012},2,FALSE) -> 5118.4872 | M10001: 460942.91

Sheet Sheet2
B1: TransactionID | C1: TransactionDate | D1: AccountID | E1: CustomerID | F1: CustomerName | G1: Branch | H1: Country | I1: TransactionType | J1: Category | K1: Currency | L1: Amount | M1: AmountUSD | N1: Balance
B2: TXN00000012 | C2: =C5=VLOOKUP($B$2,Sheet1!$A$2:$M$10001,2,0) -> #N/A | D2: =VLOOKUP($B$2,Sheet1!$A$2:$M$10001,3,0) -> #N/A | E2: =VLOOKUP($B$2,Sheet1!$A$2:$M$10001,4,0) -> #N/A | F2: =VLOOKUP($B$2,Sheet1!$A$2:$M$10001,5,0) -> #N/A | G2: =VLOOKUP($B$2,Sheet1!$A$2:$M$10001,6,0) -> #N/A | H2: =VLOOKUP($B$2,Sheet1!$A$2:$M$10001,7,0) -> #N/A | I2: =VLOOKUP($B$2,Sheet1!$A$2:$M$10001,8,0) -> #N/A | J2: =VLOOKUP($B$2,Sheet1!$A$2:$M$10001,9,0) -> #N/A | K2: =VLOOKUP($B$2,Sheet1!$A$2:$M$10001,10,0) -> #N/A | L2: =VLOOKUP($B$2,Sheet1!$A$2:$M$10001,11,0) -> #N/A | M2: =VLOOKUP($B$2,Sheet1!$A$2:$M$10001,12,0) -> #N/A | N2: =VLOOKUP($B$2,Sheet1!$A$2:$M$10001,13,0) -> #N/A
B8: TXN0000001 | C8: =IFERROR(VLOOKUP($B$8,Sheet1!$A$2:$M$10001,2,0),"not found") -> 2022-08-01

Sheet Sheet3
A1: TransactionID | B1: TXN0000001 | C1: TXN0000002 | D1: TXN0000003 | E1: TXN0000004 | F1: TXN0000005 | G1: TXN0000006 | H1: TXN0000007 | I1: TXN0000008 | J1: TXN0000009 | K1: TXN0000010 | L1: TXN0000011 | M1: TXN0000012 | N1: TXN0000013 | O1: TXN0000014 | P1: TXN0000015 | Q1: TXN0000016 | R1: TXN0000017 | S1: TXN0000018 | T1: TXN0000019 | U1: TXN0000020 | V1: TXN0000021 | W1: TXN0000022 | X1: TXN0000023 | Y1: TXN0000024 | Z1: TXN0000025 | AA1: TXN0000026 | AB1: TXN0000027 | AC1: TXN0000028 | AD1: TXN0000029 | AE1: TXN0000030 | AF1: TXN0000031 | AG1: TXN0000032 | AH1: TXN0000033 | AI1: TXN0000034 | AJ1: TXN0000035 | AK1: TXN0000036 | AL1: TXN0000037 | AM1: TXN0000038 | AN1: TXN0000039 | AO1: TXN0000040 | AP1: TXN0000041 | AQ1: TXN0000042 | AR1: TXN0000043 | AS1: TXN0000044 | AT1: TXN0000045 | AU1: TXN0000046 | AV1: TXN0000047 | AW1: TXN0000048 | AX1: TXN0000049 | AY1: TXN0000050 | AZ1: TXN0000051 | BA1: TXN0000052 | BB1: TXN0000053 | BC1: TXN0000054 | BD1: TXN0000055 | BE1: TXN0000056 | BF1: TXN0000057 | BG1: TXN0000058 | BH1: TXN0000059 | BI1: TXN0000060 | BJ1: TXN0000061 | BK1: TXN0000062 | BL1: TXN0000063 | BM1: TXN0000064 | BN1: TXN0000065 | BO1: TXN0000066 | BP1: TXN0000067 | BQ1: TXN0000068 | BR1: TXN0000069 | BS1: TXN0000070 | BT1: TXN0000071 | BU1: TXN0000072 | BV1: TXN0000073 | BW1: TXN0000074 | BX1: TXN0000075 | BY1: TXN0000076 | BZ1: TXN0000077 | CA1: TXN0000078 | CB1: TXN0000079 | CC1: TXN0000080 | CD1: TXN0000081 | CE1: TXN0000082 | CF1: TXN0000083 | CG1: TXN0000084 | CH1: TXN0000085 | CI1: TXN0000086 | CJ1: TXN0000087 | CK1: TXN0000088 | CL1: TXN0000089 | CM1: TXN0000090 | CN1: TXN0000091 | CO1: TXN0000092 | CP1: TXN0000093 | CQ1: TXN0000094 | CR1: TXN0000095 | CS1: TXN0000096 | CT1: TXN0000097 | CU1: TXN0000098 | CV1: TXN0000099 | CW1: TXN0000100 | CX1: TXN0000101 | CY1: TXN0000102 | CZ1: TXN0000103 | DA1: TXN0000104 | DB1: TXN0000105 | DC1: TXN0000106 | DD1: TXN0000107 | DE1: TXN0000108 | DF1: TXN0000109 | DG1: TXN0000110 | DH1: TXN0000111 | DI1: TXN0000112 | DJ1: TXN0000113 | DK1: TXN0000114 | DL1: TXN0000115 | DM1: TXN0000116 | DN1: TXN0000117 | DO1: TXN0000118 | DP1: TXN0000119 | DQ1: TXN0000120 | DR1: TXN0000121 | DS1: TXN0000122 | DT1: TXN0000123 | DU1: TXN0000124 | DV1: TXN0000125 | DW1: TXN0000126 | DX1: TXN0000127 | DY1: TXN0000128 | DZ1: TXN0000129 | EA1: TXN0000130 | EB1: TXN0000131 | EC1: TXN0000132 | ED1: TXN0000133 | EE1: TXN0000134 | EF1: TXN0000135 | EG1: TXN0000136 | EH1: TXN0000137 | EI1: TXN0000138 | EJ1: TXN0000139 | EK1: TXN0000140 | EL1: TXN0000141 | EM1: TXN0000142 | EN1: TXN0000143 | EO1: TXN0000144 | EP1: TXN0000145 | EQ1: TXN0000146 | ER1: TXN0000147 | ES1: TXN0000148 | ET1: TXN0000149 | EU1: TXN0000150 | EV1: TXN0000151 | EW1: TXN0000152 | EX1: TXN0000153 | EY1: TXN0000154 | EZ1: TXN0000155 | FA1: TXN0000156 | FB1: TXN0000157 | FC1: TXN0000158 | FD1: TXN0000159 | FE1: TXN0000160 | FF1: TXN0000161 | FG1: TXN0000162 | FH1: TXN0000163 | FI1: TXN0000164 | FJ1: TXN0000165 | FK1: TXN0000166 | FL1: TXN0000167 | FM1: TXN0000168 | FN1: TXN0000169 | FO1: TXN0000170 | FP1: TXN0000171 | FQ1: TXN0000172 | FR1: TXN0000173 | FS1: TXN0000174 | FT1: TXN0000175 | FU1: TXN0000176 | FV1: TXN0000177 | FW1: TXN0000178 | FX1: TXN0000179 | FY1: TXN0000180 | FZ1: TXN0000181 | GA1: TXN0000182 | GB1: TXN0000183 | GC1: TXN0000184 | GD1: TXN0000185 | GE1: TXN0000186 | GF1: TXN0000187 | GG1: TXN0000188 | GH1: TXN0000189 | GI1: TXN0000190 | GJ1: TXN0000191 | GK1: TXN0000192 | GL1: TXN0000193 | GM1: TXN0000194 | GN1: TXN0000195 | GO1: TXN0000196 | GP1: TXN0000197 | GQ1: TXN0000198 | GR1: TXN0000199 | GS1: TXN0000200 | GT1: TXN0000201 | GU1: TXN0000202 | GV1: TXN0000203 | GW1: TXN0000204 | GX1: TXN0000205 | GY1: TXN0000206 | GZ1: TXN0000207 | HA1: TXN0000208 | HB1: TXN0000209 | HC1: TXN0000210 | HD1: TXN0000211 | HE1: TXN0000212 | HF1: TXN0000213 | HG1: TXN0000214 | HH1: TXN0000215 | HI1: TXN0000216 | HJ1: TXN0000217 | HK1: TXN0000218 | HL1: TXN0000219 | HM1: TXN0000220 | HN1: TXN0000221 | HO1: TXN0000222 | HP1: TXN0000223 | HQ1: TXN0000224 | HR1: TXN0000225 | HS1: TXN0000226 | HT1: TXN0000227 | HU1: TXN0000228 | HV1: TXN0000229 | HW1: TXN0000230 | HX1: TXN0000231 | HY1: TXN0000232 | HZ1: TXN0000233 | IA1: TXN0000234 | IB1: TXN0000235 | IC1: TXN0000236 | ID1: TXN0000237 | IE1: TXN0000238 | IF1: TXN0000239 | IG1: TXN0000240 | IH1: TXN0000241 | II1: TXN0000242 | IJ1: TXN0000243 | IK1: TXN0000244 | IL1: TXN0000245 | IM1: TXN0000246 | IN1: TXN0000247 | IO1: TXN0000248 | IP1: TXN0000249 | IQ1: TXN0000250 | IR1: TXN0000251 | IS1: TXN0000252 | IT1: TXN0000253 | IU1: TXN0000254 | IV1: TXN0000255 | IW1: TXN0000256 | IX1: TXN0000257 | IY1: TXN0000258 | IZ1: TXN0000259 | JA1: TXN0000260 | JB1: TXN0000261 | JC1: TXN0000262 | JD1: TXN0000263 | JE1: TXN0000264 | JF1: TXN0000265 | JG1: TXN0000266 | JH1: TXN0000267 | JI1: TXN0000268 | JJ1: TXN0000269 | JK1: TXN0000270 | JL1: TXN0000271 | JM1: TXN0000272 | JN1: TXN0000273 | JO1: TXN0000274 | JP1: TXN0000275 | JQ1: TXN0000276 | JR1: TXN0000277 | JS1: TXN0000278 | JT1: TXN0000279 | JU1: TXN0000280 | JV1: TXN0000281 | JW1: TXN0000282 | JX1: TXN0000283 | JY1: TXN0000284 | JZ1: TXN0000285 | KA1: TXN0000286 | KB1: TXN0000287 | KC1: TXN0000288 | KD1: TXN0000289 | KE1: TXN0000290 | KF1: TXN0000291 | KG1: TXN0000292 | KH1: TXN0000293 | KI1: TXN0000294 | KJ1: TXN0000295 | KK1: TXN0000296 | KL1: TXN0000297 | KM1: TXN0000298 | KN1: TXN0000299 | KO1: TXN0000300 | KP1: TXN0000301 | KQ1: TXN0000302 | KR1: TXN0000303 | KS1: TXN0000304 | KT1: TXN0000305 | KU1: TXN0000306 | KV1: TXN0000307 | KW1: TXN0000308 | KX1: TXN0000309 | KY1: TXN0000310 | KZ1: TXN0000311 | LA1: TXN0000312 | LB1: TXN0000313 | LC1: TXN0000314 | LD1: TXN0000315 | LE1: TXN0000316 | LF1: TXN0000317 | LG1: TXN0000318 | LH1: TXN0000319 | LI1: TXN0000320 | LJ1: TXN0000321 | LK1: TXN0000322 | LL1: TXN0000323 | LM1: TXN0000324 | LN1: TXN0000325 | LO1: TXN0000326 | LP1: TXN0000327 | LQ1: TXN0000328 | LR1: TXN0000329 | LS1: TXN0000330 | LT1: TXN0000331 | LU1: TXN0000332 | LV1: TXN0000333 | LW1: TXN0000334 | LX1: TXN0000335 | LY1: TXN0000336 | LZ1: TXN0000337 | MA1: TXN0000338 | MB1: TXN0000339 | MC1: TXN0000340 | MD1: TXN0000341 | ME1: TXN0000342 | MF1: TXN0000343 | MG1: TXN0000344 | MH1: TXN0000345 | MI1: TXN0000346 | MJ1: TXN0000347 | MK1: TXN0000348 | ML1: TXN0000349 | MM1: TXN0000350 | MN1: TXN0000351 | MO1: TXN0000352 | MP1: TXN0000353 | MQ1: TXN0000354 | MR1: TXN0000355 | MS1: TXN0000356 | MT1: TXN0000357 | MU1: TXN0000358 | MV1: TXN0000359 | MW1: TXN0000360 | MX1: TXN0000361 | MY1: TXN0000362 | MZ1: TXN0000363 | NA1: TXN0000364 | NB1: TXN0000365 | NC1: TXN0000366 | ND1: TXN0000367 | NE1: TXN0000368 | NF1: TXN0000369 | NG1: TXN0000370 | NH1: TXN0000371 | NI1: TXN0000372 | NJ1: TXN0000373 | NK1: TXN0000374 | NL1: TXN0000375 | NM1: TXN0000376 | NN1: TXN0000377 | NO1: TXN0000378 | NP1: TXN0000379 | NQ1: TXN0000380 | NR1: TXN0000381 | NS1: TXN0000382 | NT1: TXN0000383 | NU1: TXN0000384 | NV1: TXN0000385 | NW1: TXN0000386 | NX1: TXN0000387 | NY1: TXN0000388 | NZ1: TXN0000389 | OA1: TXN0000390 | OB1: TXN0000391 | OC1: TXN0000392 | OD1: TXN0000393 | OE1: TXN0000394 | OF1: TXN0000395 | OG1: TXN0000396 | OH1: TXN0000397 | OI1: TXN0000398 | OJ1: TXN0000399 | OK1: TXN0000400 | OL1: TXN0000401 | OM1: TXN0000402 | ON1: TXN0000403 | OO1: TXN0000404 | OP1: TXN0000405 | OQ1: TXN0000406 | OR1: TXN0000407 | OS1: TXN0000408 | OT1: TXN0000409 | OU1: TXN0000410 | OV1: TXN0000411 | OW1: TXN0000412 | OX1: TXN0000413 | OY1: TXN0000414 | OZ1: TXN0000415 | PA1: TXN0000416 | PB1: TXN0000417 | PC1: TXN0000418 | PD1: TXN0000419 | PE1: TXN0000420 | PF1: TXN0000421 | PG1: TXN0000422 | PH1: TXN0000423 | PI1: TXN0000424 | PJ1: TXN0000425 | PK1: TXN0000426 | PL1: TXN0000427 | PM1: TXN0000428 | PN1: TXN0000429 | PO1: TXN0000430 | PP1: TXN0000431 | PQ1: TXN0000432 | PR1: TXN0000433 | PS1: TXN0000434 | PT1: TXN0000435 | PU1: TXN0000436 | PV1: TXN0000437 | PW1: TXN0000438 | PX1: TXN0000439 | PY1: TXN0000440 | PZ1: TXN0000441 | QA1: TXN0000442 | QB1: TXN0000443 | QC1: TXN0000444 | QD1: TXN0000445 | QE1: TXN0000446 | QF1: TXN0000447 | QG1: TXN0000448 | QH1: TXN0000449 | QI1: TXN0000450 | QJ1: TXN0000451 | QK1: TXN0000452 | QL1: TXN0000453 | QM1: TXN0000454 | QN1: TXN0000455 | QO1: TXN0000456 | QP1: TXN0000457 | QQ1: TXN0000458 | QR1: TXN0000459 | QS1: TXN0000460 | QT1: TXN0000461 | QU1: TXN0000462 | QV1: TXN0000463 | QW1: TXN0000464 | QX1: TXN0000465 | QY1: TXN0000466 | QZ1: TXN0000467 | RA1: TXN0000468 | RB1: TXN0000469 | RC1: TXN0000470 | RD1: TXN0000471 | RE1: TXN0000472 | RF1: TXN0000473 | RG1: TXN0000474 | RH1: TXN0000475 | RI1: TXN0000476 | RJ1: TXN0000477 | RK1: TXN0000478 | RL1: TXN0000479 | RM1: TXN0000480 | RN1: TXN0000481 | RO1: TXN0000482 | RP1: TXN0000483 | RQ1: TXN0000484 | RR1: TXN0000485 | RS1: TXN0000486 | RT1: TXN0000487 | RU1: TXN0000488 | RV1: TXN0000489 | RW1: TXN0000490 | RX1: TXN0000491 | RY1: TXN0000492 | RZ1: TXN0000493 | SA1: TXN0000494 | SB1: TXN0000495 | SC1: TXN0000496 | SD1: TXN0000497 | SE1: TXN0000498 | SF1: TXN0000499 | SG1: TXN0000500 | SH1: TXN0000501 | SI1: TXN0000502 | SJ1: TXN0000503 | SK1: TXN0000504 | SL1: TXN0000505 | SM1: TXN0000506 | SN1: TXN0000507 | SO1: TXN0000508 | SP1: TXN0000509 | SQ1: TXN0000510 | SR1: TXN0000511 | SS1: TXN0000512 | ST1: TXN0000513 | SU1: TXN0000514 | SV1: TXN0000515 | SW1: TXN0000516 | SX1: TXN0000517 | SY1: TXN0000518 | SZ1: TXN0000519 | TA1: TXN0000520 | TB1: TXN0000521 | TC1: TXN0000522 | TD1: TXN0000523 | TE1: TXN0000524 | TF1: TXN0000525 | TG1: TXN0000526 | TH1: TXN0000527 | TI1: TXN0000528 | TJ1: TXN0000529 | TK1: TXN0000530 | TL1: TXN0000531 | TM1: TXN0000532 | TN1: TXN0000533 | TO1: TXN0000534 | TP1: TXN0000535 | TQ1: TXN0000536 | TR1: TXN0000537 | TS1: TXN0000538 | TT1: TXN0000539 | TU1: TXN0000540 | TV1: TXN0000541 | TW1: TXN0000542 | TX1: TXN0000543 | TY1: TXN0000544 | TZ1: TXN0000545 | UA1: TXN0000546 | UB1: TXN0000547 | UC1: TXN0000548 | UD1: TXN0000549 | UE1: TXN0000550 | UF1: TXN0000551 | UG1: TXN0000552 | UH1: TXN0000553 | UI1: TXN0000554 | UJ1: TXN0000555 | UK1: TXN0000556 | UL1: TXN0000557 | UM1: TXN0000558 | UN1: TXN0000559 | UO1: TXN0000560 | UP1: TXN0000561 | UQ1: TXN0000562 | UR1: TXN0000563 | US1: TXN0000564 | UT1: TXN0000565 | UU1: TXN0000566 | UV1: TXN0000567 | UW1: TXN0000568 | UX1: TXN0000569 | UY1: TXN0000570 | UZ1: TXN0000571 | VA1: TXN0000572 | VB1: TXN0000573 | VC1: TXN0000574 | VD1: TXN0000575 | VE1: TXN0000576 | VF1: TXN0000577 | VG1: TXN0000578 | VH1: TXN0000579 | VI1: TXN0000580 | VJ1: TXN0000581 | VK1: TXN0000582 | VL1: TXN0000583 | VM1: TXN0000584 | VN1: TXN0000585 | VO1: TXN0000586 | VP1: TXN0000587 | VQ1: TXN0000588 | VR1: TXN0000589 | VS1: TXN0000590 | VT1: TXN0000591 | VU1: TXN0000592 | VV1: TXN0000593 | VW1: TXN0000594 | VX1: TXN0000595 | VY1: TXN0000596 | VZ1: TXN0000597 | WA1: TXN0000598 | WB1: TXN0000599 | WC1: TXN0000600 | WD1: TXN0000601 | WE1: TXN0000602 | WF1: TXN0000603 | WG1: TXN0000604 | WH1: TXN0000605 | WI1: TXN0000606 | WJ1: TXN0000607 | WK1: TXN0000608 | WL1: TXN0000609 | WM1: TXN0000610 | WN1: TXN0000611 | WO1: TXN0000612 | WP1: TXN0000613 | WQ1: TXN0000614 | WR1: TXN0000615 | WS1: TXN0000616 | WT1: TXN0000617 | WU1: TXN0000618 | WV1: TXN0000619 | WW1: TXN0000620 | WX1: TXN0000621 | WY1: TXN0000622 | WZ1: TXN0000623 | XA1: TXN0000624 | XB1: TXN0000625 | XC1: TXN0000626 | XD1: TXN0000627 | XE1: TXN0000628 | XF1: TXN0000629 | XG1: TXN0000630 | XH1: TXN0000631 | XI1: TXN0000632 | XJ1: TXN0000633 | XK1: TXN0000634 | XL1: TXN0000635 | XM1: TXN0000636 | XN1: TXN0000637 | XO1: TXN0000638 | XP1: TXN0000639 | XQ1: TXN0000640 | XR1: TXN0000641 | XS1: TXN0000642 | XT1: TXN0000643 | XU1: TXN0000644 | XV1: TXN0000645 | XW1: TXN0000646 | XX1: TXN0000647 | XY1: TXN0000648 | XZ1: TXN0000649 | YA1: TXN0000650 | YB1: TXN0000651 | YC1: TXN0000652 | YD1: TXN0000653 | YE1: TXN0000654 | YF1: TXN0000655 | YG1: TXN0000656 | YH1: TXN0000657 | YI1: TXN0000658 | YJ1: TXN0000659 | YK1: TXN0000660 | YL1: TXN0000661 | YM1: TXN0000662 | YN1: TXN0000663 | YO1: TXN0000664 | YP1: TXN0000665 | YQ1: TXN0000666 | YR1: TXN0000667 | YS1: TXN0000668 | YT1: TXN0000669 | YU1: TXN0000670 | YV1: TXN0000671 | YW1: TXN0000672 | YX1: TXN0000673 | YY1: TXN0000674 | YZ1: TXN0000675 | ZA1: TXN0000676 | ZB1: TXN0000677 | ZC1: TXN0000678 | ZD1: TXN0000679 | ZE1: TXN0000680 | ZF1: TXN0000681 | ZG1: TXN0000682 | ZH1: TXN0000683 | ZI1: TXN0000684 | ZJ1: TXN0000685 | ZK1: TXN0000686 | ZL1: TXN0000687 | ZM1: TXN0000688 | ZN1: TXN0000689 | ZO1: TXN0000690 | ZP1: TXN0000691 | ZQ1: TXN0000692 | ZR1: TXN0000693 | ZS1: TXN0000694 | ZT1: TXN0000695 | ZU1: TXN0000696 | ZV1: TXN0000697 | ZW1: TXN0000698 | ZX1: TXN0000699 | ZY1: TXN0000700 | ZZ1: TXN0000701 | AAA1: TXN0000702 | AAB1: TXN0000703 | AAC1: TXN0000704 | AAD1: TXN0000705 | AAE1: TXN0000706 | AAF1: TXN0000707 | AAG1: TXN0000708 | AAH1: TXN0000709 | AAI1: TXN0000710 | AAJ1: TXN0000711 | AAK1: TXN0000712 | AAL1: TXN0000713 | AAM1: TXN0000714 | AAN1: TXN0000715 | AAO1: TXN0000716 | AAP1: TXN0000717 | AAQ1: TXN0000718 | AAR1: TXN0000719 | AAS1: TXN0000720 | AAT1: TXN0000721 | AAU1: TXN0000722 | AAV1: TXN0000723 | AAW1: TXN0000724 | AAX1: TXN0000725 | AAY1: TXN0000726 | AAZ1: TXN0000727 | ABA1: TXN0000728 | ABB1: TXN0000729 | ABC1: TXN0000730 | ABD1: TXN0000731 | ABE1: TXN0000732 | ABF1: TXN0000733 | ABG1: TXN0000734 | ABH1: TXN0000735 | ABI1: TXN0000736 | ABJ1: TXN0000737 | ABK1: TXN0000738 | ABL1: TXN0000739 | ABM1: TXN0000740 | ABN1: TXN0000741 | ABO1: TXN0000742 | ABP1: TXN0000743 | ABQ1: TXN0000744 | ABR1: TXN0000745 | ABS1: TXN0000746 | ABT1: TXN0000747 | ABU1: TXN0000748 | ABV1: TXN0000749 | ABW1: TXN0000750 | ABX1: TXN0000751 | ABY1: TXN0000752 | ABZ1: TXN0000753 | ACA1: TXN0000754 | ACB1: TXN0000755 | ACC1: TXN0000756 | ACD1: TXN0000757 | ACE1: TXN0000758 | ACF1: TXN0000759 | ACG1: TXN0000760 | ACH1: TXN0000761 | ACI1: TXN0000762 | ACJ1: TXN0000763 | ACK1: TXN0000764 | ACL1: TXN0000765 | ACM1: TXN0000766 | ACN1: TXN0000767 | ACO1: TXN0000768 | ACP1: TXN0000769 | ACQ1: TXN0000770 | ACR1: TXN0000771 | ACS1: TXN0000772 | ACT1: TXN0000773 | ACU1: TXN0000774 | ACV1: TXN0000775 | ACW1: TXN0000776 | ACX1: TXN0000777 | ACY1: TXN0000778 | ACZ1: TXN0000779 | ADA1: TXN0000780 | ADB1: TXN0000781 | ADC1: TXN0000782 | ADD1: TXN0000783 | ADE1: TXN0000784 | ADF1: TXN0000785 | ADG1: TXN0000786 | ADH1: TXN0000787 | ADI1: TXN0000788 | ADJ1: TXN0000789 | ADK1: TXN0000790 | ADL1: TXN0000791 | ADM1: TXN0000792 | ADN1: TXN0000793 | ADO1: TXN0000794 | ADP1: TXN0000795 | ADQ1: TXN0000796 | ADR1: TXN0000797 | ADS1: TXN0000798 | ADT1: TXN0000799 | ADU1: TXN0000800 | ADV1: TXN0000801 | ADW1: TXN0000802 | ADX1: TXN0000803 | ADY1: TXN0000804 | ADZ1: TXN0000805 | AEA1: TXN0000806 | AEB1: TXN0000807 | AEC1: TXN0000808 | AED1: TXN0000809 | AEE1: TXN0000810 | AEF1: TXN0000811 | AEG1: TXN0000812 | AEH1: TXN0000813 | AEI1: TXN0000814 | AEJ1: TXN0000815 | AEK1: TXN0000816 | AEL1: TXN0000817 | AEM1: TXN0000818 | AEN1: TXN0000819 | AEO1: TXN0000820 | AEP1: TXN0000821 | AEQ1: TXN0000822 | AER1: TXN0000823 | AES1: TXN0000824 | AET1: TXN0000825 | AEU1: TXN0000826 | AEV1: TXN0000827 | AEW1: TXN0000828 | AEX1: TXN0000829 | AEY1: TXN0000830 | AEZ1: TXN0000831 | AFA1: TXN0000832 | AFB1: TXN0000833 | AFC1: TXN0000834 | AFD1: TXN0000835 | AFE1: TXN0000836 | AFF1: TXN0000837 | AFG1: TXN0000838 | AFH1: TXN0000839 | AFI1: TXN0000840 | AFJ1: TXN0000841 | AFK1: TXN0000842 | AFL1: TXN0000843 | AFM1: TXN0000844 | AFN1: TXN0000845 | AFO1: TXN0000846 | AFP1: TXN0000847 | AFQ1: TXN0000848 | AFR1: TXN0000849 | AFS1: TXN0000850 | AFT1: TXN0000851 | AFU1: TXN0000852 | AFV1: TXN0000853 | AFW1: TXN0000854 | AFX1: TXN0000855 | AFY1: TXN0000856 | AFZ1: TXN0000857 | AGA1: TXN0000858 | AGB1: TXN0000859 | AGC1: TXN0000860 | AGD1: TXN0000861 | AGE1: TXN0000862 | AGF1: TXN0000863 | AGG1: TXN0000864 | AGH1: TXN0000865 | AGI1: TXN0000866 | AGJ1: TXN0000867 | AGK1: TXN0000868 | AGL1: TXN0000869 | AGM1: TXN0000870 | AGN1: TXN0000871 | AGO1: TXN0000872 | AGP1: TXN0000873 | AGQ1: TXN0000874 | AGR1: TXN0000875 | AGS1: TXN0000876 | AGT1: TXN0000877 | AGU1: TXN0000878 | AGV1: TXN0000879 | AGW1: TXN0000880 | AGX1: TXN0000881 | AGY1: TXN0000882 | AGZ1: TXN0000883 | AHA1: TXN0000884 | AHB1: TXN0000885 | AHC1: TXN0000886 | AHD1: TXN0000887 | AHE1: TXN0000888 | AHF1: TXN0000889 | AHG1: TXN0000890 | AHH1: TXN0000891 | AHI1: TXN0000892 | AHJ1: TXN0000893 | AHK1: TXN0000894 | AHL1: TXN0000895 | AHM1: TXN0000896 | AHN1: TXN0000897 | AHO1: TXN0000898 | AHP1: TXN0000899 | AHQ1: TXN0000900 | AHR1: TXN0000901 | AHS1: TXN0000902 | AHT1: TXN0000903 | AHU1: TXN0000904 | AHV1: TXN0000905 | AHW1: TXN0000906 | AHX1: TXN0000907 | AHY1: TXN0000908 | AHZ1: TXN0000909 | AIA1: TXN0000910 | AIB1: TXN0000911 | AIC1: TXN0000912 | AID1: TXN0000913 | AIE1: TXN0000914 | AIF1: TXN0000915 | AIG1: TXN0000916 | AIH1: TXN0000917 | AII1: TXN0000918 | AIJ1: TXN0000919 | AIK1: TXN0000920 | AIL1: TXN0000921 | AIM1: TXN0000922 | AIN1: TXN0000923 | AIO1: TXN0000924 | AIP1: TXN0000925 | AIQ1: TXN0000926 | AIR1: TXN0000927 | AIS1: TXN0000928 | AIT1: TXN0000929 | AIU1: TXN0000930 | AIV1: TXN0000931 | AIW1: TXN0000932 | AIX1: TXN0000933 | AIY1: TXN0000934 | AIZ1: TXN0000935 | AJA1: TXN0000936 | AJB1: TXN0000937 | AJC1: TXN0000938 | AJD1: TXN0000939 | AJE1: TXN0000940 | AJF1: TXN0000941 | AJG1: TXN0000942 | AJH1: TXN0000943 | AJI1: TXN0000944 | AJJ1: TXN0000945 | AJK1: TXN0000946 | AJL1: TXN0000947 | AJM1: TXN0000948 | AJN1: TXN0000949 | AJO1: TXN0000950 | AJP1: TXN0000951 | AJQ1: TXN0000952 | AJR1: TXN0000953 | AJS1: TXN0000954 | AJT1: TXN0000955 | AJU1: TXN0000956 | AJV1: TXN0000957 | AJW1: TXN0000958 | AJX1: TXN0000959 | AJY1: TXN0000960 | AJZ1: TXN0000961 | AKA1: TXN0000962 | AKB1: TXN0000963 | AKC1: TXN0000964 | AKD1: TXN0000965 | AKE1: TXN0000966 | AKF1: TXN0000967 | AKG1: TXN0000968 | AKH1: TXN0000969 | AKI1: TXN0000970 | AKJ1: TXN0000971 | AKK1: TXN0000972 | AKL1: TXN0000973 | AKM1: TXN0000974 | AKN1: TXN0000975 | AKO1: TXN0000976 | AKP1: TXN0000977 | AKQ1: TXN0000978 | AKR1: TXN0000979 | AKS1: TXN0000980 | AKT1: TXN0000981 | AKU1: TXN0000982 | AKV1: TXN0000983 | AKW1: TXN0000984 | AKX1: TXN0000985 | AKY1: TXN0000986 | AKZ1: TXN0000987 | ALA1: TXN0000988 | ALB1: TXN0000989 | ALC1: TXN0000990 | ALD1: TXN0000991 | ALE1: TXN0000992 | ALF1: TXN0000993 | ALG1: TXN0000994 | ALH1: TXN0000995 | ALI1: TXN0000996 | ALJ1: TXN0000997 | ALK1: TXN0000998 | ALL1: TXN0000999 | ALM1: TXN0001000 | ALN1: TXN0001001 | ALO1: TXN0001002 | ALP1: TXN0001003 | ALQ1: TXN0001004 | ALR1: TXN0001005 | ALS1: TXN0001006 | ALT1: TXN0001007 | ALU1: TXN0001008 | ALV1: TXN0001009 | ALW1: TXN0001010 | ALX1: TXN0001011 | ALY1: TXN0001012 | ALZ1: TXN0001013 | AMA1: TXN0001014 | AMB1: TXN0001015 | AMC1: TXN0001016 | AMD1: TXN0001017 | AME1: TXN0001018 | AMF1: TXN0001019 | AMG1: TXN0001020 | AMH1: TXN0001021 | AMI1: TXN0001022 | AMJ1: TXN0001023 | AMK1: TXN0001024 | AML1: TXN0001025 | AMM1: TXN0001026 | AMN1: TXN0001027 | AMO1: TXN0001028 | AMP1: TXN0001029 | AMQ1: TXN0001030 | AMR1: TXN0001031 | AMS1: TXN0001032 | AMT1: TXN0001033 | AMU1: TXN0001034 | AMV1: TXN0001035 | AMW1: TXN0001036 | AMX1: TXN0001037 | AMY1: TXN0001038 | AMZ1: TXN0001039 | ANA1: TXN0001040 | ANB1: TXN0001041 | ANC1: TXN0001042 | AND1: TXN0001043 | ANE1: TXN0001044 | ANF1: TXN0001045 | ANG1: TXN0001046 | ANH1: TXN0001047 | ANI1: TXN0001048 | ANJ1: TXN0001049 | ANK1: TXN0001050 | ANL1: TXN0001051 | ANM1: TXN0001052 | ANN1: TXN0001053 | ANO1: TXN0001054 | ANP1: TXN0001055 | ANQ1: TXN0001056 | ANR1: TXN0001057 | ANS1: TXN0001058 | ANT1: TXN0001059 | ANU1: TXN0001060 | ANV1: TXN0001061 | ANW1: TXN0001062 | ANX1: TXN0001063 | ANY1: TXN0001064 | ANZ1: TXN0001065 | AOA1: TXN0001066 | AOB1: TXN0001067 | AOC1: TXN0001068 | AOD1: TXN0001069 | AOE1: TXN0001070 | AOF1: TXN0001071 | AOG1: TXN0001072 | AOH1: TXN0001073 | AOI1: TXN0001074 | AOJ1: TXN0001075 | AOK1: TXN0001076 | AOL1: TXN0001077 | AOM1: TXN0001078 | AON1: TXN0001079 | AOO1: TXN0001080 | AOP1: TXN0001081 | AOQ1: TXN0001082 | AOR1: TXN0001083 | AOS1: TXN0001084 | AOT1: TXN0001085 | AOU1: TXN0001086 | AOV1: TXN0001087 | AOW1: TXN0001088 | AOX1: TXN0001089 | AOY1: TXN0001090 | AOZ1: TXN0001091 | APA1: TXN0001092 | APB1: TXN0001093 | APC1: TXN0001094 | APD1: TXN0001095 | APE1: TXN0001096 | APF1: TXN0001097 | APG1: TXN0001098 | APH1: TXN0001099 | API1: TXN0001100 | APJ1: TXN0001101 | APK1: TXN0001102 | APL1: TXN0001103 | APM1: TXN0001104 | APN1: TXN0001105 | APO1: TXN0001106 | APP1: TXN0001107 | APQ1: TXN0001108 | APR1: TXN0001109 | APS1: TXN0001110 | APT1: TXN0001111 | APU1: TXN0001112 | APV1: TXN0001113 | APW1: TXN0001114 | APX1: TXN0001115 | APY1: TXN0001116 | APZ1: TXN0001117 | AQA1: TXN0001118 | AQB1: TXN0001119 | AQC1: TXN0001120 | AQD1: TXN0001121 | AQE1: TXN0001122 | AQF1: TXN0001123 | AQG1: TXN0001124 | AQH1: TXN0001125 | AQI1: TXN0001126 | AQJ1: TXN0001127 | AQK1: TXN0001128 | AQL1: TXN0001129 | AQM1: TXN0001130 | AQN1: TXN0001131 | AQO1: TXN0001132 | AQP1: TXN0001133 | AQQ1: TXN0001134 | AQR1: TXN0001135 | AQS1: TXN0001136 | AQT1: TXN0001137 | AQU1: TXN0001138 | AQV1: TXN0001139 | AQW1: TXN0001140 | AQX1: TXN0001141 | AQY1: TXN0001142 | AQZ1: TXN0001143 | ARA1: TXN0001144 | ARB1: TXN0001145 | ARC1: TXN0001146 | ARD1: TXN0001147 | ARE1: TXN0001148 | ARF1: TXN0001149 | ARG1: TXN0001150 | ARH1: TXN0001151 | ARI1: TXN0001152 | ARJ1: TXN0001153 | ARK1: TXN0001154 | ARL1: TXN0001155 | ARM1: TXN0001156 | ARN1: TXN0001157 | ARO1: TXN0001158 | ARP1: TXN0001159 | ARQ1: TXN0001160 | ARR1: TXN0001161 | ARS1: TXN0001162 | ART1: TXN0001163 | ARU1: TXN0001164 | ARV1: TXN0001165 | ARW1: TXN0001166 | ARX1: TXN0001167 | ARY1: TXN0001168 | ARZ1: TXN0001169 | ASA1: TXN0001170 | ASB1: TXN0001171 | ASC1: TXN0001172 | ASD1: TXN0001173 | ASE1: TXN0001174 | ASF1: TXN0001175 | ASG1: TXN0001176 | ASH1: TXN0001177 | ASI1: TXN0001178 | ASJ1: TXN0001179 | ASK1: TXN0001180 | ASL1: TXN0001181 | ASM1: TXN0001182 | ASN1: TXN0001183 | ASO1: TXN0001184 | ASP1: TXN0001185 | ASQ1: TXN0001186 | ASR1: TXN0001187 | ASS1: TXN0001188 | AST1: TXN0001189 | ASU1: TXN0001190 | ASV1: TXN0001191 | ASW1: TXN0001192 | ASX1: TXN0001193 | ASY1: TXN0001194 | ASZ1: TXN0001195 | ATA1: TXN0001196 | ATB1: TXN0001197 | ATC1: TXN0001198 | ATD1: TXN0001199 | ATE1: TXN0001200 | ATF1: TXN0001201 | ATG1: TXN0001202 | ATH1: TXN0001203 | ATI1: TXN0001204 | ATJ1: TXN0001205 | ATK1: TXN0001206 | ATL1: TXN0001207 | ATM1: TXN0001208 | ATN1: TXN0001209 | ATO1: TXN0001210 | ATP1: TXN0001211 | ATQ1: TXN0001212 | ATR1: TXN0001213 | ATS1: TXN0001214 | ATT1: TXN0001215 | ATU1: TXN0001216 | ATV1: TXN0001217 | ATW1: TXN0001218 | ATX1: TXN0001219 | ATY1: TXN0001220 | ATZ1: TXN0001221 | AUA1: TXN0001222 | AUB1: TXN0001223 | AUC1: TXN0001224 | AUD1: TXN0001225 | AUE1: TXN0001226 | AUF1: TXN0001227 | AUG1: TXN0001228 | AUH1: TXN0001229 | AUI1: TXN0001230 | AUJ1: TXN0001231 | AUK1: TXN0001232 | AUL1: TXN0001233 | AUM1: TXN0001234 | AUN1: TXN0001235 | AUO1: TXN0001236 | AUP1: TXN0001237 | AUQ1: TXN0001238 | AUR1: TXN0001239 | AUS1: TXN0001240 | AUT1: TXN0001241 | AUU1: TXN0001242 | AUV1: TXN0001243 | AUW1: TXN0001244 | AUX1: TXN0001245 | AUY1: TXN0001246 | AUZ1: TXN0001247 | AVA1: TXN0001248 | AVB1: TXN0001249 | AVC1: TXN0001250 | AVD1: TXN0001251 | AVE1: TXN0001252 | AVF1: TXN0001253 | AVG1: TXN0001254 | AVH1: TXN0001255 | AVI1: TXN0001256 | AVJ1: TXN0001257 | AVK1: TXN0001258 | AVL1: TXN0001259 | AVM1: TXN0001260 | AVN1: TXN0001261 | AVO1: TXN0001262 | AVP1: TXN0001263 | AVQ1: TXN0001264 | AVR1: TXN0001265 | AVS1: TXN0001266 | AVT1: TXN0001267 | AVU1: TXN0001268 | AVV1: TXN0001269 | AVW1: TXN0001270 | AVX1: TXN0001271 | AVY1: TXN0001272 | AVZ1: TXN0001273 | AWA1: TXN0001274 | AWB1: TXN0001275 | AWC1: TXN0001276 | AWD1: TXN0001277 | AWE1: TXN0001278 | AWF1: TXN0001279 | AWG1: TXN0001280 | AWH1: TXN0001281 | AWI1: TXN0001282 | AWJ1: TXN0001283 | AWK1: TXN0001284 | AWL1: TXN0001285 | AWM1: TXN0001286 | AWN1: TXN0001287 | AWO1: TXN0001288 | AWP1: TXN0001289 | AWQ1: TXN0001290 | AWR1: TXN0001291 | AWS1: TXN0001292 | AWT1: TXN0001293 | AWU1: TXN0001294 | AWV1: TXN0001295 | AWW1: TXN0001296 | AWX1: TXN0001297 | AWY1: TXN0001298 | AWZ1: TXN0001299 | AXA1: TXN0001300 | AXB1: TXN0001301 | AXC1: TXN0001302 | AXD1: TXN0001303 | AXE1: TXN0001304 | AXF1: TXN0001305 | AXG1: TXN0001306 | AXH1: TXN0001307 | AXI1: TXN0001308 | AXJ1: TXN0001309 | AXK1: TXN0001310 | AXL1: TXN0001311 | AXM1: TXN0001312 | AXN1: TXN0001313 | AXO1: TXN0001314 | AXP1: TXN0001315 | AXQ1: TXN0001316 | AXR1: TXN0001317 | AXS1: TXN0001318 | AXT1: TXN0001319 | AXU1: TXN0001320 | AXV1: TXN0001321 | AXW1: TXN0001322 | AXX1: TXN0001323 | AXY1: TXN0001324 | AXZ1: TXN0001325 | AYA1: TXN0001326 | AYB1: TXN0001327 | AYC1: TXN0001328 | AYD1: TXN0001329 | AYE1: TXN0001330 | AYF1: TXN0001331 | AYG1: TXN0001332 | AYH1: TXN0001333 | AYI1: TXN0001334 | AYJ1: TXN0001335 | AYK1: TXN0001336 | AYL1: TXN0001337 | AYM1: TXN0001338 | AYN1: TXN0001339 | AYO1: TXN0001340 | AYP1: TXN0001341 | AYQ1: TXN0001342 | AYR1: TXN0001343 | AYS1: TXN0001344 | AYT1: TXN0001345 | AYU1: TXN0001346 | AYV1: TXN0001347 | AYW1: TXN0001348 | AYX1: TXN0001349 | AYY1: TXN0001350 | AYZ1: TXN0001351 | AZA1: TXN0001352 | AZB1: TXN0001353 | AZC1: TXN0001354 | AZD1: TXN0001355 | AZE1: TXN0001356 | AZF1: TXN0001357 | AZG1: TXN0001358 | AZH1: TXN0001359 | AZI1: TXN0001360 | AZJ1: TXN0001361 | AZK1: TXN0001362 | AZL1: TXN0001363 | AZM1: TXN0001364 | AZN1: TXN0001365 | AZO1: TXN0001366 | AZP1: TXN0001367 | AZQ1: TXN0001368 | AZR1: TXN0001369 | AZS1: TXN0001370 | AZT1: TXN0001371 | AZU1: TXN0001372 | AZV1: TXN0001373 | AZW1: TXN0001374 | AZX1: TXN0001375 | AZY1: TXN0001376 | AZZ1: TXN0001377 | BAA1: TXN0001378 | BAB1: TXN0001379 | BAC1: TXN0001380 | BAD1: TXN0001381 | BAE1: TXN0001382 | BAF1: TXN0001383 | BAG1: TXN0001384 | BAH1: TXN0001385 | BAI1: TXN0001386 | BAJ1: TXN0001387 | BAK1: TXN0001388 | BAL1: TXN0001389 | BAM1: TXN0001390 | BAN1: TXN0001391 | BAO1: TXN0001392 | BAP1: TXN0001393 | BAQ1: TXN0001394 | BAR1: TXN0001395 | BAS1: TXN0001396 | BAT1: TXN0001397 | BAU1: TXN0001398 | BAV1: TXN0001399 | BAW1: TXN0001400 | BAX1: TXN0001401 | BAY1: TXN0001402 | BAZ1: TXN0001403 | BBA1: TXN0001404 | BBB1: TXN0001405 | BBC1: TXN0001406 | BBD1: TXN0001407 | BBE1: TXN0001408 | BBF1: TXN0001409 | BBG1: TXN0001410 | BBH1: TXN0001411 | BBI1: TXN0001412 | BBJ1: TXN0001413 | BBK1: TXN0001414 | BBL1: TXN0001415 | BBM1: TXN0001416 | BBN1: TXN0001417 | BBO1: TXN0001418 | BBP1: TXN0001419 | BBQ1: TXN0001420 | BBR1: TXN0001421 | BBS1: TXN0001422 | BBT1: TXN0001423 | BBU1: TXN0001424 | BBV1: TXN0001425 | BBW1: TXN0001426 | BBX1: TXN0001427 | BBY1: TXN0001428 | BBZ1: TXN0001429 | BCA1: TXN0001430 | BCB1: TXN0001431 | BCC1: TXN0001432 | BCD1: TXN0001433 | BCE1: TXN0001434 | BCF1: TXN0001435 | BCG1: TXN0001436 | BCH1: TXN0001437 | BCI1: TXN0001438 | BCJ1: TXN0001439 | BCK1: TXN0001440 | BCL1: TXN0001441 | BCM1: TXN0001442 | BCN1: TXN0001443 | BCO1: TXN0001444 | BCP1: TXN0001445 | BCQ1: TXN0001446 | BCR1: TXN0001447 | BCS1: TXN0001448 | BCT1: TXN0001449 | BCU1: TXN0001450 | BCV1: TXN0001451 | BCW1: TXN0001452 | BCX1: TXN0001453 | BCY1: TXN0001454 | BCZ1: TXN0001455 | BDA1: TXN0001456 | BDB1: TXN0001457 | BDC1: TXN0001458 | BDD1: TXN0001459 | BDE1: TXN0001460 | BDF1: TXN0001461 | BDG1: TXN0001462 | BDH1: TXN0001463 | BDI1: TXN0001464 | BDJ1: TXN0001465 | BDK1: TXN0001466 | BDL1: TXN0001467 | BDM1: TXN0001468 | BDN1: TXN0001469 | BDO1: TXN0001470 | BDP1: TXN0001471 | BDQ1: TXN0001472 | BDR1: TXN0001473 | BDS1: TXN0001474 | BDT1: TXN0001475 | BDU1: TXN0001476 | BDV1: TXN0001477 | BDW1: TXN0001478 | BDX1: TXN0001479 | BDY1: TXN0001480 | BDZ1: TXN0001481 | BEA1: TXN0001482 | BEB1: TXN0001483 | BEC1: TXN0001484 | BED1: TXN0001485 | BEE1: TXN0001486 | BEF1: TXN0001487 | BEG1: TXN0001488 | BEH1: TXN0001489 | BEI1: TXN0001490 | BEJ1: TXN0001491 | BEK1: TXN0001492 | BEL1: TXN0001493 | BEM1: TXN0001494 | BEN1: TXN0001495 | BEO1: TXN0001496 | BEP1: TXN0001497 | BEQ1: TXN0001498 | BER1: TXN0001499 | BES1: TXN0001500 | BET1: TXN0001501 | BEU1: TXN0001502 | BEV1: TXN0001503 | BEW1: TXN0001504 | BEX1: TXN0001505 | BEY1: TXN0001506 | BEZ1: TXN0001507 | BFA1: TXN0001508 | BFB1: TXN0001509 | BFC1: TXN0001510 | BFD1: TXN0001511 | BFE1: TXN0001512 | BFF1: TXN0001513 | BFG1: TXN0001514 | BFH1: TXN0001515 | BFI1: TXN0001516 | BFJ1: TXN0001517 | BFK1: TXN0001518 | BFL1: TXN0001519 | BFM1: TXN0001520 | BFN1: TXN0001521 | BFO1: TXN0001522 | BFP1: TXN0001523 | BFQ1: TXN0001524 | BFR1: TXN0001525 | BFS1: TXN0001526 | BFT1: TXN0001527 | BFU1: TXN0001528 | BFV1: TXN0001529 | BFW1: TXN0001530 | BFX1: TXN0001531 | BFY1: TXN0001532 | BFZ1: TXN0001533 | BGA1: TXN0001534 | BGB1: TXN0001535 | BGC1: TXN0001536 | BGD1: TXN0001537 | BGE1: TXN0001538 | BGF1: TXN0001539 | BGG1: TXN0001540 | BGH1: TXN0001541 | BGI1: TXN0001542 | BGJ1: TXN0001543 | BGK1: TXN0001544 | BGL1: TXN0001545 | BGM1: TXN0001546 | BGN1: TXN0001547 | BGO1: TXN0001548 | BGP1: TXN0001549 | BGQ1: TXN0001550 | BGR1: TXN0001551 | BGS1: TXN0001552 | BGT1: TXN0001553 | BGU1: TXN0001554 | BGV1: TXN0001555 | BGW1: TXN0001556 | BGX1: TXN0001557 | BGY1: TXN0001558 | BGZ1: TXN0001559 | BHA1: TXN0001560 | BHB1: TXN0001561 | BHC1: TXN0001562 | BHD1: TXN0001563 | BHE1: TXN0001564 | BHF1: TXN0001565 | BHG1: TXN0001566 | BHH1: TXN0001567 | BHI1: TXN0001568 | BHJ1: TXN0001569 | BHK1: TXN0001570 | BHL1: TXN0001571 | BHM1: TXN0001572 | BHN1: TXN0001573 | BHO1: TXN0001574 | BHP1: TXN0001575 | BHQ1: TXN0001576 | BHR1: TXN0001577 | BHS1: TXN0001578 | BHT1: TXN0001579 | BHU1: TXN0001580 | BHV1: TXN0001581 | BHW1: TXN0001582 | BHX1: TXN0001583 | BHY1: TXN0001584 | BHZ1: TXN0001585 | BIA1: TXN0001586 | BIB1: TXN0001587 | BIC1: TXN0001588 | BID1: TXN0001589 | BIE1: TXN0001590 | BIF1: TXN0001591 | BIG1: TXN0001592 | BIH1: TXN0001593 | BII1: TXN0001594 | BIJ1: TXN0001595 | BIK1: TXN0001596 | BIL1: TXN0001597 | BIM1: TXN0001598 | BIN1: TXN0001599 | BIO1: TXN0001600 | BIP1: TXN0001601 | BIQ1: TXN0001602 | BIR1: TXN0001603 | BIS1: TXN0001604 | BIT1: TXN0001605 | BIU1: TXN0001606 | BIV1: TXN0001607 | BIW1: TXN0001608 | BIX1: TXN0001609 | BIY1: TXN0001610 | BIZ1: TXN0001611 | BJA1: TXN0001612 | BJB1: TXN0001613 | BJC1: TXN0001614 | BJD1: TXN0001615 | BJE1: TXN0001616 | BJF1: TXN0001617 | BJG1: TXN0001618 | BJH1: TXN0001619 | BJI1: TXN0001620 | BJJ1: TXN0001621 | BJK1: TXN0001622 | BJL1: TXN0001623 | BJM1: TXN0001624 | BJN1: TXN0001625 | BJO1: TXN0001626 | BJP1: TXN0001627 | BJQ1: TXN0001628 | BJR1: TXN0001629 | BJS1: TXN0001630 | BJT1: TXN0001631 | BJU1: TXN0001632 | BJV1: TXN0001633 | BJW1: TXN0001634 | BJX1: TXN0001635 | BJY1: TXN0001636 | BJZ1: TXN0001637 | BKA1: TXN0001638 | BKB1: TXN0001639 | BKC1: TXN0001640 | BKD1: TXN0001641 | BKE1: TXN0001642 | BKF1: TXN0001643 | BKG1: TXN0001644 | BKH1: TXN0001645 | BKI1: TXN0001646 | BKJ1: TXN0001647 | BKK1: TXN0001648 | BKL1: TXN0001649 | BKM1: TXN0001650 | BKN1: TXN0001651 | BKO1: TXN0001652 | BKP1: TXN0001653 | BKQ1: TXN0001654 | BKR1: TXN0001655 | BKS1: TXN0001656 | BKT1: TXN0001657 | BKU1: TXN0001658 | BKV1: TXN0001659 | BKW1: TXN0001660 | BKX1: TXN0001661 | BKY1: TXN0001662 | BKZ1: TXN0001663 | BLA1: TXN0001664 | BLB1: TXN0001665 | BLC1: TXN0001666 | BLD1: TXN0001667 | BLE1: TXN0001668 | BLF1: TXN0001669 | BLG1: TXN0001670 | BLH1: TXN0001671 | BLI1: TXN0001672 | BLJ1: TXN0001673 | BLK1: TXN0001674 | BLL1: TXN0001675 | BLM1: TXN0001676 | BLN1: TXN0001677 | BLO1: TXN0001678 | BLP1: TXN0001679 | BLQ1: TXN0001680 | BLR1: TXN0001681 | BLS1: TXN0001682 | BLT1: TXN0001683 | BLU1: TXN0001684 | BLV1: TXN0001685 | BLW1: TXN0001686 | BLX1: TXN0001687 | BLY1: TXN0001688 | BLZ1: TXN0001689 | BMA1: TXN0001690 | BMB1: TXN0001691 | BMC1: TXN0001692 | BMD1: TXN0001693 | BME1: TXN0001694 | BMF1: TXN0001695 | BMG1: TXN0001696 | BMH1: TXN0001697 | BMI1: TXN0001698 | BMJ1: TXN0001699 | BMK1: TXN0001700 | BML1: TXN0001701 | BMM1: TXN0001702 | BMN1: TXN0001703 | BMO1: TXN0001704 | BMP1: TXN0001705 | BMQ1: TXN0001706 | BMR1: TXN0001707 | BMS1: TXN0001708 | BMT1: TXN0001709 | BMU1: TXN0001710 | BMV1: TXN0001711 | BMW1: TXN0001712 | BMX1: TXN0001713 | BMY1: TXN0001714 | BMZ1: TXN0001715 | BNA1: TXN0001716 | BNB1: TXN0001717 | BNC1: TXN0001718 | BND1: TXN0001719 | BNE1: TXN0001720 | BNF1: TXN0001721 | BNG1: TXN0001722 | BNH1: TXN0001723 | BNI1: TXN0001724 | BNJ1: TXN0001725 | BNK1: TXN0001726 | BNL1: TXN0001727 | BNM1: TXN0001728 | BNN1: TXN0001729 | BNO1: TXN0001730 | BNP1: TXN0001731 | BNQ1: TXN0001732 | BNR1: TXN0001733 | BNS1: TXN0001734 | BNT1: TXN0001735 | BNU1: TXN0001736 | BNV1: TXN0001737 | BNW1: TXN0001738 | BNX1: TXN0001739 | BNY1: TXN0001740 | BNZ1: TXN0001741 | BOA1: TXN0001742 | BOB1: TXN0001743 | BOC1: TXN0001744 | BOD1: TXN0001745 | BOE1: TXN0001746 | BOF1: TXN0001747 | BOG1: TXN0001748 | BOH1: TXN0001749 | BOI1: TXN0001750 | BOJ1: TXN0001751 | BOK1: TXN0001752 | BOL1: TXN0001753 | BOM1: TXN0001754 | BON1: TXN0001755 | BOO1: TXN0001756 | BOP1: TXN0001757 | BOQ1: TXN0001758 | BOR1: TXN0001759 | BOS1: TXN0001760 | BOT1: TXN0001761 | BOU1: TXN0001762 | BOV1: TXN0001763 | BOW1: TXN0001764 | BOX1: TXN0001765 | BOY1: TXN0001766 | BOZ1: TXN0001767 | BPA1: TXN0001768 | BPB1: TXN0001769 | BPC1: TXN0001770 | BPD1: TXN0001771 | BPE1: TXN0001772 | BPF1: TXN0001773 | BPG1: TXN0001774 | BPH1: TXN0001775 | BPI1: TXN0001776 | BPJ1: TXN0001777 | BPK1: TXN0001778 | BPL1: TXN0001779 | BPM1: TXN0001780 | BPN1: TXN0001781 | BPO1: TXN0001782 | BPP1: TXN0001783 | BPQ1: TXN0001784 | BPR1: TXN0001785 | BPS1: TXN0001786 | BPT1: TXN0001787 | BPU1: TXN0001788 | BPV1: TXN0001789 | BPW1: TXN0001790 | BPX1: TXN0001791 | BPY1: TXN0001792 | BPZ1: TXN0001793 | BQA1: TXN0001794 | BQB1: TXN0001795 | BQC1: TXN0001796 | BQD1: TXN0001797 | BQE1: TXN0001798 | BQF1: TXN0001799 | BQG1: TXN0001800 | BQH1: TXN0001801 | BQI1: TXN0001802 | BQJ1: TXN0001803 | BQK1: TXN0001804 | BQL1: TXN0001805 | BQM1: TXN0001806 | BQN1: TXN0001807 | BQO1: TXN0001808 | BQP1: TXN0001809 | BQQ1: TXN0001810 | BQR1: TXN0001811 | BQS1: TXN0001812 | BQT1: TXN0001813 | BQU1: TXN0001814 | BQV1: TXN0001815 | BQW1: TXN0001816 | BQX1: TXN0001817 | BQY1: TXN0001818 | BQZ1: TXN0001819 | BRA1: TXN0001820 | BRB1: TXN0001821 | BRC1: TXN0001822 | BRD1: TXN0001823 | BRE1: TXN0001824 | BRF1: TXN0001825 | BRG1: TXN0001826 | BRH1: TXN0001827 | BRI1: TXN0001828 | BRJ1: TXN0001829 | BRK1: TXN0001830 | BRL1: TXN0001831 | BRM1: TXN0001832 | BRN1: TXN0001833 | BRO1: TXN0001834 | BRP1: TXN0001835 | BRQ1: TXN0001836 | BRR1: TXN0001837 | BRS1: TXN0001838 | BRT1: TXN0001839 | BRU1: TXN0001840 | BRV1: TXN0001841 | BRW1: TXN0001842 | BRX1: TXN0001843 | BRY1: TXN0001844 | BRZ1: TXN0001845 | BSA1: TXN0001846 | BSB1: TXN0001847 | BSC1: TXN0001848 | BSD1: TXN0001849 | BSE1: TXN0001850 | BSF1: TXN0001851 | BSG1: TXN0001852 | BSH1: TXN0001853 | BSI1: TXN0001854 | BSJ1: TXN0001855 | BSK1: TXN0001856 | BSL1: TXN0001857 | BSM1: TXN0001858 | BSN1: TXN0001859 | BSO1: TXN0001860 | BSP1: TXN0001861 | BSQ1: TXN0001862 | BSR1: TXN0001863 | BSS1: TXN0001864 | BST1: TXN0001865 | BSU1: TXN0001866 | BSV1: TXN0001867 | BSW1: TXN0001868 | BSX1: TXN0001869 | BSY1: TXN0001870 | BSZ1: TXN0001871 | BTA1: TXN0001872 | BTB1: TXN0001873 | BTC1: TXN0001874 | BTD1: TXN0001875 | BTE1: TXN0001876 | BTF1: TXN0001877 | BTG1: TXN0001878 | BTH1: TXN0001879 | BTI1: TXN0001880 | BTJ1: TXN0001881 | BTK1: TXN0001882 | BTL1: TXN0001883 | BTM1: TXN0001884 | BTN1: TXN0001885 | BTO1: TXN0001886 | BTP1: TXN0001887 | BTQ1: TXN0001888 | BTR1: TXN0001889 | BTS1: TXN0001890 | BTT1: TXN0001891 | BTU1: TXN0001892 | BTV1: TXN0001893 | BTW1: TXN0001894 | BTX1: TXN0001895 | BTY1: TXN0001896 | BTZ1: TXN0001897 | BUA1: TXN0001898 | BUB1: TXN0001899 | BUC1: TXN0001900 | BUD1: TXN0001901 | BUE1: TXN0001902 | BUF1: TXN0001903 | BUG1: TXN0001904 | BUH1: TXN0001905 | BUI1: TXN0001906 | BUJ1: TXN0001907 | BUK1: TXN0001908 | BUL1: TXN0001909 | BUM1: TXN0001910 | BUN1: TXN0001911 | BUO1: TXN0001912 | BUP1: TXN0001913 | BUQ1: TXN0001914 | BUR1: TXN0001915 | BUS1: TXN0001916 | BUT1: TXN0001917 | BUU1: TXN0001918 | BUV1: TXN0001919 | BUW1: TXN0001920 | BUX1: TXN0001921 | BUY1: TXN0001922 | BUZ1: TXN0001923 | BVA1: TXN0001924 | BVB1: TXN0001925 | BVC1: TXN0001926 | BVD1: TXN0001927 | BVE1: TXN0001928 | BVF1: TXN0001929 | BVG1: TXN0001930 | BVH1: TXN0001931 | BVI1: TXN0001932 | BVJ1: TXN0001933 | BVK1: TXN0001934 | BVL1: TXN0001935 | BVM1: TXN0001936 | BVN1: TXN0001937 | BVO1: TXN0001938 | BVP1: TXN0001939 | BVQ1: TXN0001940 | BVR1: TXN0001941 | BVS1: TXN0001942 | BVT1: TXN0001943 | BVU1: TXN0001944 | BVV1: TXN0001945 | BVW1: TXN0001946 | BVX1: TXN0001947 | BVY1: TXN0001948 | BVZ1: TXN0001949 | BWA1: TXN0001950 | BWB1: TXN0001951 | BWC1: TXN0001952 | BWD1: TXN0001953 | BWE1: TXN0001954 | BWF1: TXN0001955 | BWG1: TXN0001956 | BWH1: TXN0001957 | BWI1: TXN0001958 | BWJ1: TXN0001959 | BWK1: TXN0001960 | BWL1: TXN0001961 | BWM1: TXN0001962 | BWN1: TXN0001963 | BWO1: TXN0001964 | BWP1: TXN0001965 | BWQ1: TXN0001966 | BWR1: TXN0001967 | BWS1: TXN0001968 | BWT1: TXN0001969 | BWU1: TXN0001970 | BWV1: TXN0001971 | BWW1: TXN0001972 | BWX1: TXN0001973 | BWY1: TXN0001974 | BWZ1: TXN0001975 | BXA1: TXN0001976 | BXB1: TXN0001977 | BXC1: TXN0001978 | BXD1: TXN0001979 | BXE1: TXN0001980 | BXF1: TXN0001981 | BXG1: TXN0001982 | BXH1: TXN0001983 | BXI1: TXN0001984 | BXJ1: TXN0001985 | BXK1: TXN0001986 | BXL1: TXN0001987 | BXM1: TXN0001988 | BXN1: TXN0001989 | BXO1: TXN0001990 | BXP1: TXN0001991 | BXQ1: TXN0001992 | BXR1: TXN0001993 | BXS1: TXN0001994 | BXT1: TXN0001995 | BXU1: TXN0001996 | BXV1: TXN0001997 | BXW1: TXN0001998 | BXX1: TXN0001999 | BXY1: TXN0002000 | BXZ1: TXN0002001 | BYA1: TXN0002002 | BYB1: TXN0002003 | BYC1: TXN0002004 | BYD1: TXN0002005 | BYE1: TXN0002006 | BYF1: TXN0002007 | BYG1: TXN0002008 | BYH1: TXN0002009 | BYI1: TXN0002010 | BYJ1: TXN0002011 | BYK1: TXN0002012 | BYL1: TXN0002013 | BYM1: TXN0002014 | BYN1: TXN0002015 | BYO1: TXN0002016 | BYP1: TXN0002017 | BYQ1: TXN0002018 | BYR1: TXN0002019 | BYS1: TXN0002020 | BYT1: TXN0002021 | BYU1: TXN0002022 | BYV1: TXN0002023 | BYW1: TXN0002024 | BYX1: TXN0002025 | BYY1: TXN0002026 | BYZ1: TXN0002027 | BZA1: TXN0002028 | BZB1: TXN0002029 | BZC1: TXN0002030 | BZD1: TXN0002031 | BZE1: TXN0002032 | BZF1: TXN0002033 | BZG1: TXN0002034 | BZH1: TXN0002035 | BZI1: TXN0002036 | BZJ1: TXN0002037 | BZK1: TXN0002038 | BZL1: TXN0002039 | BZM1: TXN0002040 | BZN1: TXN0002041 | BZO1: TXN0002042 | BZP1: TXN0002043 | BZQ1: TXN0002044 | BZR1: TXN0002045 | BZS1: TXN0002046 | BZT1: TXN0002047 | BZU1: TXN0002048 | BZV1: TXN0002049 | BZW1: TXN0002050 | BZX1: TXN0002051 | BZY1: TXN0002052 | BZZ1: TXN0002053 | CAA1: TXN0002054 | CAB1: TXN0002055 | CAC1: TXN0002056 | CAD1: TXN0002057 | CAE1: TXN0002058 | CAF1: TXN0002059 | CAG1: TXN0002060 | CAH1: TXN0002061 | CAI1: TXN0002062 | CAJ1: TXN0002063 | CAK1: TXN0002064 | CAL1: TXN0002065 | CAM1: TXN0002066 | CAN1: TXN0002067 | CAO1: TXN0002068 | CAP1: TXN0002069 | CAQ1: TXN0002070 | CAR1: TXN0002071 | CAS1: TXN0002072 | CAT1: TXN0002073 | CAU1: TXN0002074 | CAV1: TXN0002075 | CAW1: TXN0002076 | CAX1: TXN0002077 | CAY1: TXN0002078 | CAZ1: TXN0002079 | CBA1: TXN0002080 | CBB1: TXN0002081 | CBC1: TXN0002082 | CBD1: TXN0002083 | CBE1: TXN0002084 | CBF1: TXN0002085 | CBG1: TXN0002086 | CBH1: TXN0002087 | CBI1: TXN0002088 | CBJ1: TXN0002089 | CBK1: TXN0002090 | CBL1: TXN0002091 | CBM1: TXN0002092 | CBN1: TXN0002093 | CBO1: TXN0002094 | CBP1: TXN0002095 | CBQ1: TXN0002096 | CBR1: TXN0002097 | CBS1: TXN0002098 | CBT1: TXN0002099 | CBU1: TXN0002100 | CBV1: TXN0002101 | CBW1: TXN0002102 | CBX1: TXN0002103 | CBY1: TXN0002104 | CBZ1: TXN0002105 | CCA1: TXN0002106 | CCB1: TXN0002107 | CCC1: TXN0002108 | CCD1: TXN0002109 | CCE1: TXN0002110 | CCF1: TXN0002111 | CCG1: TXN0002112 | CCH1: TXN0002113 | CCI1: TXN0002114 | CCJ1: TXN0002115 | CCK1: TXN0002116 | CCL1: TXN0002117 | CCM1: TXN0002118 | CCN1: TXN0002119 | CCO1: TXN0002120 | CCP1: TXN0002121 | CCQ1: TXN0002122 | CCR1: TXN0002123 | CCS1: TXN0002124 | CCT1: TXN0002125 | CCU1: TXN0002126 | CCV1: TXN0002127 | CCW1: TXN0002128 | CCX1: TXN0002129 | CCY1: TXN0002130 | CCZ1: TXN0002131 | CDA1: TXN0002132 | CDB1: TXN0002133 | CDC1: TXN0002134 | CDD1: TXN0002135 | CDE1: TXN0002136 | CDF1: TXN0002137 | CDG1: TXN0002138 | CDH1: TXN0002139 | CDI1: TXN0002140 | CDJ1: TXN0002141 | CDK1: TXN0002142 | CDL1: TXN0002143 | CDM1: TXN0002144 | CDN1: TXN0002145 | CDO1: TXN0002146 | CDP1: TXN0002147 | CDQ1: TXN0002148 | CDR1: TXN0002149 | CDS1: TXN0002150 | CDT1: TXN0002151 | CDU1: TXN0002152 | CDV1: TXN0002153 | CDW1: TXN0002154 | CDX1: TXN0002155 | CDY1: TXN0002156 | CDZ1: TXN0002157 | CEA1: TXN0002158 | CEB1: TXN0002159 | CEC1: TXN0002160 | CED1: TXN0002161 | CEE1: TXN0002162 | CEF1: TXN0002163 | CEG1: TXN0002164 | CEH1: TXN0002165 | CEI1: TXN0002166 | CEJ1: TXN0002167 | CEK1: TXN0002168 | CEL1: TXN0002169 | CEM1: TXN0002170 | CEN1: TXN0002171 | CEO1: TXN0002172 | CEP1: TXN0002173 | CEQ1: TXN0002174 | CER1: TXN0002175 | CES1: TXN0002176 | CET1: TXN0002177 | CEU1: TXN0002178 | CEV1: TXN0002179 | CEW1: TXN0002180 | CEX1: TXN0002181 | CEY1: TXN0002182 | CEZ1: TXN0002183 | CFA1: TXN0002184 | CFB1: TXN0002185 | CFC1: TXN0002186 | CFD1: TXN0002187 | CFE1: TXN0002188 | CFF1: TXN0002189 | CFG1: TXN0002190 | CFH1: TXN0002191 | CFI1: TXN0002192 | CFJ1: TXN0002193 | CFK1: TXN0002194 | CFL1: TXN0002195 | CFM1: TXN0002196 | CFN1: TXN0002197 | CFO1: TXN0002198 | CFP1: TXN0002199 | CFQ1: TXN0002200 | CFR1: TXN0002201 | CFS1: TXN0002202 | CFT1: TXN0002203 | CFU1: TXN0002204 | CFV1: TXN0002205 | CFW1: TXN0002206 | CFX1: TXN0002207 | CFY1: TXN0002208 | CFZ1: TXN0002209 | CGA1: TXN0002210 | CGB1: TXN0002211 | CGC1: TXN0002212 | CGD1: TXN0002213 | CGE1: TXN0002214 | CGF1: TXN0002215 | CGG1: TXN0002216 | CGH1: TXN0002217 | CGI1: TXN0002218 | CGJ1: TXN0002219 | CGK1: TXN0002220 | CGL1: TXN0002221 | CGM1: TXN0002222 | CGN1: TXN0002223 | CGO1: TXN0002224 | CGP1: TXN0002225 | CGQ1: TXN0002226 | CGR1: TXN0002227 | CGS1: TXN0002228 | CGT1: TXN0002229 | CGU1: TXN0002230 | CGV1: TXN0002231 | CGW1: TXN0002232 | CGX1: TXN0002233 | CGY1: TXN0002234 | CGZ1: TXN0002235 | CHA1: TXN0002236 | CHB1: TXN0002237 | CHC1: TXN0002238 | CHD1: TXN0002239 | CHE1: TXN0002240 | CHF1: TXN0002241 | CHG1: TXN0002242 | CHH1: TXN0002243 | CHI1: TXN0002244 | CHJ1: TXN0002245 | CHK1: TXN0002246 | CHL1: TXN0002247 | CHM1: TXN0002248 | CHN1: TXN0002249 | CHO1: TXN0002250 | CHP1: TXN0002251 | CHQ1: TXN0002252 | CHR1: TXN0002253 | CHS1: TXN0002254 | CHT1: TXN0002255 | CHU1: TXN0002256 | CHV1: TXN0002257 | CHW1: TXN0002258 | CHX1: TXN0002259 | CHY1: TXN0002260 | CHZ1: TXN0002261 | CIA1: TXN0002262 | CIB1: TXN0002263 | CIC1: TXN0002264 | CID1: TXN0002265 | CIE1: TXN0002266 | CIF1: TXN0002267 | CIG1: TXN0002268 | CIH1: TXN0002269 | CII1: TXN0002270 | CIJ1: TXN0002271 | CIK1: TXN0002272 | CIL1: TXN0002273 | CIM1: TXN0002274 | CIN1: TXN0002275 | CIO1: TXN0002276 | CIP1: TXN0002277 | CIQ1: TXN0002278 | CIR1: TXN0002279 | CIS1: TXN0002280 | CIT1: TXN0002281 | CIU1: TXN0002282 | CIV1: TXN0002283 | CIW1: TXN0002284 | CIX1: TXN0002285 | CIY1: TXN0002286 | CIZ1: TXN0002287 | CJA1: TXN0002288 | CJB1: TXN0002289 | CJC1: TXN0002290 | CJD1: TXN0002291 | CJE1: TXN0002292 | CJF1: TXN0002293 | CJG1: TXN0002294 | CJH1: TXN0002295 | CJI1: TXN0002296 | CJJ1: TXN0002297 | CJK1: TXN0002298 | CJL1: TXN0002299 | CJM1: TXN0002300 | CJN1: TXN0002301 | CJO1: TXN0002302 | CJP1: TXN0002303 | CJQ1: TXN0002304 | CJR1: TXN0002305 | CJS1: TXN0002306 | CJT1: TXN0002307 | CJU1: TXN0002308 | CJV1: TXN0002309 | CJW1: TXN0002310 | CJX1: TXN0002311 | CJY1: TXN0002312 | CJZ1: TXN0002313 | CKA1: TXN0002314 | CKB1: TXN0002315 | CKC1: TXN0002316 | CKD1: TXN0002317 | CKE1: TXN0002318 | CKF1: TXN0002319 | CKG1: TXN0002320 | CKH1: TXN0002321 | CKI1: TXN0002322 | CKJ1: TXN0002323 | CKK1: TXN0002324 | CKL1: TXN0002325 | CKM1: TXN0002326 | CKN1: TXN0002327 | CKO1: TXN0002328 | CKP1: TXN0002329 | CKQ1: TXN0002330 | CKR1: TXN0002331 | CKS1: TXN0002332 | CKT1: TXN0002333 | CKU1: TXN0002334 | CKV1: TXN0002335 | CKW1: TXN0002336 | CKX1: TXN0002337 | CKY1: TXN0002338 | CKZ1: TXN0002339 | CLA1: TXN0002340 | CLB1: TXN0002341 | CLC1: TXN0002342 | CLD1: TXN0002343 | CLE1: TXN0002344 | CLF1: TXN0002345 | CLG1: TXN0002346 | CLH1: TXN0002347 | CLI1: TXN0002348 | CLJ1: TXN0002349 | CLK1: TXN0002350 | CLL1: TXN0002351 | CLM1: TXN0002352 | CLN1: TXN0002353 | CLO1: TXN0002354 | CLP1: TXN0002355 | CLQ1: TXN0002356 | CLR1: TXN0002357 | CLS1: TXN0002358 | CLT1: TXN0002359 | CLU1: TXN0002360 | CLV1: TXN0002361 | CLW1: TXN0002362 | CLX1: TXN0002363 | CLY1: TXN0002364 | CLZ1: TXN0002365 | CMA1: TXN0002366 | CMB1: TXN0002367 | CMC1: TXN0002368 | CMD1: TXN0002369 | CME1: TXN0002370 | CMF1: TXN0002371 | CMG1: TXN0002372 | CMH1: TXN0002373 | CMI1: TXN0002374 | CMJ1: TXN0002375 | CMK1: TXN0002376 | CML1: TXN0002377 | CMM1: TXN0002378 | CMN1: TXN0002379 | CMO1: TXN0002380 | CMP1: TXN0002381 | CMQ1: TXN0002382 | CMR1: TXN0002383 | CMS1: TXN0002384 | CMT1: TXN0002385 | CMU1: TXN0002386 | CMV1: TXN0002387 | CMW1: TXN0002388 | CMX1: TXN0002389 | CMY1: TXN0002390 | CMZ1: TXN0002391 | CNA1: TXN0002392 | CNB1: TXN0002393 | CNC1: TXN0002394 | CND1: TXN0002395 | CNE1: TXN0002396 | CNF1: TXN0002397 | CNG1: TXN0002398 | CNH1: TXN0002399 | CNI1: TXN0002400 | CNJ1: TXN0002401 | CNK1: TXN0002402 | CNL1: TXN0002403 | CNM1: TXN0002404 | CNN1: TXN0002405 | CNO1: TXN0002406 | CNP1: TXN0002407 | CNQ1: TXN0002408 | CNR1: TXN0002409 | CNS1: TXN0002410 | CNT1: TXN0002411 | CNU1: TXN0002412 | CNV1: TXN0002413 | CNW1: TXN0002414 | CNX1: TXN0002415 | CNY1: TXN0002416 | CNZ1: TXN0002417 | COA1: TXN0002418 | COB1: TXN0002419 | COC1: TXN0002420 | COD1: TXN0002421 | COE1: TXN0002422 | COF1: TXN0002423 | COG1: TXN0002424 | COH1: TXN0002425 | COI1: TXN0002426 | COJ1: TXN0002427 | COK1: TXN0002428 | COL1: TXN0002429 | COM1: TXN0002430 | CON1: TXN0002431 | COO1: TXN0002432 | COP1: TXN0002433 | COQ1: TXN0002434 | COR1: TXN0002435 | COS1: TXN0002436 | COT1: TXN0002437 | COU1: TXN0002438 | COV1: TXN0002439 | COW1: TXN0002440 | COX1: TXN0002441 | COY1: TXN0002442 | COZ1: TXN0002443 | CPA1: TXN0002444 | CPB1: TXN0002445 | CPC1: TXN0002446 | CPD1: TXN0002447 | CPE1: TXN0002448 | CPF1: TXN0002449 | CPG1: TXN0002450 | CPH1: TXN0002451 | CPI1: TXN0002452 | CPJ1: TXN0002453 | CPK1: TXN0002454 | CPL1: TXN0002455 | CPM1: TXN0002456 | CPN1: TXN0002457 | CPO1: TXN0002458 | CPP1: TXN0002459 | CPQ1: TXN0002460 | CPR1: TXN0002461 | CPS1: TXN0002462 | CPT1: TXN0002463 | CPU1: TXN0002464 | CPV1: TXN0002465 | CPW1: TXN0002466 | CPX1: TXN0002467 | CPY1: TXN0002468 | CPZ1: TXN0002469 | CQA1: TXN0002470 | CQB1: TXN0002471 | CQC1: TXN0002472 | CQD1: TXN0002473 | CQE1: TXN0002474 | CQF1: TXN0002475 | CQG1: TXN0002476 | CQH1: TXN0002477 | CQI1: TXN0002478 | CQJ1: TXN0002479 | CQK1: TXN0002480 | CQL1: TXN0002481 | CQM1: TXN0002482 | CQN1: TXN0002483 | CQO1: TXN0002484 | CQP1: TXN0002485 | CQQ1: TXN0002486 | CQR1: TXN0002487 | CQS1: TXN0002488 | CQT1: TXN0002489 | CQU1: TXN0002490 | CQV1: TXN0002491 | CQW1: TXN0002492 | CQX1: TXN0002493 | CQY1: TXN0002494 | CQZ1: TXN0002495 | CRA1: TXN0002496 | CRB1: TXN0002497 | CRC1: TXN0002498 | CRD1: TXN0002499 | CRE1: TXN0002500 | CRF1: TXN0002501 | CRG1: TXN0002502 | CRH1: TXN0002503 | CRI1: TXN0002504 | CRJ1: TXN0002505 | CRK1: TXN0002506 | CRL1: TXN0002507 | CRM1: TXN0002508 | CRN1: TXN0002509 | CRO1: TXN0002510 | CRP1: TXN0002511 | CRQ1: TXN0002512 | CRR1: TXN0002513 | CRS1: TXN0002514 | CRT1: TXN0002515 | CRU1: TXN0002516 | CRV1: TXN0002517 | CRW1: TXN0002518 | CRX1: TXN0002519 | CRY1: TXN0002520 | CRZ1: TXN0002521 | CSA1: TXN0002522 | CSB1: TXN0002523 | CSC1: TXN0002524 | CSD1: TXN0002525 | CSE1: TXN0002526 | CSF1: TXN0002527 | CSG1: TXN0002528 | CSH1: TXN0002529 | CSI1: TXN0002530 | CSJ1: TXN0002531 | CSK1: TXN0002532 | CSL1: TXN0002533 | CSM1: TXN0002534 | CSN1: TXN0002535 | CSO1: TXN0002536 | CSP1: TXN0002537 | CSQ1: TXN0002538 | CSR1: TXN0002539 | CSS1: TXN0002540 | CST1: TXN0002541 | CSU1: TXN0002542 | CSV1: TXN0002543 | CSW1: TXN0002544 | CSX1: TXN0002545 | CSY1: TXN0002546 | CSZ1: TXN0002547 | CTA1: TXN0002548 | CTB1: TXN0002549 | CTC1: TXN0002550 | CTD1: TXN0002551 | CTE1: TXN0002552 | CTF1: TXN0002553 | CTG1: TXN0002554 | CTH1: TXN0002555 | CTI1: TXN0002556 | CTJ1: TXN0002557 | CTK1: TXN0002558 | CTL1: TXN0002559 | CTM1: TXN0002560 | CTN1: TXN0002561 | CTO1: TXN0002562 | CTP1: TXN0002563 | CTQ1: TXN0002564 | CTR1: TXN0002565 | CTS1: TXN0002566 | CTT1: TXN0002567 | CTU1: TXN0002568 | CTV1: TXN0002569 | CTW1: TXN0002570 | CTX1: TXN0002571 | CTY1: TXN0002572 | CTZ1: TXN0002573 | CUA1: TXN0002574 | CUB1: TXN0002575 | CUC1: TXN0002576 | CUD1: TXN0002577 | CUE1: TXN0002578 | CUF1: TXN0002579 | CUG1: TXN0002580 | CUH1: TXN0002581 | CUI1: TXN0002582 | CUJ1: TXN0002583 | CUK1: TXN0002584 | CUL1: TXN0002585 | CUM1: TXN0002586 | CUN1: TXN0002587 | CUO1: TXN0002588 | CUP1: TXN0002589 | CUQ1: TXN0002590 | CUR1: TXN0002591 | CUS1: TXN0002592 | CUT1: TXN0002593 | CUU1: TXN0002594 | CUV1: TXN0002595 | CUW1: TXN0002596 | CUX1: TXN0002597 | CUY1: TXN0002598 | CUZ1: TXN0002599 | CVA1: TXN0002600 | CVB1: TXN0002601 | CVC1: TXN0002602 | CVD1: TXN0002603 | CVE1: TXN0002604 | CVF1: TXN0002605 | CVG1: TXN0002606 | CVH1: TXN0002607 | CVI1: TXN0002608 | CVJ1: TXN0002609 | CVK1: TXN0002610 | CVL1: TXN0002611 | CVM1: TXN0002612 | CVN1: TXN0002613 | CVO1: TXN0002614 | CVP1: TXN0002615 | CVQ1: TXN0002616 | CVR1: TXN0002617 | CVS1: TXN0002618 | CVT1: TXN0002619 | CVU1: TXN0002620 | CVV1: TXN0002621 | CVW1: TXN0002622 | CVX1: TXN0002623 | CVY1: TXN0002624 | CVZ1: TXN0002625 | CWA1: TXN0002626 | CWB1: TXN0002627 | CWC1: TXN0002628 | CWD1: TXN0002629 | CWE1: TXN0002630 | CWF1: TXN0002631 | CWG1: TXN0002632 | CWH1: TXN0002633 | CWI1: TXN0002634 | CWJ1: TXN0002635 | CWK1: TXN0002636 | CWL1: TXN0002637 | CWM1: TXN0002638 | CWN1: TXN0002639 | CWO1: TXN0002640 | CWP1: TXN0002641 | CWQ1: TXN0002642 | CWR1: TXN0002643 | CWS1: TXN0002644 | CWT1: TXN0002645 | CWU1: TXN0002646 | CWV1: TXN0002647 | CWW1: TXN0002648 | CWX1: TXN0002649 | CWY1: TXN0002650 | CWZ1: TXN0002651 | CXA1: TXN0002652 | CXB1: TXN0002653 | CXC1: TXN0002654 | CXD1: TXN0002655 | CXE1: TXN0002656 | CXF1: TXN0002657 | CXG1: TXN0002658 | CXH1: TXN0002659 | CXI1: TXN0002660 | CXJ1: TXN0002661 | CXK1: TXN0002662 | CXL1: TXN0002663 | CXM1: TXN0002664 | CXN1: TXN0002665 | CXO1: TXN0002666 | CXP1: TXN0002667 | CXQ1: TXN0002668 | CXR1: TXN0002669 | CXS1: TXN0002670 | CXT1: TXN0002671 | CXU1: TXN0002672 | CXV1: TXN0002673 | CXW1: TXN0002674 | CXX1: TXN0002675 | CXY1: TXN0002676 | CXZ1: TXN0002677 | CYA1: TXN0002678 | CYB1: TXN0002679 | CYC1: TXN0002680 | CYD1: TXN0002681 | CYE1: TXN0002682 | CYF1: TXN0002683 | CYG1: TXN0002684 | CYH1: TXN0002685 | CYI1: TXN0002686 | CYJ1: TXN0002687 | CYK1: TXN0002688 | CYL1: TXN0002689 | CYM1: TXN0002690 | CYN1: TXN0002691 | CYO1: TXN0002692 | CYP1: TXN0002693 | CYQ1: TXN0002694 | CYR1: TXN0002695 | CYS1: TXN0002696 | CYT1: TXN0002697 | CYU1: TXN0002698 | CYV1: TXN0002699 | CYW1: TXN0002700 | CYX1: TXN0002701 | CYY1: TXN0002702 | CYZ1: TXN0002703 | CZA1: TXN0002704 | CZB1: TXN0002705 | CZC1: TXN0002706 | CZD1: TXN0002707 | CZE1: TXN0002708 | CZF1: TXN0002709 | CZG1: TXN0002710 | CZH1: TXN0002711 | CZI1: TXN0002712 | CZJ1: TXN0002713 | CZK1: TXN0002714 | CZL1: TXN0002715 | CZM1: TXN0002716 | CZN1: TXN0002717 | CZO1: TXN0002718 | CZP1: TXN0002719 | CZQ1: TXN0002720 | CZR1: TXN0002721 | CZS1: TXN0002722 | CZT1: TXN0002723 | CZU1: TXN0002724 | CZV1: TXN0002725 | CZW1: TXN0002726 | CZX1: TXN0002727 | CZY1: TXN0002728 | CZZ1: TXN0002729 | DAA1: TXN0002730 | DAB1: TXN0002731 | DAC1: TXN0002732 | DAD1: TXN0002733 | DAE1: TXN0002734 | DAF1: TXN0002735 | DAG1: TXN0002736 | DAH1: TXN0002737 | DAI1: TXN0002738 | DAJ1: TXN0002739 | DAK1: TXN0002740 | DAL1: TXN0002741 | DAM1: TXN0002742 | DAN1: TXN0002743 | DAO1: TXN0002744 | DAP1: TXN0002745 | DAQ1: TXN0002746 | DAR1: TXN0002747 | DAS1: TXN0002748 | DAT1: TXN0002749 | DAU1: TXN0002750 | DAV1: TXN0002751 | DAW1: TXN0002752 | DAX1: TXN0002753 | DAY1: TXN0002754 | DAZ1: TXN0002755 | DBA1: TXN0002756 | DBB1: TXN0002757 | DBC1: TXN0002758 | DBD1: TXN0002759 | DBE1: TXN0002760 | DBF1: TXN0002761 | DBG1: TXN0002762 | DBH1: TXN0002763 | DBI1: TXN0002764 | DBJ1: TXN0002765 | DBK1: TXN0002766 | DBL1: TXN0002767 | DBM1: TXN0002768 | DBN1: TXN0002769 | DBO1: TXN0002770 | DBP1: TXN0002771 | DBQ1: TXN0002772 | DBR1: TXN0002773 | DBS1: TXN0002774 | DBT1: TXN0002775 | DBU1: TXN0002776 | DBV1: TXN0002777 | DBW1: TXN0002778 | DBX1: TXN0002779 | DBY1: TXN0002780 | DBZ1: TXN0002781 | DCA1: TXN0002782 | DCB1: TXN0002783 | DCC1: TXN0002784 | DCD1: TXN0002785 | DCE1: TXN0002786 | DCF1: TXN0002787 | DCG1: TXN0002788 | DCH1: TXN0002789 | DCI1: TXN0002790 | DCJ1: TXN0002791 | DCK1: TXN0002792 | DCL1: TXN0002793 | DCM1: TXN0002794 | DCN1: TXN0002795 | DCO1: TXN0002796 | DCP1: TXN0002797 | DCQ1: TXN0002798 | DCR1: TXN0002799 | DCS1: TXN0002800 | DCT1: TXN0002801 | DCU1: TXN0002802 | DCV1: TXN0002803 | DCW1: TXN0002804 | DCX1: TXN0002805 | DCY1: TXN0002806 | DCZ1: TXN0002807 | DDA1: TXN0002808 | DDB1: TXN0002809 | DDC1: TXN0002810 | DDD1: TXN0002811 | DDE1: TXN0002812 | DDF1: TXN0002813 | DDG1: TXN0002814 | DDH1: TXN0002815 | DDI1: TXN0002816 | DDJ1: TXN0002817 | DDK1: TXN0002818 | DDL1: TXN0002819 | DDM1: TXN0002820 | DDN1: TXN0002821 | DDO1: TXN0002822 | DDP1: TXN0002823 | DDQ1: TXN0002824 | DDR1: TXN0002825 | DDS1: TXN0002826 | DDT1: TXN0002827 | DDU1: TXN0002828 | DDV1: TXN0002829 | DDW1: TXN0002830 | DDX1: TXN0002831 | DDY1: TXN0002832 | DDZ1: TXN0002833 | DEA1: TXN0002834 | DEB1: TXN0002835 | DEC1: TXN0002836 | DED1: TXN0002837 | DEE1: TXN0002838 | DEF1: TXN0002839 | DEG1: TXN0002840 | DEH1: TXN0002841 | DEI1: TXN0002842 | DEJ1: TXN0002843 | DEK1: TXN0002844 | DEL1: TXN0002845 | DEM1: TXN0002846 | DEN1: TXN0002847 | DEO1: TXN0002848 | DEP1: TXN0002849 | DEQ1: TXN0002850 | DER1: TXN0002851 | DES1: TXN0002852 | DET1: TXN0002853 | DEU1: TXN0002854 | DEV1: TXN0002855 | DEW1: TXN0002856 | DEX1: TXN0002857 | DEY1: TXN0002858 | DEZ1: TXN0002859 | DFA1: TXN0002860 | DFB1: TXN0002861 | DFC1: TXN0002862 | DFD1: TXN0002863 | DFE1: TXN0002864 | DFF1: TXN0002865 | DFG1: TXN0002866 | DFH1: TXN0002867 | DFI1: TXN0002868 | DFJ1: TXN0002869 | DFK1: TXN0002870 | DFL1: TXN0002871 | DFM1: TXN0002872 | DFN1: TXN0002873 | DFO1: TXN0002874 | DFP1: TXN0002875 | DFQ1: TXN0002876 | DFR1: TXN0002877 | DFS1: TXN0002878 | DFT1: TXN0002879 | DFU1: TXN0002880 | DFV1: TXN0002881 | DFW1: TXN0002882 | DFX1: TXN0002883 | DFY1: TXN0002884 | DFZ1: TXN0002885 | DGA1: TXN0002886 | DGB1: TXN0002887 | DGC1: TXN0002888 | DGD1: TXN0002889 | DGE1: TXN0002890 | DGF1: TXN0002891 | DGG1: TXN0002892 | DGH1: TXN0002893 | DGI1: TXN0002894 | DGJ1: TXN0002895 | DGK1: TXN0002896 | DGL1: TXN0002897 | DGM1: TXN0002898 | DGN1: TXN0002899 | DGO1: TXN0002900 | DGP1: TXN0002901 | DGQ1: TXN0002902 | DGR1: TXN0002903 | DGS1: TXN0002904 | DGT1: TXN0002905 | DGU1: TXN0002906 | DGV1: TXN0002907 | DGW1: TXN0002908 | DGX1: TXN0002909 | DGY1: TXN0002910 | DGZ1: TXN0002911 | DHA1: TXN0002912 | DHB1: TXN0002913 | DHC1: TXN0002914 | DHD1: TXN0002915 | DHE1: TXN0002916 | DHF1: TXN0002917 | DHG1: TXN0002918 | DHH1: TXN0002919 | DHI1: TXN0002920 | DHJ1: TXN0002921 | DHK1: TXN0002922 | DHL1: TXN0002923 | DHM1: TXN0002924 | DHN1: TXN0002925 | DHO1: TXN0002926 | DHP1: TXN0002927 | DHQ1: TXN0002928 | DHR1: TXN0002929 | DHS1: TXN0002930 | DHT1: TXN0002931 | DHU1: TXN0002932 | DHV1: TXN0002933 | DHW1: TXN0002934 | DHX1: TXN0002935 | DHY1: TXN0002936 | DHZ1: TXN0002937 | DIA1: TXN0002938 | DIB1: TXN0002939 | DIC1: TXN0002940 | DID1: TXN0002941 | DIE1: TXN0002942 | DIF1: TXN0002943 | DIG1: TXN0002944 | DIH1: TXN0002945 | DII1: TXN0002946 | DIJ1: TXN0002947 | DIK1: TXN0002948 | DIL1: TXN0002949 | DIM1: TXN0002950 | DIN1: TXN0002951 | DIO1: TXN0002952 | DIP1: TXN0002953 | DIQ1: TXN0002954 | DIR1: TXN0002955 | DIS1: TXN0002956 | DIT1: TXN0002957 | DIU1: TXN0002958 | DIV1: TXN0002959 | DIW1: TXN0002960 | DIX1: TXN0002961 | DIY1: TXN0002962 | DIZ1: TXN0002963 | DJA1: TXN0002964 | DJB1: TXN0002965 | DJC1: TXN0002966 | DJD1: TXN0002967 | DJE1: TXN0002968 | DJF1: TXN0002969 | DJG1: TXN0002970 | DJH1: TXN0002971 | DJI1: TXN0002972 | DJJ1: TXN0002973 | DJK1: TXN0002974 | DJL1: TXN0002975 | DJM1: TXN0002976 | DJN1: TXN0002977 | DJO1: TXN0002978 | DJP1: TXN0002979 | DJQ1: TXN0002980 | DJR1: TXN0002981 | DJS1: TXN0002982 | DJT1: TXN0002983 | DJU1: TXN0002984 | DJV1: TXN0002985 | DJW1: TXN0002986 | DJX1: TXN0002987 | DJY1: TXN0002988 | DJZ1: TXN0002989 | DKA1: TXN0002990 | DKB1: TXN0002991 | DKC1: TXN0002992 | DKD1: TXN0002993 | DKE1: TXN0002994 | DKF1: TXN0002995 | DKG1: TXN0002996 | DKH1: TXN0002997 | DKI1: TXN0002998 | DKJ1: TXN0002999 | DKK1: TXN0003000 | DKL1: TXN0003001 | DKM1: TXN0003002 | DKN1: TXN0003003 | DKO1: TXN0003004 | DKP1: TXN0003005 | DKQ1: TXN0003006 | DKR1: TXN0003007 | DKS1: TXN0003008 | DKT1: TXN0003009 | DKU1: TXN0003010 | DKV1: TXN0003011 | DKW1: TXN0003012 | DKX1: TXN0003013 | DKY1: TXN0003014 | DKZ1: TXN0003015 | DLA1: TXN0003016 | DLB1: TXN0003017 | DLC1: TXN0003018 | DLD1: TXN0003019 | DLE1: TXN0003020 | DLF1: TXN0003021 | DLG1: TXN0003022 | DLH1: TXN0003023 | DLI1: TXN0003024 | DLJ1: TXN0003025 | DLK1: TXN0003026 | DLL1: TXN0003027 | DLM1: TXN0003028 | DLN1: TXN0003029 | DLO1: TXN0003030 | DLP1: TXN0003031 | DLQ1: TXN0003032 | DLR1: TXN0003033 | DLS1: TXN0003034 | DLT1: TXN0003035 | DLU1: TXN0003036 | DLV1: TXN0003037 | DLW1: TXN0003038 | DLX1: TXN0003039 | DLY1: TXN0003040 | DLZ1: TXN0003041 | DMA1: TXN0003042 | DMB1: TXN0003043 | DMC1: TXN0003044 | DMD1: TXN0003045 | DME1: TXN0003046 | DMF1: TXN0003047 | DMG1: TXN0003048 | DMH1: TXN0003049 | DMI1: TXN0003050 | DMJ1: TXN0003051 | DMK1: TXN0003052 | DML1: TXN0003053 | DMM1: TXN0003054 | DMN1: TXN0003055 | DMO1: TXN0003056 | DMP1: TXN0003057 | DMQ1: TXN0003058 | DMR1: TXN0003059 | DMS1: TXN0003060 | DMT1: TXN0003061 | DMU1: TXN0003062 | DMV1: TXN0003063 | DMW1: TXN0003064 | DMX1: TXN0003065 | DMY1: TXN0003066 | DMZ1: TXN0003067 | DNA1: TXN0003068 | DNB1: TXN0003069 | DNC1: TXN0003070 | DND1: TXN0003071 | DNE1: TXN0003072 | DNF1: TXN0003073 | DNG1: TXN0003074 | DNH1: TXN0003075 | DNI1: TXN0003076 | DNJ1: TXN0003077 | DNK1: TXN0003078 | DNL1: TXN0003079 | DNM1: TXN0003080 | DNN1: TXN0003081 | DNO1: TXN0003082 | DNP1: TXN0003083 | DNQ1: TXN0003084 | DNR1: TXN0003085 | DNS1: TXN0003086 | DNT1: TXN0003087 | DNU1: TXN0003088 | DNV1: TXN0003089 | DNW1: TXN0003090 | DNX1: TXN0003091 | DNY1: TXN0003092 | DNZ1: TXN0003093 | DOA1: TXN0003094 | DOB1: TXN0003095 | DOC1: TXN0003096 | DOD1: TXN0003097 | DOE1: TXN0003098 | DOF1: TXN0003099 | DOG1: TXN0003100 | DOH1: TXN0003101 | DOI1: TXN0003102 | DOJ1: TXN0003103 | DOK1: TXN0003104 | DOL1: TXN0003105 | DOM1: TXN0003106 | DON1: TXN0003107 | DOO1: TXN0003108 | DOP1: TXN0003109 | DOQ1: TXN0003110 | DOR1: TXN0003111 | DOS1: TXN0003112 | DOT1: TXN0003113 | DOU1: TXN0003114 | DOV1: TXN0003115 | DOW1: TXN0003116 | DOX1: TXN0003117 | DOY1: TXN0003118 | DOZ1: TXN0003119 | DPA1: TXN0003120 | DPB1: TXN0003121 | DPC1: TXN0003122 | DPD1: TXN0003123 | DPE1: TXN0003124 | DPF1: TXN0003125 | DPG1: TXN0003126 | DPH1: TXN0003127 | DPI1: TXN0003128 | DPJ1: TXN0003129 | DPK1: TXN0003130 | DPL1: TXN0003131 | DPM1: TXN0003132 | DPN1: TXN0003133 | DPO1: TXN0003134 | DPP1: TXN0003135 | DPQ1: TXN0003136 | DPR1: TXN0003137 | DPS1: TXN0003138 | DPT1: TXN0003139 | DPU1: TXN0003140 | DPV1: TXN0003141 | DPW1: TXN0003142 | DPX1: TXN0003143 | DPY1: TXN0003144 | DPZ1: TXN0003145 | DQA1: TXN0003146 | DQB1: TXN0003147 | DQC1: TXN0003148 | DQD1: TXN0003149 | DQE1: TXN0003150 | DQF1: TXN0003151 | DQG1: TXN0003152 | DQH1: TXN0003153 | DQI1: TXN0003154 | DQJ1: TXN0003155 | DQK1: TXN0003156 | DQL1: TXN0003157 | DQM1: TXN0003158 | DQN1: TXN0003159 | DQO1: TXN0003160 | DQP1: TXN0003161 | DQQ1: TXN0003162 | DQR1: TXN0003163 | DQS1: TXN0003164 | DQT1: TXN0003165 | DQU1: TXN0003166 | DQV1: TXN0003167 | DQW1: TXN0003168 | DQX1: TXN0003169 | DQY1: TXN0003170 | DQZ1: TXN0003171 | DRA1: TXN0003172 | DRB1: TXN0003173 | DRC1: TXN0003174 | DRD1: TXN0003175 | DRE1: TXN0003176 | DRF1: TXN0003177 | DRG1: TXN0003178 | DRH1: TXN0003179 | DRI1: TXN0003180 | DRJ1: TXN0003181 | DRK1: TXN0003182 | DRL1: TXN0003183 | DRM1: TXN0003184 | DRN1: TXN0003185 | DRO1: TXN0003186 | DRP1: TXN0003187 | DRQ1: TXN0003188 | DRR1: TXN0003189 | DRS1: TXN0003190 | DRT1: TXN0003191 | DRU1: TXN0003192 | DRV1: TXN0003193 | DRW1: TXN0003194 | DRX1: TXN0003195 | DRY1: TXN0003196 | DRZ1: TXN0003197 | DSA1: TXN0003198 | DSB1: TXN0003199 | DSC1: TXN0003200 | DSD1: TXN0003201 | DSE1: TXN0003202 | DSF1: TXN0003203 | DSG1: TXN0003204 | DSH1: TXN0003205 | DSI1: TXN0003206 | DSJ1: TXN0003207 | DSK1: TXN0003208 | DSL1: TXN0003209 | DSM1: TXN0003210 | DSN1: TXN0003211 | DSO1: TXN0003212 | DSP1: TXN0003213 | DSQ1: TXN0003214 | DSR1: TXN0003215 | DSS1: TXN0003216 | DST1: TXN0003217 | DSU1: TXN0003218 | DSV1: TXN0003219 | DSW1: TXN0003220 | DSX1: TXN0003221 | DSY1: TXN0003222 | DSZ1: TXN0003223 | DTA1: TXN0003224 | DTB1: TXN0003225 | DTC1: TXN0003226 | DTD1: TXN0003227 | DTE1: TXN0003228 | DTF1: TXN0003229 | DTG1: TXN0003230 | DTH1: TXN0003231 | DTI1: TXN0003232 | DTJ1: TXN0003233 | DTK1: TXN0003234 | DTL1: TXN0003235 | DTM1: TXN0003236 | DTN1: TXN0003237 | DTO1: TXN0003238 | DTP1: TXN0003239 | DTQ1: TXN0003240 | DTR1: TXN0003241 | DTS1: TXN0003242 | DTT1: TXN0003243 | DTU1: TXN0003244 | DTV1: TXN0003245 | DTW1: TXN0003246 | DTX1: TXN0003247 | DTY1: TXN0003248 | DTZ1: TXN0003249 | DUA1: TXN0003250 | DUB1: TXN0003251 | DUC1: TXN0003252 | DUD1: TXN0003253 | DUE1: TXN0003254 | DUF1: TXN0003255 | DUG1: TXN0003256 | DUH1: TXN0003257 | DUI1: TXN0003258 | DUJ1: TXN0003259 | DUK1: TXN0003260 | DUL1: TXN0003261 | DUM1: TXN0003262 | DUN1: TXN0003263 | DUO1: TXN0003264 | DUP1: TXN0003265 | DUQ1: TXN0003266 | DUR1: TXN0003267 | DUS1: TXN0003268 | DUT1: TXN0003269 | DUU1: TXN0003270 | DUV1: TXN0003271 | DUW1: TXN0003272 | DUX1: TXN0003273 | DUY1: TXN0003274 | DUZ1: TXN0003275 | DVA1: TXN0003276 | DVB1: TXN0003277 | DVC1: TXN0003278 | DVD1: TXN0003279 | DVE1: TXN0003280 | DVF1: TXN0003281 | DVG1: TXN0003282 | DVH1: TXN0003283 | DVI1: TXN0003284 | DVJ1: TXN0003285 | DVK1: TXN0003286 | DVL1: TXN0003287 | DVM1: TXN0003288 | DVN1: TXN0003289 | DVO1: TXN0003290 | DVP1: TXN0003291 | DVQ1: TXN0003292 | DVR1: TXN0003293 | DVS1: TXN0003294 | DVT1: TXN0003295 | DVU1: TXN0003296 | DVV1: TXN0003297 | DVW1: TXN0003298 | DVX1: TXN0003299 | DVY1: TXN0003300 | DVZ1: TXN0003301 | DWA1: TXN0003302 | DWB1: TXN0003303 | DWC1: TXN0003304 | DWD1: TXN0003305 | DWE1: TXN0003306 | DWF1: TXN0003307 | DWG1: TXN0003308 | DWH1: TXN0003309 | DWI1: TXN0003310 | DWJ1: TXN0003311 | DWK1: TXN0003312 | DWL1: TXN0003313 | DWM1: TXN0003314 | DWN1: TXN0003315 | DWO1: TXN0003316 | DWP1: TXN0003317 | DWQ1: TXN0003318 | DWR1: TXN0003319 | DWS1: TXN0003320 | DWT1: TXN0003321 | DWU1: TXN0003322 | DWV1: TXN0003323 | DWW1: TXN0003324 | DWX1: TXN0003325 | DWY1: TXN0003326 | DWZ1: TXN0003327 | DXA1: TXN0003328 | DXB1: TXN0003329 | DXC1: TXN0003330 | DXD1: TXN0003331 | DXE1: TXN0003332 | DXF1: TXN0003333 | DXG1: TXN0003334 | DXH1: TXN0003335 | DXI1: TXN0003336 | DXJ1: TXN0003337 | DXK1: TXN0003338 | DXL1: TXN0003339 | DXM1: TXN0003340 | DXN1: TXN0003341 | DXO1: TXN0003342 | DXP1: TXN0003343 | DXQ1: TXN0003344 | DXR1: TXN0003345 | DXS1: TXN0003346 | DXT1: TXN0003347 | DXU1: TXN0003348 | DXV1: TXN0003349 | DXW1: TXN0003350 | DXX1: TXN0003351 | DXY1: TXN0003352 | DXZ1: TXN0003353 | DYA1: TXN0003354 | DYB1: TXN0003355 | DYC1: TXN0003356 | DYD1: TXN0003357 | DYE1: TXN0003358 | DYF1: TXN0003359 | DYG1: TXN0003360 | DYH1: TXN0003361 | DYI1: TXN0003362 | DYJ1: TXN0003363 | DYK1: TXN0003364 | DYL1: TXN0003365 | DYM1: TXN0003366 | DYN1: TXN0003367 | DYO1: TXN0003368 | DYP1: TXN0003369 | DYQ1: TXN0003370 | DYR1: TXN0003371 | DYS1: TXN0003372 | DYT1: TXN0003373 | DYU1: TXN0003374 | DYV1: TXN0003375 | DYW1: TXN0003376 | DYX1: TXN0003377 | DYY1: TXN0003378 | DYZ1: TXN0003379 | DZA1: TXN0003380 | DZB1: TXN0003381 | DZC1: TXN0003382 | DZD1: TXN0003383 | DZE1: TXN0003384 | DZF1: TXN0003385 | DZG1: TXN0003386 | DZH1: TXN0003387 | DZI1: TXN0003388 | DZJ1: TXN0003389 | DZK1: TXN0003390 | DZL1: TXN0003391 | DZM1: TXN0003392 | DZN1: TXN0003393 | DZO1: TXN0003394 | DZP1: TXN0003395 | DZQ1: TXN0003396 | DZR1: TXN0003397 | DZS1: TXN0003398 | DZT1: TXN0003399 | DZU1: TXN0003400 | DZV1: TXN0003401 | DZW1: TXN0003402 | DZX1: TXN0003403 | DZY1: TXN0003404 | DZZ1: TXN0003405 | EAA1: TXN0003406 | EAB1: TXN0003407 | EAC1: TXN0003408 | EAD1: TXN0003409 | EAE1: TXN0003410 | EAF1: TXN0003411 | EAG1: TXN0003412 | EAH1: TXN0003413 | EAI1: TXN0003414 | EAJ1: TXN0003415 | EAK1: TXN0003416 | EAL1: TXN0003417 | EAM1: TXN0003418 | EAN1: TXN0003419 | EAO1: TXN0003420 | EAP1: TXN0003421 | EAQ1: TXN0003422 | EAR1: TXN0003423 | EAS1: TXN0003424 | EAT1: TXN0003425 | EAU1: TXN0003426 | EAV1: TXN0003427 | EAW1: TXN0003428 | EAX1: TXN0003429 | EAY1: TXN0003430 | EAZ1: TXN0003431 | EBA1: TXN0003432 | EBB1: TXN0003433 | EBC1: TXN0003434 | EBD1: TXN0003435 | EBE1: TXN0003436 | EBF1: TXN0003437 | EBG1: TXN0003438 | EBH1: TXN0003439 | EBI1: TXN0003440 | EBJ1: TXN0003441 | EBK1: TXN0003442 | EBL1: TXN0003443 | EBM1: TXN0003444 | EBN1: TXN0003445 | EBO1: TXN0003446 | EBP1: TXN0003447 | EBQ1: TXN0003448 | EBR1: TXN0003449 | EBS1: TXN0003450 | EBT1: TXN0003451 | EBU1: TXN0003452 | EBV1: TXN0003453 | EBW1: TXN0003454 | EBX1: TXN0003455 | EBY1: TXN0003456 | EBZ1: TXN0003457 | ECA1: TXN0003458 | ECB1: TXN0003459 | ECC1: TXN0003460 | ECD1: TXN0003461 | ECE1: TXN0003462 | ECF1: TXN0003463 | ECG1: TXN0003464 | ECH1: TXN0003465 | ECI1: TXN0003466 | ECJ1: TXN0003467 | ECK1: TXN0003468 | ECL1: TXN0003469 | ECM1: TXN0003470 | ECN1: TXN0003471 | ECO1: TXN0003472 | ECP1: TXN0003473 | ECQ1: TXN0003474 | ECR1: TXN0003475 | ECS1: TXN0003476 | ECT1: TXN0003477 | ECU1: TXN0003478 | ECV1: TXN0003479 | ECW1: TXN0003480 | ECX1: TXN0003481 | ECY1: TXN0003482 | ECZ1: TXN0003483 | EDA1: TXN0003484 | EDB1: TXN0003485 | EDC1: TXN0003486 | EDD1: TXN0003487 | EDE1: TXN0003488 | EDF1: TXN0003489 | EDG1: TXN0003490 | EDH1: TXN0003491 | EDI1: TXN0003492 | EDJ1: TXN0003493 | EDK1: TXN0003494 | EDL1: TXN0003495 | EDM1: TXN0003496 | EDN1: TXN0003497 | EDO1: TXN0003498 | EDP1: TXN0003499 | EDQ1: TXN0003500 | EDR1: TXN0003501 | EDS1: TXN0003502 | EDT1: TXN0003503 | EDU1: TXN0003504 | EDV1: TXN0003505 | EDW1: TXN0003506 | EDX1: TXN0003507 | EDY1: TXN0003508 | EDZ1: TXN0003509 | EEA1: TXN0003510 | EEB1: TXN0003511 | EEC1: TXN0003512 | EED1: TXN0003513 | EEE1: TXN0003514 | EEF1: TXN0003515 | EEG1: TXN0003516 | EEH1: TXN0003517 | EEI1: TXN0003518 | EEJ1: TXN0003519 | EEK1: TXN0003520 | EEL1: TXN0003521 | EEM1: TXN0003522 | EEN1: TXN0003523 | EEO1: TXN0003524 | EEP1: TXN0003525 | EEQ1: TXN0003526 | EER1: TXN0003527 | EES1: TXN0003528 | EET1: TXN0003529 | EEU1: TXN0003530 | EEV1: TXN0003531 | EEW1: TXN0003532 | EEX1: TXN0003533 | EEY1: TXN0003534 | EEZ1: TXN0003535 | EFA1: TXN0003536 | EFB1: TXN0003537 | EFC1: TXN0003538 | EFD1: TXN0003539 | EFE1: TXN0003540 | EFF1: TXN0003541 | EFG1: TXN0003542 | EFH1: TXN0003543 | EFI1: TXN0003544 | EFJ1: TXN0003545 | EFK1: TXN0003546 | EFL1: TXN0003547 | EFM1: TXN0003548 | EFN1: TXN0003549 | EFO1: TXN0003550 | EFP1: TXN0003551 | EFQ1: TXN0003552 | EFR1: TXN0003553 | EFS1: TXN0003554 | EFT1: TXN0003555 | EFU1: TXN0003556 | EFV1: TXN0003557 | EFW1: TXN0003558 | EFX1: TXN0003559 | EFY1: TXN0003560 | EFZ1: TXN0003561 | EGA1: TXN0003562 | EGB1: TXN0003563 | EGC1: TXN0003564 | EGD1: TXN0003565 | EGE1: TXN0003566 | EGF1: TXN0003567 | EGG1: TXN0003568 | EGH1: TXN0003569 | EGI1: TXN0003570 | EGJ1: TXN0003571 | EGK1: TXN0003572 | EGL1: TXN0003573 | EGM1: TXN0003574 | EGN1: TXN0003575 | EGO1: TXN0003576 | EGP1: TXN0003577 | EGQ1: TXN0003578 | EGR1: TXN0003579 | EGS1: TXN0003580 | EGT1: TXN0003581 | EGU1: TXN0003582 | EGV1: TXN0003583 | EGW1: TXN0003584 | EGX1: TXN0003585 | EGY1: TXN0003586 | EGZ1: TXN0003587 | EHA1: TXN0003588 | EHB1: TXN0003589 | EHC1: TXN0003590 | EHD1: TXN0003591 | EHE1: TXN0003592 | EHF1: TXN0003593 | EHG1: TXN0003594 | EHH1: TXN0003595 | EHI1: TXN0003596 | EHJ1: TXN0003597 | EHK1: TXN0003598 | EHL1: TXN0003599 | EHM1: TXN0003600 | EHN1: TXN0003601 | EHO1: TXN0003602 | EHP1: TXN0003603 | EHQ1: TXN0003604 | EHR1: TXN0003605 | EHS1: TXN0003606 | EHT1: TXN0003607 | EHU1: TXN0003608 | EHV1: TXN0003609 | EHW1: TXN0003610 | EHX1: TXN0003611 | EHY1: TXN0003612 | EHZ1: TXN0003613 | EIA1: TXN0003614 | EIB1: TXN0003615 | EIC1: TXN0003616 | EID1: TXN0003617 | EIE1: TXN0003618 | EIF1: TXN0003619 | EIG1: TXN0003620 | EIH1: TXN0003621 | EII1: TXN0003622 | EIJ1: TXN0003623 | EIK1: TXN0003624 | EIL1: TXN0003625 | EIM1: TXN0003626 | EIN1: TXN0003627 | EIO1: TXN0003628 | EIP1: TXN0003629 | EIQ1: TXN0003630 | EIR1: TXN0003631 | EIS1: TXN0003632 | EIT1: TXN0003633 | EIU1: TXN0003634 | EIV1: TXN0003635 | EIW1: TXN0003636 | EIX1: TXN0003637 | EIY1: TXN0003638 | EIZ1: TXN0003639 | EJA1: TXN0003640 | EJB1: TXN0003641 | EJC1: TXN0003642 | EJD1: TXN0003643 | EJE1: TXN0003644 | EJF1: TXN0003645 | EJG1: TXN0003646 | EJH1: TXN0003647 | EJI1: TXN0003648 | EJJ1: TXN0003649 | EJK1: TXN0003650 | EJL1: TXN0003651 | EJM1: TXN0003652 | EJN1: TXN0003653 | EJO1: TXN0003654 | EJP1: TXN0003655 | EJQ1: TXN0003656 | EJR1: TXN0003657 | EJS1: TXN0003658 | EJT1: TXN0003659 | EJU1: TXN0003660 | EJV1: TXN0003661 | EJW1: TXN0003662 | EJX1: TXN0003663 | EJY1: TXN0003664 | EJZ1: TXN0003665 | EKA1: TXN0003666 | EKB1: TXN0003667 | EKC1: TXN0003668 | EKD1: TXN0003669 | EKE1: TXN0003670 | EKF1: TXN0003671 | EKG1: TXN0003672 | EKH1: TXN0003673 | EKI1: TXN0003674 | EKJ1: TXN0003675 | EKK1: TXN0003676 | EKL1: TXN0003677 | EKM1: TXN0003678 | EKN1: TXN0003679 | EKO1: TXN0003680 | EKP1: TXN0003681 | EKQ1: TXN0003682 | EKR1: TXN0003683 | EKS1: TXN0003684 | EKT1: TXN0003685 | EKU1: TXN0003686 | EKV1: TXN0003687 | EKW1: TXN0003688 | EKX1: TXN0003689 | EKY1: TXN0003690 | EKZ1: TXN0003691 | ELA1: TXN0003692 | ELB1: TXN0003693 | ELC1: TXN0003694 | ELD1: TXN0003695 | ELE1: TXN0003696 | ELF1: TXN0003697 | ELG1: TXN0003698 | ELH1: TXN0003699 | ELI1: TXN0003700 | ELJ1: TXN0003701 | ELK1: TXN0003702 | ELL1: TXN0003703 | ELM1: TXN0003704 | ELN1: TXN0003705 | ELO1: TXN0003706 | ELP1: TXN0003707 | ELQ1: TXN0003708 | ELR1: TXN0003709 | ELS1: TXN0003710 | ELT1: TXN0003711 | ELU1: TXN0003712 | ELV1: TXN0003713 | ELW1: TXN0003714 | ELX1: TXN0003715 | ELY1: TXN0003716 | ELZ1: TXN0003717 | EMA1: TXN0003718 | EMB1: TXN0003719 | EMC1: TXN0003720 | EMD1: TXN0003721 | EME1: TXN0003722 | EMF1: TXN0003723 | EMG1: TXN0003724 | EMH1: TXN0003725 | EMI1: TXN0003726 | EMJ1: TXN0003727 | EMK1: TXN0003728 | EML1: TXN0003729 | EMM1: TXN0003730 | EMN1: TXN0003731 | EMO1: TXN0003732 | EMP1: TXN0003733 | EMQ1: TXN0003734 | EMR1: TXN0003735 | EMS1: TXN0003736 | EMT1: TXN0003737 | EMU1: TXN0003738 | EMV1: TXN0003739 | EMW1: TXN0003740 | EMX1: TXN0003741 | EMY1: TXN0003742 | EMZ1: TXN0003743 | ENA1: TXN0003744 | ENB1: TXN0003745 | ENC1: TXN0003746 | END1: TXN0003747 | ENE1: TXN0003748 | ENF1: TXN0003749 | ENG1: TXN0003750 | ENH1: TXN0003751 | ENI1: TXN0003752 | ENJ1: TXN0003753 | ENK1: TXN0003754 | ENL1: TXN0003755 | ENM1: TXN0003756 | ENN1: TXN0003757 | ENO1: TXN0003758 | ENP1: TXN0003759 | ENQ1: TXN0003760 | ENR1: TXN0003761 | ENS1: TXN0003762 | ENT1: TXN0003763 | ENU1: TXN0003764 | ENV1: TXN0003765 | ENW1: TXN0003766 | ENX1: TXN0003767 | ENY1: TXN0003768 | ENZ1: TXN0003769 | EOA1: TXN0003770 | EOB1: TXN0003771 | EOC1: TXN0003772 | EOD1: TXN0003773 | EOE1: TXN0003774 | EOF1: TXN0003775 | EOG1: TXN0003776 | EOH1: TXN0003777 | EOI1: TXN0003778 | EOJ1: TXN0003779 | EOK1: TXN0003780 | EOL1: TXN0003781 | EOM1: TXN0003782 | EON1: TXN0003783 | EOO1: TXN0003784 | EOP1: TXN0003785 | EOQ1: TXN0003786 | EOR1: TXN0003787 | EOS1: TXN0003788 | EOT1: TXN0003789 | EOU1: TXN0003790 | EOV1: TXN0003791 | EOW1: TXN0003792 | EOX1: TXN0003793 | EOY1: TXN0003794 | EOZ1: TXN0003795 | EPA1: TXN0003796 | EPB1: TXN0003797 | EPC1: TXN0003798 | EPD1: TXN0003799 | EPE1: TXN0003800 | EPF1: TXN0003801 | EPG1: TXN0003802 | EPH1: TXN0003803 | EPI1: TXN0003804 | EPJ1: TXN0003805 | EPK1: TXN0003806 | EPL1: TXN0003807 | EPM1: TXN0003808 | EPN1: TXN0003809 | EPO1: TXN0003810 | EPP1: TXN0003811 | EPQ1: TXN0003812 | EPR1: TXN0003813 | EPS1: TXN0003814 | EPT1: TXN0003815 | EPU1: TXN0003816 | EPV1: TXN0003817 | EPW1: TXN0003818 | EPX1: TXN0003819 | EPY1: TXN0003820 | EPZ1: TXN0003821 | EQA1: TXN0003822 | EQB1: TXN0003823 | EQC1: TXN0003824 | EQD1: TXN0003825 | EQE1: TXN0003826 | EQF1: TXN0003827 | EQG1: TXN0003828 | EQH1: TXN0003829 | EQI1: TXN0003830 | EQJ1: TXN0003831 | EQK1: TXN0003832 | EQL1: TXN0003833 | EQM1: TXN0003834 | EQN1: TXN0003835 | EQO1: TXN0003836 | EQP1: TXN0003837 | EQQ1: TXN0003838 | EQR1: TXN0003839 | EQS1: TXN0003840 | EQT1: TXN0003841 | EQU1: TXN0003842 | EQV1: TXN0003843 | EQW1: TXN0003844 | EQX1: TXN0003845 | EQY1: TXN0003846 | EQZ1: TXN0003847 | ERA1: TXN0003848 | ERB1: TXN0003849 | ERC1: TXN0003850 | ERD1: TXN0003851 | ERE1: TXN0003852 | ERF1: TXN0003853 | ERG1: TXN0003854 | ERH1: TXN0003855 | ERI1: TXN0003856 | ERJ1: TXN0003857 | ERK1: TXN0003858 | ERL1: TXN0003859 | ERM1: TXN0003860 | ERN1: TXN0003861 | ERO1: TXN0003862 | ERP1: TXN0003863 | ERQ1: TXN0003864 | ERR1: TXN0003865 | ERS1: TXN0003866 | ERT1: TXN0003867 | ERU1: TXN0003868 | ERV1: TXN0003869 | ERW1: TXN0003870 | ERX1: TXN0003871 | ERY1: TXN0003872 | ERZ1: TXN0003873 | ESA1: TXN0003874 | ESB1: TXN0003875 | ESC1: TXN0003876 | ESD1: TXN0003877 | ESE1: TXN0003878 | ESF1: TXN0003879 | ESG1: TXN0003880 | ESH1: TXN0003881 | ESI1: TXN0003882 | ESJ1: TXN0003883 | ESK1: TXN0003884 | ESL1: TXN0003885 | ESM1: TXN0003886 | ESN1: TXN0003887 | ESO1: TXN0003888 | ESP1: TXN0003889 | ESQ1: TXN0003890 | ESR1: TXN0003891 | ESS1: TXN0003892 | EST1: TXN0003893 | ESU1: TXN0003894 | ESV1: TXN0003895 | ESW1: TXN0003896 | ESX1: TXN0003897 | ESY1: TXN0003898 | ESZ1: TXN0003899 | ETA1: TXN0003900 | ETB1: TXN0003901 | ETC1: TXN0003902 | ETD1: TXN0003903 | ETE1: TXN0003904 | ETF1: TXN0003905 | ETG1: TXN0003906 | ETH1: TXN0003907 | ETI1: TXN0003908 | ETJ1: TXN0003909 | ETK1: TXN0003910 | ETL1: TXN0003911 | ETM1: TXN0003912 | ETN1: TXN0003913 | ETO1: TXN0003914 | ETP1: TXN0003915 | ETQ1: TXN0003916 | ETR1: TXN0003917 | ETS1: TXN0003918 | ETT1: TXN0003919 | ETU1: TXN0003920 | ETV1: TXN0003921 | ETW1: TXN0003922 | ETX1: TXN0003923 | ETY1: TXN0003924 | ETZ1: TXN0003925 | EUA1: TXN0003926 | EUB1: TXN0003927 | EUC1: TXN0003928 | EUD1: TXN0003929 | EUE1: TXN0003930 | EUF1: TXN0003931 | EUG1: TXN0003932 | EUH1: TXN0003933 | EUI1: TXN0003934 | EUJ1: TXN0003935 | EUK1: TXN0003936 | EUL1: TXN0003937 | EUM1: TXN0003938 | EUN1: TXN0003939 | EUO1: TXN0003940 | EUP1: TXN0003941 | EUQ1: TXN0003942 | EUR1: TXN0003943 | EUS1: TXN0003944 | EUT1: TXN0003945 | EUU1: TXN0003946 | EUV1: TXN0003947 | EUW1: TXN0003948 | EUX1: TXN0003949 | EUY1: TXN0003950 | EUZ1: TXN0003951 | EVA1: TXN0003952 | EVB1: TXN0003953 | EVC1: TXN0003954 | EVD1: TXN0003955 | EVE1: TXN0003956 | EVF1: TXN0003957 | EVG1: TXN0003958 | EVH1: TXN0003959 | EVI1: TXN0003960 | EVJ1: TXN0003961 | EVK1: TXN0003962 | EVL1: TXN0003963 | EVM1: TXN0003964 | EVN1: TXN0003965 | EVO1: TXN0003966 | EVP1: TXN0003967 | EVQ1: TXN0003968 | EVR1: TXN0003969 | EVS1: TXN0003970 | EVT1: TXN0003971 | EVU1: TXN0003972 | EVV1: TXN0003973 | EVW1: TXN0003974 | EVX1: TXN0003975 | EVY1: TXN0003976 | EVZ1: TXN0003977 | EWA1: TXN0003978 | EWB1: TXN0003979 | EWC1: TXN0003980 | EWD1: TXN0003981 | EWE1: TXN0003982 | EWF1: TXN0003983 | EWG1: TXN0003984 | EWH1: TXN0003985 | EWI1: TXN0003986 | EWJ1: TXN0003987 | EWK1: TXN0003988 | EWL1: TXN0003989 | EWM1: TXN0003990 | EWN1: TXN0003991 | EWO1: TXN0003992 | EWP1: TXN0003993 | EWQ1: TXN0003994 | EWR1: TXN0003995 | EWS1: TXN0003996 | EWT1: TXN0003997 | EWU1: TXN0003998 | EWV1: TXN0003999 | EWW1: TXN0004000 | EWX1: TXN0004001 | EWY1: TXN0004002 | EWZ1: TXN0004003 | EXA1: TXN0004004 | EXB1: TXN0004005 | EXC1: TXN0004006 | EXD1: TXN0004007 | EXE1: TXN0004008 | EXF1: TXN0004009 | EXG1: TXN0004010 | EXH1: TXN0004011 | EXI1: TXN0004012 | EXJ1: TXN0004013 | EXK1: TXN0004014 | EXL1: TXN0004015 | EXM1: TXN0004016 | EXN1: TXN0004017 | EXO1: TXN0004018 | EXP1: TXN0004019 | EXQ1: TXN0004020 | EXR1: TXN0004021 | EXS1: TXN0004022 | EXT1: TXN0004023 | EXU1: TXN0004024 | EXV1: TXN0004025 | EXW1: TXN0004026 | EXX1: TXN0004027 | EXY1: TXN0004028 | EXZ1: TXN0004029 | EYA1: TXN0004030 | EYB1: TXN0004031 | EYC1: TXN0004032 | EYD1: TXN0004033 | EYE1: TXN0004034 | EYF1: TXN0004035 | EYG1: TXN0004036 | EYH1: TXN0004037 | EYI1: TXN0004038 | EYJ1: TXN0004039 | EYK1: TXN0004040 | EYL1: TXN0004041 | EYM1: TXN0004042 | EYN1: TXN0004043 | EYO1: TXN0004044 | EYP1: TXN0004045 | EYQ1: TXN0004046 | EYR1: TXN0004047 | EYS1: TXN0004048 | EYT1: TXN0004049 | EYU1: TXN0004050 | EYV1: TXN0004051 | EYW1: TXN0004052 | EYX1: TXN0004053 | EYY1: TXN0004054 | EYZ1: TXN0004055 | EZA1: TXN0004056 | EZB1: TXN0004057 | EZC1: TXN0004058 | EZD1: TXN0004059 | EZE1: TXN0004060 | EZF1: TXN0004061 | EZG1: TXN0004062 | EZH1: TXN0004063 | EZI1: TXN0004064 | EZJ1: TXN0004065 | EZK1: TXN0004066 | EZL1: TXN0004067 | EZM1: TXN0004068 | EZN1: TXN0004069 | EZO1: TXN0004070 | EZP1: TXN0004071 | EZQ1: TXN0004072 | EZR1: TXN0004073 | EZS1: TXN0004074 | EZT1: TXN0004075 | EZU1: TXN0004076 | EZV1: TXN0004077 | EZW1: TXN0004078 | EZX1: TXN0004079 | EZY1: TXN0004080 | EZZ1: TXN0004081 | FAA1: TXN0004082 | FAB1: TXN0004083 | FAC1: TXN0004084 | FAD1: TXN0004085 | FAE1: TXN0004086 | FAF1: TXN0004087 | FAG1: TXN0004088 | FAH1: TXN0004089 | FAI1: TXN0004090 | FAJ1: TXN0004091 | FAK1: TXN0004092 | FAL1: TXN0004093 | FAM1: TXN0004094 | FAN1: TXN0004095 | FAO1: TXN0004096 | FAP1: TXN0004097 | FAQ1: TXN0004098 | FAR1: TXN0004099 | FAS1: TXN0004100 | FAT1: TXN0004101 | FAU1: TXN0004102 | FAV1: TXN0004103 | FAW1: TXN0004104 | FAX1: TXN0004105 | FAY1: TXN0004106 | FAZ1: TXN0004107 | FBA1: TXN0004108 | FBB1: TXN0004109 | FBC1: TXN0004110 | FBD1: TXN0004111 | FBE1: TXN0004112 | FBF1: TXN0004113 | FBG1: TXN0004114 | FBH1: TXN0004115 | FBI1: TXN0004116 | FBJ1: TXN0004117 | FBK1: TXN0004118 | FBL1: TXN0004119 | FBM1: TXN0004120 | FBN1: TXN0004121 | FBO1: TXN0004122 | FBP1: TXN0004123 | FBQ1: TXN0004124 | FBR1: TXN0004125 | FBS1: TXN0004126 | FBT1: TXN0004127 | FBU1: TXN0004128 | FBV1: TXN0004129 | FBW1: TXN0004130 | FBX1: TXN0004131 | FBY1: TXN0004132 | FBZ1: TXN0004133 | FCA1: TXN0004134 | FCB1: TXN0004135 | FCC1: TXN0004136 | FCD1: TXN0004137 | FCE1: TXN0004138 | FCF1: TXN0004139 | FCG1: TXN0004140 | FCH1: TXN0004141 | FCI1: TXN0004142 | FCJ1: TXN0004143 | FCK1: TXN0004144 | FCL1: TXN0004145 | FCM1: TXN0004146 | FCN1: TXN0004147 | FCO1: TXN0004148 | FCP1: TXN0004149 | FCQ1: TXN0004150 | FCR1: TXN0004151 | FCS1: TXN0004152 | FCT1: TXN0004153 | FCU1: TXN0004154 | FCV1: TXN0004155 | FCW1: TXN0004156 | FCX1: TXN0004157 | FCY1: TXN0004158 | FCZ1: TXN0004159 | FDA1: TXN0004160 | FDB1: TXN0004161 | FDC1: TXN0004162 | FDD1: TXN0004163 | FDE1: TXN0004164 | FDF1: TXN0004165 | FDG1: TXN0004166 | FDH1: TXN0004167 | FDI1: TXN0004168 | FDJ1: TXN0004169 | FDK1: TXN0004170 | FDL1: TXN0004171 | FDM1: TXN0004172 | FDN1: TXN0004173 | FDO1: TXN0004174 | FDP1: TXN0004175 | FDQ1: TXN0004176 | FDR1: TXN0004177 | FDS1: TXN0004178 | FDT1: TXN0004179 | FDU1: TXN0004180 | FDV1: TXN0004181 | FDW1: TXN0004182 | FDX1: TXN0004183 | FDY1: TXN0004184 | FDZ1: TXN0004185 | FEA1: TXN0004186 | FEB1: TXN0004187 | FEC1: TXN0004188 | FED1: TXN0004189 | FEE1: TXN0004190 | FEF1: TXN0004191 | FEG1: TXN0004192 | FEH1: TXN0004193 | FEI1: TXN0004194 | FEJ1: TXN0004195 | FEK1: TXN0004196 | FEL1: TXN0004197 | FEM1: TXN0004198 | FEN1: TXN0004199 | FEO1: TXN0004200 | FEP1: TXN0004201 | FEQ1: TXN0004202 | FER1: TXN0004203 | FES1: TXN0004204 | FET1: TXN0004205 | FEU1: TXN0004206 | FEV1: TXN0004207 | FEW1: TXN0004208 | FEX1: TXN0004209 | FEY1: TXN0004210 | FEZ1: TXN0004211 | FFA1: TXN0004212 | FFB1: TXN0004213 | FFC1: TXN0004214 | FFD1: TXN0004215 | FFE1: TXN0004216 | FFF1: TXN0004217 | FFG1: TXN0004218 | FFH1: TXN0004219 | FFI1: TXN0004220 | FFJ1: TXN0004221 | FFK1: TXN0004222 | FFL1: TXN0004223 | FFM1: TXN0004224 | FFN1: TXN0004225 | FFO1: TXN0004226 | FFP1: TXN0004227 | FFQ1: TXN0004228 | FFR1: TXN0004229 | FFS1: TXN0004230 | FFT1: TXN0004231 | FFU1: TXN0004232 | FFV1: TXN0004233 | FFW1: TXN0004234 | FFX1: TXN0004235 | FFY1: TXN0004236 | FFZ1: TXN0004237 | FGA1: TXN0004238 | FGB1: TXN0004239 | FGC1: TXN0004240 | FGD1: TXN0004241 | FGE1: TXN0004242 | FGF1: TXN0004243 | FGG1: TXN0004244 | FGH1: TXN0004245 | FGI1: TXN0004246 | FGJ1: TXN0004247 | FGK1: TXN0004248 | FGL1: TXN0004249 | FGM1: TXN0004250 | FGN1: TXN0004251 | FGO1: TXN0004252 | FGP1: TXN0004253 | FGQ1: TXN0004254 | FGR1: TXN0004255 | FGS1: TXN0004256 | FGT1: TXN0004257 | FGU1: TXN0004258 | FGV1: TXN0004259 | FGW1: TXN0004260 | FGX1: TXN0004261 | FGY1: TXN0004262 | FGZ1: TXN0004263 | FHA1: TXN0004264 | FHB1: TXN0004265 | FHC1: TXN0004266 | FHD1: TXN0004267 | FHE1: TXN0004268 | FHF1: TXN0004269 | FHG1: TXN0004270 | FHH1: TXN0004271 | FHI1: TXN0004272 | FHJ1: TXN0004273 | FHK1: TXN0004274 | FHL1: TXN0004275 | FHM1: TXN0004276 | FHN1: TXN0004277 | FHO1: TXN0004278 | FHP1: TXN0004279 | FHQ1: TXN0004280 | FHR1: TXN0004281 | FHS1: TXN0004282 | FHT1: TXN0004283 | FHU1: TXN0004284 | FHV1: TXN0004285 | FHW1: TXN0004286 | FHX1: TXN0004287 | FHY1: TXN0004288 | FHZ1: TXN0004289 | FIA1: TXN0004290 | FIB1: TXN0004291 | FIC1: TXN0004292 | FID1: TXN0004293 | FIE1: TXN0004294 | FIF1: TXN0004295 | FIG1: TXN0004296 | FIH1: TXN0004297 | FII1: TXN0004298 | FIJ1: TXN0004299 | FIK1: TXN0004300 | FIL1: TXN0004301 | FIM1: TXN0004302 | FIN1: TXN0004303 | FIO1: TXN0004304 | FIP1: TXN0004305 | FIQ1: TXN0004306 | FIR1: TXN0004307 | FIS1: TXN0004308 | FIT1: TXN0004309 | FIU1: TXN0004310 | FIV1: TXN0004311 | FIW1: TXN0004312 | FIX1: TXN0004313 | FIY1: TXN0004314 | FIZ1: TXN0004315 | FJA1: TXN0004316 | FJB1: TXN0004317 | FJC1: TXN0004318 | FJD1: TXN0004319 | FJE1: TXN0004320 | FJF1: TXN0004321 | FJG1: TXN0004322 | FJH1: TXN0004323 | FJI1: TXN0004324 | FJJ1: TXN0004325 | FJK1: TXN0004326 | FJL1: TXN0004327 | FJM1: TXN0004328 | FJN1: TXN0004329 | FJO1: TXN0004330 | FJP1: TXN0004331 | FJQ1: TXN0004332 | FJR1: TXN0004333 | FJS1: TXN0004334 | FJT1: TXN0004335 | FJU1: TXN0004336 | FJV1: TXN0004337 | FJW1: TXN0004338 | FJX1: TXN0004339 | FJY1: TXN0004340 | FJZ1: TXN0004341 | FKA1: TXN0004342 | FKB1: TXN0004343 | FKC1: TXN0004344 | FKD1: TXN0004345 | FKE1: TXN0004346 | FKF1: TXN0004347 | FKG1: TXN0004348 | FKH1: TXN0004349 | FKI1: TXN0004350 | FKJ1: TXN0004351 | FKK1: TXN0004352 | FKL1: TXN0004353 | FKM1: TXN0004354 | FKN1: TXN0004355 | FKO1: TXN0004356 | FKP1: TXN0004357 | FKQ1: TXN0004358 | FKR1: TXN0004359 | FKS1: TXN0004360 | FKT1: TXN0004361 | FKU1: TXN0004362 | FKV1: TXN0004363 | FKW1: TXN0004364 | FKX1: TXN0004365 | FKY1: TXN0004366 | FKZ1: TXN0004367 | FLA1: TXN0004368 | FLB1: TXN0004369 | FLC1: TXN0004370 | FLD1: TXN0004371 | FLE1: TXN0004372 | FLF1: TXN0004373 | FLG1: TXN0004374 | FLH1: TXN0004375 | FLI1: TXN0004376 | FLJ1: TXN0004377 | FLK1: TXN0004378 | FLL1: TXN0004379 | FLM1: TXN0004380 | FLN1: TXN0004381 | FLO1: TXN0004382 | FLP1: TXN0004383 | FLQ1: TXN0004384 | FLR1: TXN0004385 | FLS1: TXN0004386 | FLT1: TXN0004387 | FLU1: TXN0004388 | FLV1: TXN0004389 | FLW1: TXN0004390 | FLX1: TXN0004391 | FLY1: TXN0004392 | FLZ1: TXN0004393 | FMA1: TXN0004394 | FMB1: TXN0004395 | FMC1: TXN0004396 | FMD1: TXN0004397 | FME1: TXN0004398 | FMF1: TXN0004399 | FMG1: TXN0004400 | FMH1: TXN0004401 | FMI1: TXN0004402 | FMJ1: TXN0004403 | FMK1: TXN0004404 | FML1: TXN0004405 | FMM1: TXN0004406 | FMN1: TXN0004407 | FMO1: TXN0004408 | FMP1: TXN0004409 | FMQ1: TXN0004410 | FMR1: TXN0004411 | FMS1: TXN0004412 | FMT1: TXN0004413 | FMU1: TXN0004414 | FMV1: TXN0004415 | FMW1: TXN0004416 | FMX1: TXN0004417 | FMY1: TXN0004418 | FMZ1: TXN0004419 | FNA1: TXN0004420 | FNB1: TXN0004421 | FNC1: TXN0004422 | FND1: TXN0004423 | FNE1: TXN0004424 | FNF1: TXN0004425 | FNG1: TXN0004426 | FNH1: TXN0004427 | FNI1: TXN0004428 | FNJ1: TXN0004429 | FNK1: TXN0004430 | FNL1: TXN0004431 | FNM1: TXN0004432 | FNN1: TXN0004433 | FNO1: TXN0004434 | FNP1: TXN0004435 | FNQ1: TXN0004436 | FNR1: TXN0004437 | FNS1: TXN0004438 | FNT1: TXN0004439 | FNU1: TXN0004440 | FNV1: TXN0004441 | FNW1: TXN0004442 | FNX1: TXN0004443 | FNY1: TXN0004444 | FNZ1: TXN0004445 | FOA1: TXN0004446 | FOB1: TXN0004447 | FOC1: TXN0004448 | FOD1: TXN0004449 | FOE1: TXN0004450 | FOF1: TXN0004451 | FOG1: TXN0004452 | FOH1: TXN0004453 | FOI1: TXN0004454 | FOJ1: TXN0004455 | FOK1: TXN0004456 | FOL1: TXN0004457 | FOM1: TXN0004458 | FON1: TXN0004459 | FOO1: TXN0004460 | FOP1: TXN0004461 | FOQ1: TXN0004462 | FOR1: TXN0004463 | FOS1: TXN0004464 | FOT1: TXN0004465 | FOU1: TXN0004466 | FOV1: TXN0004467 | FOW1: TXN0004468 | FOX1: TXN0004469 | FOY1: TXN0004470 | FOZ1: TXN0004471 | FPA1: TXN0004472 | FPB1: TXN0004473 | FPC1: TXN0004474 | FPD1: TXN0004475 | FPE1: TXN0004476 | FPF1: TXN0004477 | FPG1: TXN0004478 | FPH1: TXN0004479 | FPI1: TXN0004480 | FPJ1: TXN0004481 | FPK1: TXN0004482 | FPL1: TXN0004483 | FPM1: TXN0004484 | FPN1: TXN0004485 | FPO1: TXN0004486 | FPP1: TXN0004487 | FPQ1: TXN0004488 | FPR1: TXN0004489 | FPS1: TXN0004490 | FPT1: TXN0004491 | FPU1: TXN0004492 | FPV1: TXN0004493 | FPW1: TXN0004494 | FPX1: TXN0004495 | FPY1: TXN0004496 | FPZ1: TXN0004497 | FQA1: TXN0004498 | FQB1: TXN0004499 | FQC1: TXN0004500 | FQD1: TXN0004501 | FQE1: TXN0004502 | FQF1: TXN0004503 | FQG1: TXN0004504 | FQH1: TXN0004505 | FQI1: TXN0004506 | FQJ1: TXN0004507 | FQK1: TXN0004508 | FQL1: TXN0004509 | FQM1: TXN0004510 | FQN1: TXN0004511 | FQO1: TXN0004512 | FQP1: TXN0004513 | FQQ1: TXN0004514 | FQR1: TXN0004515 | FQS1: TXN0004516 | FQT1: TXN0004517 | FQU1: TXN0004518 | FQV1: TXN0004519 | FQW1: TXN0004520 | FQX1: TXN0004521 | FQY1: TXN0004522 | FQZ1: TXN0004523 | FRA1: TXN0004524 | FRB1: TXN0004525 | FRC1: TXN0004526 | FRD1: TXN0004527 | FRE1: TXN0004528 | FRF1: TXN0004529 | FRG1: TXN0004530 | FRH1: TXN0004531 | FRI1: TXN0004532 | FRJ1: TXN0004533 | FRK1: TXN0004534 | FRL1: TXN0004535 | FRM1: TXN0004536 | FRN1: TXN0004537 | FRO1: TXN0004538 | FRP1: TXN0004539 | FRQ1: TXN0004540 | FRR1: TXN0004541 | FRS1: TXN0004542 | FRT1: TXN0004543 | FRU1: TXN0004544 | FRV1: TXN0004545 | FRW1: TXN0004546 | FRX1: TXN0004547 | FRY1: TXN0004548 | FRZ1: TXN0004549 | FSA1: TXN0004550 | FSB1: TXN0004551 | FSC1: TXN0004552 | FSD1: TXN0004553 | FSE1: TXN0004554 | FSF1: TXN0004555 | FSG1: TXN0004556 | FSH1: TXN0004557 | FSI1: TXN0004558 | FSJ1: TXN0004559 | FSK1: TXN0004560 | FSL1: TXN0004561 | FSM1: TXN0004562 | FSN1: TXN0004563 | FSO1: TXN0004564 | FSP1: TXN0004565 | FSQ1: TXN0004566 | FSR1: TXN0004567 | FSS1: TXN0004568 | FST1: TXN0004569 | FSU1: TXN0004570 | FSV1: TXN0004571 | FSW1: TXN0004572 | FSX1: TXN0004573 | FSY1: TXN0004574 | FSZ1: TXN0004575 | FTA1: TXN0004576 | FTB1: TXN0004577 | FTC1: TXN0004578 | FTD1: TXN0004579 | FTE1: TXN0004580 | FTF1: TXN0004581 | FTG1: TXN0004582 | FTH1: TXN0004583 | FTI1: TXN0004584 | FTJ1: TXN0004585 | FTK1: TXN0004586 | FTL1: TXN0004587 | FTM1: TXN0004588 | FTN1: TXN0004589 | FTO1: TXN0004590 | FTP1: TXN0004591 | FTQ1: TXN0004592 | FTR1: TXN0004593 | FTS1: TXN0004594 | FTT1: TXN0004595 | FTU1: TXN0004596 | FTV1: TXN0004597 | FTW1: TXN0004598 | FTX1: TXN0004599 | FTY1: TXN0004600 | FTZ1: TXN0004601 | FUA1: TXN0004602 | FUB1: TXN0004603 | FUC1: TXN0004604 | FUD1: TXN0004605 | FUE1: TXN0004606 | FUF1: TXN0004607 | FUG1: TXN0004608 | FUH1: TXN0004609 | FUI1: TXN0004610 | FUJ1: TXN0004611 | FUK1: TXN0004612 | FUL1: TXN0004613 | FUM1: TXN0004614 | FUN1: TXN0004615 | FUO1: TXN0004616 | FUP1: TXN0004617 | FUQ1: TXN0004618 | FUR1: TXN0004619 | FUS1: TXN0004620 | FUT1: TXN0004621 | FUU1: TXN0004622 | FUV1: TXN0004623 | FUW1: TXN0004624 | FUX1: TXN0004625 | FUY1: TXN0004626 | FUZ1: TXN0004627 | FVA1: TXN0004628 | FVB1: TXN0004629 | FVC1: TXN0004630 | FVD1: TXN0004631 | FVE1: TXN0004632 | FVF1: TXN0004633 | FVG1: TXN0004634 | FVH1: TXN0004635 | FVI1: TXN0004636 | FVJ1: TXN0004637 | FVK1: TXN0004638 | FVL1: TXN0004639 | FVM1: TXN0004640 | FVN1: TXN0004641 | FVO1: TXN0004642 | FVP1: TXN0004643 | FVQ1: TXN0004644 | FVR1: TXN0004645 | FVS1: TXN0004646 | FVT1: TXN0004647 | FVU1: TXN0004648 | FVV1: TXN0004649 | FVW1: TXN0004650 | FVX1: TXN0004651 | FVY1: TXN0004652 | FVZ1: TXN0004653 | FWA1: TXN0004654 | FWB1: TXN0004655 | FWC1: TXN0004656 | FWD1: TXN0004657 | FWE1: TXN0004658 | FWF1: TXN0004659 | FWG1: TXN0004660 | FWH1: TXN0004661 | FWI1: TXN0004662 | FWJ1: TXN0004663 | FWK1: TXN0004664 | FWL1: TXN0004665 | FWM1: TXN0004666 | FWN1: TXN0004667 | FWO1: TXN0004668 | FWP1: TXN0004669 | FWQ1: TXN0004670 | FWR1: TXN0004671 | FWS1: TXN0004672 | FWT1: TXN0004673 | FWU1: TXN0004674 | FWV1: TXN0004675 | FWW1: TXN0004676 | FWX1: TXN0004677 | FWY1: TXN0004678 | FWZ1: TXN0004679 | FXA1: TXN0004680 | FXB1: TXN0004681 | FXC1: TXN0004682 | FXD1: TXN0004683 | FXE1: TXN0004684 | FXF1: TXN0004685 | FXG1: TXN0004686 | FXH1: TXN0004687 | FXI1: TXN0004688 | FXJ1: TXN0004689 | FXK1: TXN0004690 | FXL1: TXN0004691 | FXM1: TXN0004692 | FXN1: TXN0004693 | FXO1: TXN0004694 | FXP1: TXN0004695 | FXQ1: TXN0004696 | FXR1: TXN0004697 | FXS1: TXN0004698 | FXT1: TXN0004699 | FXU1: TXN0004700 | FXV1: TXN0004701 | FXW1: TXN0004702 | FXX1: TXN0004703 | FXY1: TXN0004704 | FXZ1: TXN0004705 | FYA1: TXN0004706 | FYB1: TXN0004707 | FYC1: TXN0004708 | FYD1: TXN0004709 | FYE1: TXN0004710 | FYF1: TXN0004711 | FYG1: TXN0004712 | FYH1: TXN0004713 | FYI1: TXN0004714 | FYJ1: TXN0004715 | FYK1: TXN0004716 | FYL1: TXN0004717 | FYM1: TXN0004718 | FYN1: TXN0004719 | FYO1: TXN0004720 | FYP1: TXN0004721 | FYQ1: TXN0004722 | FYR1: TXN0004723 | FYS1: TXN0004724 | FYT1: TXN0004725 | FYU1: TXN0004726 | FYV1: TXN0004727 | FYW1: TXN0004728 | FYX1: TXN0004729 | FYY1: TXN0004730 | FYZ1: TXN0004731 | FZA1: TXN0004732 | FZB1: TXN0004733 | FZC1: TXN0004734 | FZD1: TXN0004735 | FZE1: TXN0004736 | FZF1: TXN0004737 | FZG1: TXN0004738 | FZH1: TXN0004739 | FZI1: TXN0004740 | FZJ1: TXN0004741 | FZK1: TXN0004742 | FZL1: TXN0004743 | FZM1: TXN0004744 | FZN1: TXN0004745 | FZO1: TXN0004746 | FZP1: TXN0004747 | FZQ1: TXN0004748 | FZR1: TXN0004749 | FZS1: TXN0004750 | FZT1: TXN0004751 | FZU1: TXN0004752 | FZV1: TXN0004753 | FZW1: TXN0004754 | FZX1: TXN0004755 | FZY1: TXN0004756 | FZZ1: TXN0004757 | GAA1: TXN0004758 | GAB1: TXN0004759 | GAC1: TXN0004760 | GAD1: TXN0004761 | GAE1: TXN0004762 | GAF1: TXN0004763 | GAG1: TXN0004764 | GAH1: TXN0004765 | GAI1: TXN0004766 | GAJ1: TXN0004767 | GAK1: TXN0004768 | GAL1: TXN0004769 | GAM1: TXN0004770 | GAN1: TXN0004771 | GAO1: TXN0004772 | GAP1: TXN0004773 | GAQ1: TXN0004774 | GAR1: TXN0004775 | GAS1: TXN0004776 | GAT1: TXN0004777 | GAU1: TXN0004778 | GAV1: TXN0004779 | GAW1: TXN0004780 | GAX1: TXN0004781 | GAY1: TXN0004782 | GAZ1: TXN0004783 | GBA1: TXN0004784 | GBB1: TXN0004785 | GBC1: TXN0004786 | GBD1: TXN0004787 | GBE1: TXN0004788 | GBF1: TXN0004789 | GBG1: TXN0004790 | GBH1: TXN0004791 | GBI1: TXN0004792 | GBJ1: TXN0004793 | GBK1: TXN0004794 | GBL1: TXN0004795 | GBM1: TXN0004796 | GBN1: TXN0004797 | GBO1: TXN0004798 | GBP1: TXN0004799 | GBQ1: TXN0004800 | GBR1: TXN0004801 | GBS1: TXN0004802 | GBT1: TXN0004803 | GBU1: TXN0004804 | GBV1: TXN0004805 | GBW1: TXN0004806 | GBX1: TXN0004807 | GBY1: TXN0004808 | GBZ1: TXN0004809 | GCA1: TXN0004810 | GCB1: TXN0004811 | GCC1: TXN0004812 | GCD1: TXN0004813 | GCE1: TXN0004814 | GCF1: TXN0004815 | GCG1: TXN0004816 | GCH1: TXN0004817 | GCI1: TXN0004818 | GCJ1: TXN0004819 | GCK1: TXN0004820 | GCL1: TXN0004821 | GCM1: TXN0004822 | GCN1: TXN0004823 | GCO1: TXN0004824 | GCP1: TXN0004825 | GCQ1: TXN0004826 | GCR1: TXN0004827 | GCS1: TXN0004828 | GCT1: TXN0004829 | GCU1: TXN0004830 | GCV1: TXN0004831 | GCW1: TXN0004832 | GCX1: TXN0004833 | GCY1: TXN0004834 | GCZ1: TXN0004835 | GDA1: TXN0004836 | GDB1: TXN0004837 | GDC1: TXN0004838 | GDD1: TXN0004839 | GDE1: TXN0004840 | GDF1: TXN0004841 | GDG1: TXN0004842 | GDH1: TXN0004843 | GDI1: TXN0004844 | GDJ1: TXN0004845 | GDK1: TXN0004846 | GDL1: TXN0004847 | GDM1: TXN0004848 | GDN1: TXN0004849 | GDO1: TXN0004850 | GDP1: TXN0004851 | GDQ1: TXN0004852 | GDR1: TXN0004853 | GDS1: TXN0004854 | GDT1: TXN0004855 | GDU1: TXN0004856 | GDV1: TXN0004857 | GDW1: TXN0004858 | GDX1: TXN0004859 | GDY1: TXN0004860 | GDZ1: TXN0004861 | GEA1: TXN0004862 | GEB1: TXN0004863 | GEC1: TXN0004864 | GED1: TXN0004865 | GEE1: TXN0004866 | GEF1: TXN0004867 | GEG1: TXN0004868 | GEH1: TXN0004869 | GEI1: TXN0004870 | GEJ1: TXN0004871 | GEK1: TXN0004872 | GEL1: TXN0004873 | GEM1: TXN0004874 | GEN1: TXN0004875 | GEO1: TXN0004876 | GEP1: TXN0004877 | GEQ1: TXN0004878 | GER1: TXN0004879 | GES1: TXN0004880 | GET1: TXN0004881 | GEU1: TXN0004882 | GEV1: TXN0004883 | GEW1: TXN0004884 | GEX1: TXN0004885 | GEY1: TXN0004886 | GEZ1: TXN0004887 | GFA1: TXN0004888 | GFB1: TXN0004889 | GFC1: TXN0004890 | GFD1: TXN0004891 | GFE1: TXN0004892 | GFF1: TXN0004893 | GFG1: TXN0004894 | GFH1: TXN0004895 | GFI1: TXN0004896 | GFJ1: TXN0004897 | GFK1: TXN0004898 | GFL1: TXN0004899 | GFM1: TXN0004900 | GFN1: TXN0004901 | GFO1: TXN0004902 | GFP1: TXN0004903 | GFQ1: TXN0004904 | GFR1: TXN0004905 | GFS1: TXN0004906 | GFT1: TXN0004907 | GFU1: TXN0004908 | GFV1: TXN0004909 | GFW1: TXN0004910 | GFX1: TXN0004911 | GFY1: TXN0004912 | GFZ1: TXN0004913 | GGA1: TXN0004914 | GGB1: TXN0004915 | GGC1: TXN0004916 | GGD1: TXN0004917 | GGE1: TXN0004918 | GGF1: TXN0004919 | GGG1: TXN0004920 | GGH1: TXN0004921 | GGI1: TXN0004922 | GGJ1: TXN0004923 | GGK1: TXN0004924 | GGL1: TXN0004925 | GGM1: TXN0004926 | GGN1: TXN0004927 | GGO1: TXN0004928 | GGP1: TXN0004929 | GGQ1: TXN0004930 | GGR1: TXN0004931 | GGS1: TXN0004932 | GGT1: TXN0004933 | GGU1: TXN0004934 | GGV1: TXN0004935 | GGW1: TXN0004936 | GGX1: TXN0004937 | GGY1: TXN0004938 | GGZ1: TXN0004939 | GHA1: TXN0004940 | GHB1: TXN0004941 | GHC1: TXN0004942 | GHD1: TXN0004943 | GHE1: TXN0004944 | GHF1: TXN0004945 | GHG1: TXN0004946 | GHH1: TXN0004947 | GHI1: TXN0004948 | GHJ1: TXN0004949 | GHK1: TXN0004950 | GHL1: TXN0004951 | GHM1: TXN0004952 | GHN1: TXN0004953 | GHO1: TXN0004954 | GHP1: TXN0004955 | GHQ1: TXN0004956 | GHR1: TXN0004957 | GHS1: TXN0004958 | GHT1: TXN0004959 | GHU1: TXN0004960 | GHV1: TXN0004961 | GHW1: TXN0004962 | GHX1: TXN0004963 | GHY1: TXN0004964 | GHZ1: TXN0004965 | GIA1: TXN0004966 | GIB1: TXN0004967 | GIC1: TXN0004968 | GID1: TXN0004969 | GIE1: TXN0004970 | GIF1: TXN0004971 | GIG1: TXN0004972 | GIH1: TXN0004973 | GII1: TXN0004974 | GIJ1: TXN0004975 | GIK1: TXN0004976 | GIL1: TXN0004977 | GIM1: TXN0004978 | GIN1: TXN0004979 | GIO1: TXN0004980 | GIP1: TXN0004981 | GIQ1: TXN0004982 | GIR1: TXN0004983 | GIS1: TXN0004984 | GIT1: TXN0004985 | GIU1: TXN0004986 | GIV1: TXN0004987 | GIW1: TXN0004988 | GIX1: TXN0004989 | GIY1: TXN0004990 | GIZ1: TXN0004991 | GJA1: TXN0004992 | GJB1: TXN0004993 | GJC1: TXN0004994 | GJD1: TXN0004995 | GJE1: TXN0004996 | GJF1: TXN0004997 | GJG1: TXN0004998 | GJH1: TXN0004999 | GJI1: TXN0005000 | GJJ1: TXN0005001 | GJK1: TXN0005002 | GJL1: TXN0005003 | GJM1: TXN0005004 | GJN1: TXN0005005 | GJO1: TXN0005006 | GJP1: TXN0005007 | GJQ1: TXN0005008 | GJR1: TXN0005009 | GJS1: TXN0005010 | GJT1: TXN0005011 | GJU1: TXN0005012 | GJV1: TXN0005013 | GJW1: TXN0005014 | GJX1: TXN0005015 | GJY1: TXN0005016 | GJZ1: TXN0005017 | GKA1: TXN0005018 | GKB1: TXN0005019 | GKC1: TXN0005020 | GKD1: TXN0005021 | GKE1: TXN0005022 | GKF1: TXN0005023 | GKG1: TXN0005024 | GKH1: TXN0005025 | GKI1: TXN0005026 | GKJ1: TXN0005027 | GKK1: TXN0005028 | GKL1: TXN0005029 | GKM1: TXN0005030 | GKN1: TXN0005031 | GKO1: TXN0005032 | GKP1: TXN0005033 | GKQ1: TXN0005034 | GKR1: TXN0005035 | GKS1: TXN0005036 | GKT1: TXN0005037 | GKU1: TXN0005038 | GKV1: TXN0005039 | GKW1: TXN0005040 | GKX1: TXN0005041 | GKY1: TXN0005042 | GKZ1: TXN0005043 | GLA1: TXN0005044 | GLB1: TXN0005045 | GLC1: TXN0005046 | GLD1: TXN0005047 | GLE1: TXN0005048 | GLF1: TXN0005049 | GLG1: TXN0005050 | GLH1: TXN0005051 | GLI1: TXN0005052 | GLJ1: TXN0005053 | GLK1: TXN0005054 | GLL1: TXN0005055 | GLM1: TXN0005056 | GLN1: TXN0005057 | GLO1: TXN0005058 | GLP1: TXN0005059 | GLQ1: TXN0005060 | GLR1: TXN0005061 | GLS1: TXN0005062 | GLT1: TXN0005063 | GLU1: TXN0005064 | GLV1: TXN0005065 | GLW1: TXN0005066 | GLX1: TXN0005067 | GLY1: TXN0005068 | GLZ1: TXN0005069 | GMA1: TXN0005070 | GMB1: TXN0005071 | GMC1: TXN0005072 | GMD1: TXN0005073 | GME1: TXN0005074 | GMF1: TXN0005075 | GMG1: TXN0005076 | GMH1: TXN0005077 | GMI1: TXN0005078 | GMJ1: TXN0005079 | GMK1: TXN0005080 | GML1: TXN0005081 | GMM1: TXN0005082 | GMN1: TXN0005083 | GMO1: TXN0005084 | GMP1: TXN0005085 | GMQ1: TXN0005086 | GMR1: TXN0005087 | GMS1: TXN0005088 | GMT1: TXN0005089 | GMU1: TXN0005090 | GMV1: TXN0005091 | GMW1: TXN0005092 | GMX1: TXN0005093 | GMY1: TXN0005094 | GMZ1: TXN0005095 | GNA1: TXN0005096 | GNB1: TXN0005097 | GNC1: TXN0005098 | GND1: TXN0005099 | GNE1: TXN0005100 | GNF1: TXN0005101 | GNG1: TXN0005102 | GNH1: TXN0005103 | GNI1: TXN0005104 | GNJ1: TXN0005105 | GNK1: TXN0005106 | GNL1: TXN0005107 | GNM1: TXN0005108 | GNN1: TXN0005109 | GNO1: TXN0005110 | GNP1: TXN0005111 | GNQ1: TXN0005112 | GNR1: TXN0005113 | GNS1: TXN0005114 | GNT1: TXN0005115 | GNU1: TXN0005116 | GNV1: TXN0005117 | GNW1: TXN0005118 | GNX1: TXN0005119 | GNY1: TXN0005120 | GNZ1: TXN0005121 | GOA1: TXN0005122 | GOB1: TXN0005123 | GOC1: TXN0005124 | GOD1: TXN0005125 | GOE1: TXN0005126 | GOF1: TXN0005127 | GOG1: TXN0005128 | GOH1: TXN0005129 | GOI1: TXN0005130 | GOJ1: TXN0005131 | GOK1: TXN0005132 | GOL1: TXN0005133 | GOM1: TXN0005134 | GON1: TXN0005135 | GOO1: TXN0005136 | GOP1: TXN0005137 | GOQ1: TXN0005138 | GOR1: TXN0005139 | GOS1: TXN0005140 | GOT1: TXN0005141 | GOU1: TXN0005142 | GOV1: TXN0005143 | GOW1: TXN0005144 | GOX1: TXN0005145 | GOY1: TXN0005146 | GOZ1: TXN0005147 | GPA1: TXN0005148 | GPB1: TXN0005149 | GPC1: TXN0005150 | GPD1: TXN0005151 | GPE1: TXN0005152 | GPF1: TXN0005153 | GPG1: TXN0005154 | GPH1: TXN0005155 | GPI1: TXN0005156 | GPJ1: TXN0005157 | GPK1: TXN0005158 | GPL1: TXN0005159 | GPM1: TXN0005160 | GPN1: TXN0005161 | GPO1: TXN0005162 | GPP1: TXN0005163 | GPQ1: TXN0005164 | GPR1: TXN0005165 | GPS1: TXN0005166 | GPT1: TXN0005167 | GPU1: TXN0005168 | GPV1: TXN0005169 | GPW1: TXN0005170 | GPX1: TXN0005171 | GPY1: TXN0005172 | GPZ1: TXN0005173 | GQA1: TXN0005174 | GQB1: TXN0005175 | GQC1: TXN0005176 | GQD1: TXN0005177 | GQE1: TXN0005178 | GQF1: TXN0005179 | GQG1: TXN0005180 | GQH1: TXN0005181 | GQI1: TXN0005182 | GQJ1: TXN0005183 | GQK1: TXN0005184 | GQL1: TXN0005185 | GQM1: TXN0005186 | GQN1: TXN0005187 | GQO1: TXN0005188 | GQP1: TXN0005189 | GQQ1: TXN0005190 | GQR1: TXN0005191 | GQS1: TXN0005192 | GQT1: TXN0005193 | GQU1: TXN0005194 | GQV1: TXN0005195 | GQW1: TXN0005196 | GQX1: TXN0005197 | GQY1: TXN0005198 | GQZ1: TXN0005199 | GRA1: TXN0005200 | GRB1: TXN0005201 | GRC1: TXN0005202 | GRD1: TXN0005203 | GRE1: TXN0005204 | GRF1: TXN0005205 | GRG1: TXN0005206 | GRH1: TXN0005207 | GRI1: TXN0005208 | GRJ1: TXN0005209 | GRK1: TXN0005210 | GRL1: TXN0005211 | GRM1: TXN0005212 | GRN1: TXN0005213 | GRO1: TXN0005214 | GRP1: TXN0005215 | GRQ1: TXN0005216 | GRR1: TXN0005217 | GRS1: TXN0005218 | GRT1: TXN0005219 | GRU1: TXN0005220 | GRV1: TXN0005221 | GRW1: TXN0005222 | GRX1: TXN0005223 | GRY1: TXN0005224 | GRZ1: TXN0005225 | GSA1: TXN0005226 | GSB1: TXN0005227 | GSC1: TXN0005228 | GSD1: TXN0005229 | GSE1: TXN0005230 | GSF1: TXN0005231 | GSG1: TXN0005232 | GSH1: TXN0005233 | GSI1: TXN0005234 | GSJ1: TXN0005235 | GSK1: TXN0005236 | GSL1: TXN0005237 | GSM1: TXN0005238 | GSN1: TXN0005239 | GSO1: TXN0005240 | GSP1: TXN0005241 | GSQ1: TXN0005242 | GSR1: TXN0005243 | GSS1: TXN0005244 | GST1: TXN0005245 | GSU1: TXN0005246 | GSV1: TXN0005247 | GSW1: TXN0005248 | GSX1: TXN0005249 | GSY1: TXN0005250 | GSZ1: TXN0005251 | GTA1: TXN0005252 | GTB1: TXN0005253 | GTC1: TXN0005254 | GTD1: TXN0005255 | GTE1: TXN0005256 | GTF1: TXN0005257 | GTG1: TXN0005258 | GTH1: TXN0005259 | GTI1: TXN0005260 | GTJ1: TXN0005261 | GTK1: TXN0005262 | GTL1: TXN0005263 | GTM1: TXN0005264 | GTN1: TXN0005265 | GTO1: TXN0005266 | GTP1: TXN0005267 | GTQ1: TXN0005268 | GTR1: TXN0005269 | GTS1: TXN0005270 | GTT1: TXN0005271 | GTU1: TXN0005272 | GTV1: TXN0005273 | GTW1: TXN0005274 | GTX1: TXN0005275 | GTY1: TXN0005276 | GTZ1: TXN0005277 | GUA1: TXN0005278 | GUB1: TXN0005279 | GUC1: TXN0005280 | GUD1: TXN0005281 | GUE1: TXN0005282 | GUF1: TXN0005283 | GUG1: TXN0005284 | GUH1: TXN0005285 | GUI1: TXN0005286 | GUJ1: TXN0005287 | GUK1: TXN0005288 | GUL1: TXN0005289 | GUM1: TXN0005290 | GUN1: TXN0005291 | GUO1: TXN0005292 | GUP1: TXN0005293 | GUQ1: TXN0005294 | GUR1: TXN0005295 | GUS1: TXN0005296 | GUT1: TXN0005297 | GUU1: TXN0005298 | GUV1: TXN0005299 | GUW1: TXN0005300 | GUX1: TXN0005301 | GUY1: TXN0005302 | GUZ1: TXN0005303 | GVA1: TXN0005304 | GVB1: TXN0005305 | GVC1: TXN0005306 | GVD1: TXN0005307 | GVE1: TXN0005308 | GVF1: TXN0005309 | GVG1: TXN0005310 | GVH1: TXN0005311 | GVI1: TXN0005312 | GVJ1: TXN0005313 | GVK1: TXN0005314 | GVL1: TXN0005315 | GVM1: TXN0005316 | GVN1: TXN0005317 | GVO1: TXN0005318 | GVP1: TXN0005319 | GVQ1: TXN0005320 | GVR1: TXN0005321 | GVS1: TXN0005322 | GVT1: TXN0005323 | GVU1: TXN0005324 | GVV1: TXN0005325 | GVW1: TXN0005326 | GVX1: TXN0005327 | GVY1: TXN0005328 | GVZ1: TXN0005329 | GWA1: TXN0005330 | GWB1: TXN0005331 | GWC1: TXN0005332 | GWD1: TXN0005333 | GWE1: TXN0005334 | GWF1: TXN0005335 | GWG1: TXN0005336 | GWH1: TXN0005337 | GWI1: TXN0005338 | GWJ1: TXN0005339 | GWK1: TXN0005340 | GWL1: TXN0005341 | GWM1: TXN0005342 | GWN1: TXN0005343 | GWO1: TXN0005344 | GWP1: TXN0005345 | GWQ1: TXN0005346 | GWR1: TXN0005347 | GWS1: TXN0005348 | GWT1: TXN0005349 | GWU1: TXN0005350 | GWV1: TXN0005351 | GWW1: TXN0005352 | GWX1: TXN0005353 | GWY1: TXN0005354 | GWZ1: TXN0005355 | GXA1: TXN0005356 | GXB1: TXN0005357 | GXC1: TXN0005358 | GXD1: TXN0005359 | GXE1: TXN0005360 | GXF1: TXN0005361 | GXG1: TXN0005362 | GXH1: TXN0005363 | GXI1: TXN0005364 | GXJ1: TXN0005365 | GXK1: TXN0005366 | GXL1: TXN0005367 | GXM1: TXN0005368 | GXN1: TXN0005369 | GXO1: TXN0005370 | GXP1: TXN0005371 | GXQ1: TXN0005372 | GXR1: TXN0005373 | GXS1: TXN0005374 | GXT1: TXN0005375 | GXU1: TXN0005376 | GXV1: TXN0005377 | GXW1: TXN0005378 | GXX1: TXN0005379 | GXY1: TXN0005380 | GXZ1: TXN0005381 | GYA1: TXN0005382 | GYB1: TXN0005383 | GYC1: TXN0005384 | GYD1: TXN0005385 | GYE1: TXN0005386 | GYF1: TXN0005387 | GYG1: TXN0005388 | GYH1: TXN0005389 | GYI1: TXN0005390 | GYJ1: TXN0005391 | GYK1: TXN0005392 | GYL1: TXN0005393 | GYM1: TXN0005394 | GYN1: TXN0005395 | GYO1: TXN0005396 | GYP1: TXN0005397 | GYQ1: TXN0005398 | GYR1: TXN0005399 | GYS1: TXN0005400 | GYT1: TXN0005401 | GYU1: TXN0005402 | GYV1: TXN0005403 | GYW1: TXN0005404 | GYX1: TXN0005405 | GYY1: TXN0005406 | GYZ1: TXN0005407 | GZA1: TXN0005408 | GZB1: TXN0005409 | GZC1: TXN0005410 | GZD1: TXN0005411 | GZE1: TXN0005412 | GZF1: TXN0005413 | GZG1: TXN0005414 | GZH1: TXN0005415 | GZI1: TXN0005416 | GZJ1: TXN0005417 | GZK1: TXN0005418 | GZL1: TXN0005419 | GZM1: TXN0005420 | GZN1: TXN0005421 | GZO1: TXN0005422 | GZP1: TXN0005423 | GZQ1: TXN0005424 | GZR1: TXN0005425 | GZS1: TXN0005426 | GZT1: TXN0005427 | GZU1: TXN0005428 | GZV1: TXN0005429 | GZW1: TXN0005430 | GZX1: TXN0005431 | GZY1: TXN0005432 | GZZ1: TXN0005433 | HAA1: TXN0005434 | HAB1: TXN0005435 | HAC1: TXN0005436 | HAD1: TXN0005437 | HAE1: TXN0005438 | HAF1: TXN0005439 | HAG1: TXN0005440 | HAH1: TXN0005441 | HAI1: TXN0005442 | HAJ1: TXN0005443 | HAK1: TXN0005444 | HAL1: TXN0005445 | HAM1: TXN0005446 | HAN1: TXN0005447 | HAO1: TXN0005448 | HAP1: TXN0005449 | HAQ1: TXN0005450 | HAR1: TXN0005451 | HAS1: TXN0005452 | HAT1: TXN0005453 | HAU1: TXN0005454 | HAV1: TXN0005455 | HAW1: TXN0005456 | HAX1: TXN0005457 | HAY1: TXN0005458 | HAZ1: TXN0005459 | HBA1: TXN0005460 | HBB1: TXN0005461 | HBC1: TXN0005462 | HBD1: TXN0005463 | HBE1: TXN0005464 | HBF1: TXN0005465 | HBG1: TXN0005466 | HBH1: TXN0005467 | HBI1: TXN0005468 | HBJ1: TXN0005469 | HBK1: TXN0005470 | HBL1: TXN0005471 | HBM1: TXN0005472 | HBN1: TXN0005473 | HBO1: TXN0005474 | HBP1: TXN0005475 | HBQ1: TXN0005476 | HBR1: TXN0005477 | HBS1: TXN0005478 | HBT1: TXN0005479 | HBU1: TXN0005480 | HBV1: TXN0005481 | HBW1: TXN0005482 | HBX1: TXN0005483 | HBY1: TXN0005484 | HBZ1: TXN0005485 | HCA1: TXN0005486 | HCB1: TXN0005487 | HCC1: TXN0005488 | HCD1: TXN0005489 | HCE1: TXN0005490 | HCF1: TXN0005491 | HCG1: TXN0005492 | HCH1: TXN0005493 | HCI1: TXN0005494 | HCJ1: TXN0005495 | HCK1: TXN0005496 | HCL1: TXN0005497 | HCM1: TXN0005498 | HCN1: TXN0005499 | HCO1: TXN0005500 | HCP1: TXN0005501 | HCQ1: TXN0005502 | HCR1: TXN0005503 | HCS1: TXN0005504 | HCT1: TXN0005505 | HCU1: TXN0005506 | HCV1: TXN0005507 | HCW1: TXN0005508 | HCX1: TXN0005509 | HCY1: TXN0005510 | HCZ1: TXN0005511 | HDA1: TXN0005512 | HDB1: TXN0005513 | HDC1: TXN0005514 | HDD1: TXN0005515 | HDE1: TXN0005516 | HDF1: TXN0005517 | HDG1: TXN0005518 | HDH1: TXN0005519 | HDI1: TXN0005520 | HDJ1: TXN0005521 | HDK1: TXN0005522 | HDL1: TXN0005523 | HDM1: TXN0005524 | HDN1: TXN0005525 | HDO1: TXN0005526 | HDP1: TXN0005527 | HDQ1: TXN0005528 | HDR1: TXN0005529 | HDS1: TXN0005530 | HDT1: TXN0005531 | HDU1: TXN0005532 | HDV1: TXN0005533 | HDW1: TXN0005534 | HDX1: TXN0005535 | HDY1: TXN0005536 | HDZ1: TXN0005537 | HEA1: TXN0005538 | HEB1: TXN0005539 | HEC1: TXN0005540 | HED1: TXN0005541 | HEE1: TXN0005542 | HEF1: TXN0005543 | HEG1: TXN0005544 | HEH1: TXN0005545 | HEI1: TXN0005546 | HEJ1: TXN0005547 | HEK1: TXN0005548 | HEL1: TXN0005549 | HEM1: TXN0005550 | HEN1: TXN0005551 | HEO1: TXN0005552 | HEP1: TXN0005553 | HEQ1: TXN0005554 | HER1: TXN0005555 | HES1: TXN0005556 | HET1: TXN0005557 | HEU1: TXN0005558 | HEV1: TXN0005559 | HEW1: TXN0005560 | HEX1: TXN0005561 | HEY1: TXN0005562 | HEZ1: TXN0005563 | HFA1: TXN0005564 | HFB1: TXN0005565 | HFC1: TXN0005566 | HFD1: TXN0005567 | HFE1: TXN0005568 | HFF1: TXN0005569 | HFG1: TXN0005570 | HFH1: TXN0005571 | HFI1: TXN0005572 | HFJ1: TXN0005573 | HFK1: TXN0005574 | HFL1: TXN0005575 | HFM1: TXN0005576 | HFN1: TXN0005577 | HFO1: TXN0005578 | HFP1: TXN0005579 | HFQ1: TXN0005580 | HFR1: TXN0005581 | HFS1: TXN0005582 | HFT1: TXN0005583 | HFU1: TXN0005584 | HFV1: TXN0005585 | HFW1: TXN0005586 | HFX1: TXN0005587 | HFY1: TXN0005588 | HFZ1: TXN0005589 | HGA1: TXN0005590 | HGB1: TXN0005591 | HGC1: TXN0005592 | HGD1: TXN0005593 | HGE1: TXN0005594 | HGF1: TXN0005595 | HGG1: TXN0005596 | HGH1: TXN0005597 | HGI1: TXN0005598 | HGJ1: TXN0005599 | HGK1: TXN0005600 | HGL1: TXN0005601 | HGM1: TXN0005602 | HGN1: TXN0005603 | HGO1: TXN0005604 | HGP1: TXN0005605 | HGQ1: TXN0005606 | HGR1: TXN0005607 | HGS1: TXN0005608 | HGT1: TXN0005609 | HGU1: TXN0005610 | HGV1: TXN0005611 | HGW1: TXN0005612 | HGX1: TXN0005613 | HGY1: TXN0005614 | HGZ1: TXN0005615 | HHA1: TXN0005616 | HHB1: TXN0005617 | HHC1: TXN0005618 | HHD1: TXN0005619 | HHE1: TXN0005620 | HHF1: TXN0005621 | HHG1: TXN0005622 | HHH1: TXN0005623 | HHI1: TXN0005624 | HHJ1: TXN0005625 | HHK1: TXN0005626 | HHL1: TXN0005627 | HHM1: TXN0005628 | HHN1: TXN0005629 | HHO1: TXN0005630 | HHP1: TXN0005631 | HHQ1: TXN0005632 | HHR1: TXN0005633 | HHS1: TXN0005634 | HHT1: TXN0005635 | HHU1: TXN0005636 | HHV1: TXN0005637 | HHW1: TXN0005638 | HHX1: TXN0005639 | HHY1: TXN0005640 | HHZ1: TXN0005641 | HIA1: TXN0005642 | HIB1: TXN0005643 | HIC1: TXN0005644 | HID1: TXN0005645 | HIE1: TXN0005646 | HIF1: TXN0005647 | HIG1: TXN0005648 | HIH1: TXN0005649 | HII1: TXN0005650 | HIJ1: TXN0005651 | HIK1: TXN0005652 | HIL1: TXN0005653 | HIM1: TXN0005654 | HIN1: TXN0005655 | HIO1: TXN0005656 | HIP1: TXN0005657 | HIQ1: TXN0005658 | HIR1: TXN0005659 | HIS1: TXN0005660 | HIT1: TXN0005661 | HIU1: TXN0005662 | HIV1: TXN0005663 | HIW1: TXN0005664 | HIX1: TXN0005665 | HIY1: TXN0005666 | HIZ1: TXN0005667 | HJA1: TXN0005668 | HJB1: TXN0005669 | HJC1: TXN0005670 | HJD1: TXN0005671 | HJE1: TXN0005672 | HJF1: TXN0005673 | HJG1: TXN0005674 | HJH1: TXN0005675 | HJI1: TXN0005676 | HJJ1: TXN0005677 | HJK1: TXN0005678 | HJL1: TXN0005679 | HJM1: TXN0005680 | HJN1: TXN0005681 | HJO1: TXN0005682 | HJP1: TXN0005683 | HJQ1: TXN0005684 | HJR1: TXN0005685 | HJS1: TXN0005686 | HJT1: TXN0005687 | HJU1: TXN0005688 | HJV1: TXN0005689 | HJW1: TXN0005690 | HJX1: TXN0005691 | HJY1: TXN0005692 | HJZ1: TXN0005693 | HKA1: TXN0005694 | HKB1: TXN0005695 | HKC1: TXN0005696 | HKD1: TXN0005697 | HKE1: TXN0005698 | HKF1: TXN0005699 | HKG1: TXN0005700 | HKH1: TXN0005701 | HKI1: TXN0005702 | HKJ1: TXN0005703 | HKK1: TXN0005704 | HKL1: TXN0005705 | HKM1: TXN0005706 | HKN1: TXN0005707 | HKO1: TXN0005708 | HKP1: TXN0005709 | HKQ1: TXN0005710 | HKR1: TXN0005711 | HKS1: TXN0005712 | HKT1: TXN0005713 | HKU1: TXN0005714 | HKV1: TXN0005715 | HKW1: TXN0005716 | HKX1: TXN0005717 | HKY1: TXN0005718 | HKZ1: TXN0005719 | HLA1: TXN0005720 | HLB1: TXN0005721 | HLC1: TXN0005722 | HLD1: TXN0005723 | HLE1: TXN0005724 | HLF1: TXN0005725 | HLG1: TXN0005726 | HLH1: TXN0005727 | HLI1: TXN0005728 | HLJ1: TXN0005729 | HLK1: TXN0005730 | HLL1: TXN0005731 | HLM1: TXN0005732 | HLN1: TXN0005733 | HLO1: TXN0005734 | HLP1: TXN0005735 | HLQ1: TXN0005736 | HLR1: TXN0005737 | HLS1: TXN0005738 | HLT1: TXN0005739 | HLU1: TXN0005740 | HLV1: TXN0005741 | HLW1: TXN0005742 | HLX1: TXN0005743 | HLY1: TXN0005744 | HLZ1: TXN0005745 | HMA1: TXN0005746 | HMB1: TXN0005747 | HMC1: TXN0005748 | HMD1: TXN0005749 | HME1: TXN0005750 | HMF1: TXN0005751 | HMG1: TXN0005752 | HMH1: TXN0005753 | HMI1: TXN0005754 | HMJ1: TXN0005755 | HMK1: TXN0005756 | HML1: TXN0005757 | HMM1: TXN0005758 | HMN1: TXN0005759 | HMO1: TXN0005760 | HMP1: TXN0005761 | HMQ1: TXN0005762 | HMR1: TXN0005763 | HMS1: TXN0005764 | HMT1: TXN0005765 | HMU1: TXN0005766 | HMV1: TXN0005767 | HMW1: TXN0005768 | HMX1: TXN0005769 | HMY1: TXN0005770 | HMZ1: TXN0005771 | HNA1: TXN0005772 | HNB1: TXN0005773 | HNC1: TXN0005774 | HND1: TXN0005775 | HNE1: TXN0005776 | HNF1: TXN0005777 | HNG1: TXN0005778 | HNH1: TXN0005779 | HNI1: TXN0005780 | HNJ1: TXN0005781 | HNK1: TXN0005782 | HNL1: TXN0005783 | HNM1: TXN0005784 | HNN1: TXN0005785 | HNO1: TXN0005786 | HNP1: TXN0005787 | HNQ1: TXN0005788 | HNR1: TXN0005789 | HNS1: TXN0005790 | HNT1: TXN0005791 | HNU1: TXN0005792 | HNV1: TXN0005793 | HNW1: TXN0005794 | HNX1: TXN0005795 | HNY1: TXN0005796 | HNZ1: TXN0005797 | HOA1: TXN0005798 | HOB1: TXN0005799 | HOC1: TXN0005800 | HOD1: TXN0005801 | HOE1: TXN0005802 | HOF1: TXN0005803 | HOG1: TXN0005804 | HOH1: TXN0005805 | HOI1: TXN0005806 | HOJ1: TXN0005807 | HOK1: TXN0005808 | HOL1: TXN0005809 | HOM1: TXN0005810 | HON1: TXN0005811 | HOO1: TXN0005812 | HOP1: TXN0005813 | HOQ1: TXN0005814 | HOR1: TXN0005815 | HOS1: TXN0005816 | HOT1: TXN0005817 | HOU1: TXN0005818 | HOV1: TXN0005819 | HOW1: TXN0005820 | HOX1: TXN0005821 | HOY1: TXN0005822 | HOZ1: TXN0005823 | HPA1: TXN0005824 | HPB1: TXN0005825 | HPC1: TXN0005826 | HPD1: TXN0005827 | HPE1: TXN0005828 | HPF1: TXN0005829 | HPG1: TXN0005830 | HPH1: TXN0005831 | HPI1: TXN0005832 | HPJ1: TXN0005833 | HPK1: TXN0005834 | HPL1: TXN0005835 | HPM1: TXN0005836 | HPN1: TXN0005837 | HPO1: TXN0005838 | HPP1: TXN0005839 | HPQ1: TXN0005840 | HPR1: TXN0005841 | HPS1: TXN0005842 | HPT1: TXN0005843 | HPU1: TXN0005844 | HPV1: TXN0005845 | HPW1: TXN0005846 | HPX1: TXN0005847 | HPY1: TXN0005848 | HPZ1: TXN0005849 | HQA1: TXN0005850 | HQB1: TXN0005851 | HQC1: TXN0005852 | HQD1: TXN0005853 | HQE1: TXN0005854 | HQF1: TXN0005855 | HQG1: TXN0005856 | HQH1: TXN0005857 | HQI1: TXN0005858 | HQJ1: TXN0005859 | HQK1: TXN0005860 | HQL1: TXN0005861 | HQM1: TXN0005862 | HQN1: TXN0005863 | HQO1: TXN0005864 | HQP1: TXN0005865 | HQQ1: TXN0005866 | HQR1: TXN0005867 | HQS1: TXN0005868 | HQT1: TXN0005869 | HQU1: TXN0005870 | HQV1: TXN0005871 | HQW1: TXN0005872 | HQX1: TXN0005873 | HQY1: TXN0005874 | HQZ1: TXN0005875 | HRA1: TXN0005876 | HRB1: TXN0005877 | HRC1: TXN0005878 | HRD1: TXN0005879 | HRE1: TXN0005880 | HRF1: TXN0005881 | HRG1: TXN0005882 | HRH1: TXN0005883 | HRI1: TXN0005884 | HRJ1: TXN0005885 | HRK1: TXN0005886 | HRL1: TXN0005887 | HRM1: TXN0005888 | HRN1: TXN0005889 | HRO1: TXN0005890 | HRP1: TXN0005891 | HRQ1: TXN0005892 | HRR1: TXN0005893 | HRS1: TXN0005894 | HRT1: TXN0005895 | HRU1: TXN0005896 | HRV1: TXN0005897 | HRW1: TXN0005898 | HRX1: TXN0005899 | HRY1: TXN0005900 | HRZ1: TXN0005901 | HSA1: TXN0005902 | HSB1: TXN0005903 | HSC1: TXN0005904 | HSD1: TXN0005905 | HSE1: TXN0005906 | HSF1: TXN0005907 | HSG1: TXN0005908 | HSH1: TXN0005909 | HSI1: TXN0005910 | HSJ1: TXN0005911 | HSK1: TXN0005912 | HSL1: TXN0005913 | HSM1: TXN0005914 | HSN1: TXN0005915 | HSO1: TXN0005916 | HSP1: TXN0005917 | HSQ1: TXN0005918 | HSR1: TXN0005919 | HSS1: TXN0005920 | HST1: TXN0005921 | HSU1: TXN0005922 | HSV1: TXN0005923 | HSW1: TXN0005924 | HSX1: TXN0005925 | HSY1: TXN0005926 | HSZ1: TXN0005927 | HTA1: TXN0005928 | HTB1: TXN0005929 | HTC1: TXN0005930 | HTD1: TXN0005931 | HTE1: TXN0005932 | HTF1: TXN0005933 | HTG1: TXN0005934 | HTH1: TXN0005935 | HTI1: TXN0005936 | HTJ1: TXN0005937 | HTK1: TXN0005938 | HTL1: TXN0005939 | HTM1: TXN0005940 | HTN1: TXN0005941 | HTO1: TXN0005942 | HTP1: TXN0005943 | HTQ1: TXN0005944 | HTR1: TXN0005945 | HTS1: TXN0005946 | HTT1: TXN0005947 | HTU1: TXN0005948 | HTV1: TXN0005949 | HTW1: TXN0005950 | HTX1: TXN0005951 | HTY1: TXN0005952 | HTZ1: TXN0005953 | HUA1: TXN0005954 | HUB1: TXN0005955 | HUC1: TXN0005956 | HUD1: TXN0005957 | HUE1: TXN0005958 | HUF1: TXN0005959 | HUG1: TXN0005960 | HUH1: TXN0005961 | HUI1: TXN0005962 | HUJ1: TXN0005963 | HUK1: TXN0005964 | HUL1: TXN0005965 | HUM1: TXN0005966 | HUN1: TXN0005967 | HUO1: TXN0005968 | HUP1: TXN0005969 | HUQ1: TXN0005970 | HUR1: TXN0005971 | HUS1: TXN0005972 | HUT1: TXN0005973 | HUU1: TXN0005974 | HUV1: TXN0005975 | HUW1: TXN0005976 | HUX1: TXN0005977 | HUY1: TXN0005978 | HUZ1: TXN0005979 | HVA1: TXN0005980 | HVB1: TXN0005981 | HVC1: TXN0005982 | HVD1: TXN0005983 | HVE1: TXN0005984 | HVF1: TXN0005985 | HVG1: TXN0005986 | HVH1: TXN0005987 | HVI1: TXN0005988 | HVJ1: TXN0005989 | HVK1: TXN0005990 | HVL1: TXN0005991 | HVM1: TXN0005992 | HVN1: TXN0005993 | HVO1: TXN0005994 | HVP1: TXN0005995 | HVQ1: TXN0005996 | HVR1: TXN0005997 | HVS1: TXN0005998 | HVT1: TXN0005999 | HVU1: TXN0006000 | HVV1: TXN0006001 | HVW1: TXN0006002 | HVX1: TXN0006003 | HVY1: TXN0006004 | HVZ1: TXN0006005 | HWA1: TXN0006006 | HWB1: TXN0006007 | HWC1: TXN0006008 | HWD1: TXN0006009 | HWE1: TXN0006010 | HWF1: TXN0006011 | HWG1: TXN0006012 | HWH1: TXN0006013 | HWI1: TXN0006014 | HWJ1: TXN0006015 | HWK1: TXN0006016 | HWL1: TXN0006017 | HWM1: TXN0006018 | HWN1: TXN0006019 | HWO1: TXN0006020 | HWP1: TXN0006021 | HWQ1: TXN0006022 | HWR1: TXN0006023 | HWS1: TXN0006024 | HWT1: TXN0006025 | HWU1: TXN0006026 | HWV1: TXN0006027 | HWW1: TXN0006028 | HWX1: TXN0006029 | HWY1: TXN0006030 | HWZ1: TXN0006031 | HXA1: TXN0006032 | HXB1: TXN0006033 | HXC1: TXN0006034 | HXD1: TXN0006035 | HXE1: TXN0006036 | HXF1: TXN0006037 | HXG1: TXN0006038 | HXH1: TXN0006039 | HXI1: TXN0006040 | HXJ1: TXN0006041 | HXK1: TXN0006042 | HXL1: TXN0006043 | HXM1: TXN0006044 | HXN1: TXN0006045 | HXO1: TXN0006046 | HXP1: TXN0006047 | HXQ1: TXN0006048 | HXR1: TXN0006049 | HXS1: TXN0006050 | HXT1: TXN0006051 | HXU1: TXN0006052 | HXV1: TXN0006053 | HXW1: TXN0006054 | HXX1: TXN0006055 | HXY1: TXN0006056 | HXZ1: TXN0006057 | HYA1: TXN0006058 | HYB1: TXN0006059 | HYC1: TXN0006060 | HYD1: TXN0006061 | HYE1: TXN0006062 | HYF1: TXN0006063 | HYG1: TXN0006064 | HYH1: TXN0006065 | HYI1: TXN0006066 | HYJ1: TXN0006067 | HYK1: TXN0006068 | HYL1: TXN0006069 | HYM1: TXN0006070 | HYN1: TXN0006071 | HYO1: TXN0006072 | HYP1: TXN0006073 | HYQ1: TXN0006074 | HYR1: TXN0006075 | HYS1: TXN0006076 | HYT1: TXN0006077 | HYU1: TXN0006078 | HYV1: TXN0006079 | HYW1: TXN0006080 | HYX1: TXN0006081 | HYY1: TXN0006082 | HYZ1: TXN0006083 | HZA1: TXN0006084 | HZB1: TXN0006085 | HZC1: TXN0006086 | HZD1: TXN0006087 | HZE1: TXN0006088 | HZF1: TXN0006089 | HZG1: TXN0006090 | HZH1: TXN0006091 | HZI1: TXN0006092 | HZJ1: TXN0006093 | HZK1: TXN0006094 | HZL1: TXN0006095 | HZM1: TXN0006096 | HZN1: TXN0006097 | HZO1: TXN0006098 | HZP1: TXN0006099 | HZQ1: TXN0006100 | HZR1: TXN0006101 | HZS1: TXN0006102 | HZT1: TXN0006103 | HZU1: TXN0006104 | HZV1: TXN0006105 | HZW1: TXN0006106 | HZX1: TXN0006107 | HZY1: TXN0006108 | HZZ1: TXN0006109 | IAA1: TXN0006110 | IAB1: TXN0006111 | IAC1: TXN0006112 | IAD1: TXN0006113 | IAE1: TXN0006114 | IAF1: TXN0006115 | IAG1: TXN0006116 | IAH1: TXN0006117 | IAI1: TXN0006118 | IAJ1: TXN0006119 | IAK1: TXN0006120 | IAL1: TXN0006121 | IAM1: TXN0006122 | IAN1: TXN0006123 | IAO1: TXN0006124 | IAP1: TXN0006125 | IAQ1: TXN0006126 | IAR1: TXN0006127 | IAS1: TXN0006128 | IAT1: TXN0006129 | IAU1: TXN0006130 | IAV1: TXN0006131 | IAW1: TXN0006132 | IAX1: TXN0006133 | IAY1: TXN0006134 | IAZ1: TXN0006135 | IBA1: TXN0006136 | IBB1: TXN0006137 | IBC1: TXN0006138 | IBD1: TXN0006139 | IBE1: TXN0006140 | IBF1: TXN0006141 | IBG1: TXN0006142 | IBH1: TXN0006143 | IBI1: TXN0006144 | IBJ1: TXN0006145 | IBK1: TXN0006146 | IBL1: TXN0006147 | IBM1: TXN0006148 | IBN1: TXN0006149 | IBO1: TXN0006150 | IBP1: TXN0006151 | IBQ1: TXN0006152 | IBR1: TXN0006153 | IBS1: TXN0006154 | IBT1: TXN0006155 | IBU1: TXN0006156 | IBV1: TXN0006157 | IBW1: TXN0006158 | IBX1: TXN0006159 | IBY1: TXN0006160 | IBZ1: TXN0006161 | ICA1: TXN0006162 | ICB1: TXN0006163 | ICC1: TXN0006164 | ICD1: TXN0006165 | ICE1: TXN0006166 | ICF1: TXN0006167 | ICG1: TXN0006168 | ICH1: TXN0006169 | ICI1: TXN0006170 | ICJ1: TXN0006171 | ICK1: TXN0006172 | ICL1: TXN0006173 | ICM1: TXN0006174 | ICN1: TXN0006175 | ICO1: TXN0006176 | ICP1: TXN0006177 | ICQ1: TXN0006178 | ICR1: TXN0006179 | ICS1: TXN0006180 | ICT1: TXN0006181 | ICU1: TXN0006182 | ICV1: TXN0006183 | ICW1: TXN0006184 | ICX1: TXN0006185 | ICY1: TXN0006186 | ICZ1: TXN0006187 | IDA1: TXN0006188 | IDB1: TXN0006189 | IDC1: TXN0006190 | IDD1: TXN0006191 | IDE1: TXN0006192 | IDF1: TXN0006193 | IDG1: TXN0006194 | IDH1: TXN0006195 | IDI1: TXN0006196 | IDJ1: TXN0006197 | IDK1: TXN0006198 | IDL1: TXN0006199 | IDM1: TXN0006200 | IDN1: TXN0006201 | IDO1: TXN0006202 | IDP1: TXN0006203 | IDQ1: TXN0006204 | IDR1: TXN0006205 | IDS1: TXN0006206 | IDT1: TXN0006207 | IDU1: TXN0006208 | IDV1: TXN0006209 | IDW1: TXN0006210 | IDX1: TXN0006211 | IDY1: TXN0006212 | IDZ1: TXN0006213 | IEA1: TXN0006214 | IEB1: TXN0006215 | IEC1: TXN0006216 | IED1: TXN0006217 | IEE1: TXN0006218 | IEF1: TXN0006219 | IEG1: TXN0006220 | IEH1: TXN0006221 | IEI1: TXN0006222 | IEJ1: TXN0006223 | IEK1: TXN0006224 | IEL1: TXN0006225 | IEM1: TXN0006226 | IEN1: TXN0006227 | IEO1: TXN0006228 | IEP1: TXN0006229 | IEQ1: TXN0006230 | IER1: TXN0006231 | IES1: TXN0006232 | IET1: TXN0006233 | IEU1: TXN0006234 | IEV1: TXN0006235 | IEW1: TXN0006236 | IEX1: TXN0006237 | IEY1: TXN0006238 | IEZ1: TXN0006239 | IFA1: TXN0006240 | IFB1: TXN0006241 | IFC1: TXN0006242 | IFD1: TXN0006243 | IFE1: TXN0006244 | IFF1: TXN0006245 | IFG1: TXN0006246 | IFH1: TXN0006247 | IFI1: TXN0006248 | IFJ1: TXN0006249 | IFK1: TXN0006250 | IFL1: TXN0006251 | IFM1: TXN0006252 | IFN1: TXN0006253 | IFO1: TXN0006254 | IFP1: TXN0006255 | IFQ1: TXN0006256 | IFR1: TXN0006257 | IFS1: TXN0006258 | IFT1: TXN0006259 | IFU1: TXN0006260 | IFV1: TXN0006261 | IFW1: TXN0006262 | IFX1: TXN0006263 | IFY1: TXN0006264 | IFZ1: TXN0006265 | IGA1: TXN0006266 | IGB1: TXN0006267 | IGC1: TXN0006268 | IGD1: TXN0006269 | IGE1: TXN0006270 | IGF1: TXN0006271 | IGG1: TXN0006272 | IGH1: TXN0006273 | IGI1: TXN0006274 | IGJ1: TXN0006275 | IGK1: TXN0006276 | IGL1: TXN0006277 | IGM1: TXN0006278 | IGN1: TXN0006279 | IGO1: TXN0006280 | IGP1: TXN0006281 | IGQ1: TXN0006282 | IGR1: TXN0006283 | IGS1: TXN0006284 | IGT1: TXN0006285 | IGU1: TXN0006286 | IGV1: TXN0006287 | IGW1: TXN0006288 | IGX1: TXN0006289 | IGY1: TXN0006290 | IGZ1: TXN0006291 | IHA1: TXN0006292 | IHB1: TXN0006293 | IHC1: TXN0006294 | IHD1: TXN0006295 | IHE1: TXN0006296 | IHF1: TXN0006297 | IHG1: TXN0006298 | IHH1: TXN0006299 | IHI1: TXN0006300 | IHJ1: TXN0006301 | IHK1: TXN0006302 | IHL1: TXN0006303 | IHM1: TXN0006304 | IHN1: TXN0006305 | IHO1: TXN0006306 | IHP1: TXN0006307 | IHQ1: TXN0006308 | IHR1: TXN0006309 | IHS1: TXN0006310 | IHT1: TXN0006311 | IHU1: TXN0006312 | IHV1: TXN0006313 | IHW1: TXN0006314 | IHX1: TXN0006315 | IHY1: TXN0006316 | IHZ1: TXN0006317 | IIA1: TXN0006318 | IIB1: TXN0006319 | IIC1: TXN0006320 | IID1: TXN0006321 | IIE1: TXN0006322 | IIF1: TXN0006323 | IIG1: TXN0006324 | IIH1: TXN0006325 | III1: TXN0006326 | IIJ1: TXN0006327 | IIK1: TXN0006328 | IIL1: TXN0006329 | IIM1: TXN0006330 | IIN1: TXN0006331 | IIO1: TXN0006332 | IIP1: TXN0006333 | IIQ1: TXN0006334 | IIR1: TXN0006335 | IIS1: TXN0006336 | IIT1: TXN0006337 | IIU1: TXN0006338 | IIV1: TXN0006339 | IIW1: TXN0006340 | IIX1: TXN0006341 | IIY1: TXN0006342 | IIZ1: TXN0006343 | IJA1: TXN0006344 | IJB1: TXN0006345 | IJC1: TXN0006346 | IJD1: TXN0006347 | IJE1: TXN0006348 | IJF1: TXN0006349 | IJG1: TXN0006350 | IJH1: TXN0006351 | IJI1: TXN0006352 | IJJ1: TXN0006353 | IJK1: TXN0006354 | IJL1: TXN0006355 | IJM1: TXN0006356 | IJN1: TXN0006357 | IJO1: TXN0006358 | IJP1: TXN0006359 | IJQ1: TXN0006360 | IJR1: TXN0006361 | IJS1: TXN0006362 | IJT1: TXN0006363 | IJU1: TXN0006364 | IJV1: TXN0006365 | IJW1: TXN0006366 | IJX1: TXN0006367 | IJY1: TXN0006368 | IJZ1: TXN0006369 | IKA1: TXN0006370 | IKB1: TXN0006371 | IKC1: TXN0006372 | IKD1: TXN0006373 | IKE1: TXN0006374 | IKF1: TXN0006375 | IKG1: TXN0006376 | IKH1: TXN0006377 | IKI1: TXN0006378 | IKJ1: TXN0006379 | IKK1: TXN0006380 | IKL1: TXN0006381 | IKM1: TXN0006382 | IKN1: TXN0006383 | IKO1: TXN0006384 | IKP1: TXN0006385 | IKQ1: TXN0006386 | IKR1: TXN0006387 | IKS1: TXN0006388 | IKT1: TXN0006389 | IKU1: TXN0006390 | IKV1: TXN0006391 | IKW1: TXN0006392 | IKX1: TXN0006393 | IKY1: TXN0006394 | IKZ1: TXN0006395 | ILA1: TXN0006396 | ILB1: TXN0006397 | ILC1: TXN0006398 | ILD1: TXN0006399 | ILE1: TXN0006400 | ILF1: TXN0006401 | ILG1: TXN0006402 | ILH1: TXN0006403 | ILI1: TXN0006404 | ILJ1: TXN0006405 | ILK1: TXN0006406 | ILL1: TXN0006407 | ILM1: TXN0006408 | ILN1: TXN0006409 | ILO1: TXN0006410 | ILP1: TXN0006411 | ILQ1: TXN0006412 | ILR1: TXN0006413 | ILS1: TXN0006414 | ILT1: TXN0006415 | ILU1: TXN0006416 | ILV1: TXN0006417 | ILW1: TXN0006418 | ILX1: TXN0006419 | ILY1: TXN0006420 | ILZ1: TXN0006421 | IMA1: TXN0006422 | IMB1: TXN0006423 | IMC1: TXN0006424 | IMD1: TXN0006425 | IME1: TXN0006426 | IMF1: TXN0006427 | IMG1: TXN0006428 | IMH1: TXN0006429 | IMI1: TXN0006430 | IMJ1: TXN0006431 | IMK1: TXN0006432 | IML1: TXN0006433 | IMM1: TXN0006434 | IMN1: TXN0006435 | IMO1: TXN0006436 | IMP1: TXN0006437 | IMQ1: TXN0006438 | IMR1: TXN0006439 | IMS1: TXN0006440 | IMT1: TXN0006441 | IMU1: TXN0006442 | IMV1: TXN0006443 | IMW1: TXN0006444 | IMX1: TXN0006445 | IMY1: TXN0006446 | IMZ1: TXN0006447 | INA1: TXN0006448 | INB1: TXN0006449 | INC1: TXN0006450 | IND1: TXN0006451 | INE1: TXN0006452 | INF1: TXN0006453 | ING1: TXN0006454 | INH1: TXN0006455 | INI1: TXN0006456 | INJ1: TXN0006457 | INK1: TXN0006458 | INL1: TXN0006459 | INM1: TXN0006460 | INN1: TXN0006461 | INO1: TXN0006462 | INP1: TXN0006463 | INQ1: TXN0006464 | INR1: TXN0006465 | INS1: TXN0006466 | INT1: TXN0006467 | INU1: TXN0006468 | INV1: TXN0006469 | INW1: TXN0006470 | INX1: TXN0006471 | INY1: TXN0006472 | INZ1: TXN0006473 | IOA1: TXN0006474 | IOB1: TXN0006475 | IOC1: TXN0006476 | IOD1: TXN0006477 | IOE1: TXN0006478 | IOF1: TXN0006479 | IOG1: TXN0006480 | IOH1: TXN0006481 | IOI1: TXN0006482 | IOJ1: TXN0006483 | IOK1: TXN0006484 | IOL1: TXN0006485 | IOM1: TXN0006486 | ION1: TXN0006487 | IOO1: TXN0006488 | IOP1: TXN0006489 | IOQ1: TXN0006490 | IOR1: TXN0006491 | IOS1: TXN0006492 | IOT1: TXN0006493 | IOU1: TXN0006494 | IOV1: TXN0006495 | IOW1: TXN0006496 | IOX1: TXN0006497 | IOY1: TXN0006498 | IOZ1: TXN0006499 | IPA1: TXN0006500 | IPB1: TXN0006501 | IPC1: TXN0006502 | IPD1: TXN0006503 | IPE1: TXN0006504 | IPF1: TXN0006505 | IPG1: TXN0006506 | IPH1: TXN0006507 | IPI1: TXN0006508 | IPJ1: TXN0006509 | IPK1: TXN0006510 | IPL1: TXN0006511 | IPM1: TXN0006512 | IPN1: TXN0006513 | IPO1: TXN0006514 | IPP1: TXN0006515 | IPQ1: TXN0006516 | IPR1: TXN0006517 | IPS1: TXN0006518 | IPT1: TXN0006519 | IPU1: TXN0006520 | IPV1: TXN0006521 | IPW1: TXN0006522 | IPX1: TXN0006523 | IPY1: TXN0006524 | IPZ1: TXN0006525 | IQA1: TXN0006526 | IQB1: TXN0006527 | IQC1: TXN0006528 | IQD1: TXN0006529 | IQE1: TXN0006530 | IQF1: TXN0006531 | IQG1: TXN0006532 | IQH1: TXN0006533 | IQI1: TXN0006534 | IQJ1: TXN0006535 | IQK1: TXN0006536 | IQL1: TXN0006537 | IQM1: TXN0006538 | IQN1: TXN0006539 | IQO1: TXN0006540 | IQP1: TXN0006541 | IQQ1: TXN0006542 | IQR1: TXN0006543 | IQS1: TXN0006544 | IQT1: TXN0006545 | IQU1: TXN0006546 | IQV1: TXN0006547 | IQW1: TXN0006548 | IQX1: TXN0006549 | IQY1: TXN0006550 | IQZ1: TXN0006551 | IRA1: TXN0006552 | IRB1: TXN0006553 | IRC1: TXN0006554 | IRD1: TXN0006555 | IRE1: TXN0006556 | IRF1: TXN0006557 | IRG1: TXN0006558 | IRH1: TXN0006559 | IRI1: TXN0006560 | IRJ1: TXN0006561 | IRK1: TXN0006562 | IRL1: TXN0006563 | IRM1: TXN0006564 | IRN1: TXN0006565 | IRO1: TXN0006566 | IRP1: TXN0006567 | IRQ1: TXN0006568 | IRR1: TXN0006569 | IRS1: TXN0006570 | IRT1: TXN0006571 | IRU1: TXN0006572 | IRV1: TXN0006573 | IRW1: TXN0006574 | IRX1: TXN0006575 | IRY1: TXN0006576 | IRZ1: TXN0006577 | ISA1: TXN0006578 | ISB1: TXN0006579 | ISC1: TXN0006580 | ISD1: TXN0006581 | ISE1: TXN0006582 | ISF1: TXN0006583 | ISG1: TXN0006584 | ISH1: TXN0006585 | ISI1: TXN0006586 | ISJ1: TXN0006587 | ISK1: TXN0006588 | ISL1: TXN0006589 | ISM1: TXN0006590 | ISN1: TXN0006591 | ISO1: TXN0006592 | ISP1: TXN0006593 | ISQ1: TXN0006594 | ISR1: TXN0006595 | ISS1: TXN0006596 | IST1: TXN0006597 | ISU1: TXN0006598 | ISV1: TXN0006599 | ISW1: TXN0006600 | ISX1: TXN0006601 | ISY1: TXN0006602 | ISZ1: TXN0006603 | ITA1: TXN0006604 | ITB1: TXN0006605 | ITC1: TXN0006606 | ITD1: TXN0006607 | ITE1: TXN0006608 | ITF1: TXN0006609 | ITG1: TXN0006610 | ITH1: TXN0006611 | ITI1: TXN0006612 | ITJ1: TXN0006613 | ITK1: TXN0006614 | ITL1: TXN0006615 | ITM1: TXN0006616 | ITN1: TXN0006617 | ITO1: TXN0006618 | ITP1: TXN0006619 | ITQ1: TXN0006620 | ITR1: TXN0006621 | ITS1: TXN0006622 | ITT1: TXN0006623 | ITU1: TXN0006624 | ITV1: TXN0006625 | ITW1: TXN0006626 | ITX1: TXN0006627 | ITY1: TXN0006628 | ITZ1: TXN0006629 | IUA1: TXN0006630 | IUB1: TXN0006631 | IUC1: TXN0006632 | IUD1: TXN0006633 | IUE1: TXN0006634 | IUF1: TXN0006635 | IUG1: TXN0006636 | IUH1: TXN0006637 | IUI1: TXN0006638 | IUJ1: TXN0006639 | IUK1: TXN0006640 | IUL1: TXN0006641 | IUM1: TXN0006642 | IUN1: TXN0006643 | IUO1: TXN0006644 | IUP1: TXN0006645 | IUQ1: TXN0006646 | IUR1: TXN0006647 | IUS1: TXN0006648 | IUT1: TXN0006649 | IUU1: TXN0006650 | IUV1: TXN0006651 | IUW1: TXN0006652 | IUX1: TXN0006653 | IUY1: TXN0006654 | IUZ1: TXN0006655 | IVA1: TXN0006656 | IVB1: TXN0006657 | IVC1: TXN0006658 | IVD1: TXN0006659 | IVE1: TXN0006660 | IVF1: TXN0006661 | IVG1: TXN0006662 | IVH1: TXN0006663 | IVI1: TXN0006664 | IVJ1: TXN0006665 | IVK1: TXN0006666 | IVL1: TXN0006667 | IVM1: TXN0006668 | IVN1: TXN0006669 | IVO1: TXN0006670 | IVP1: TXN0006671 | IVQ1: TXN0006672 | IVR1: TXN0006673 | IVS1: TXN0006674 | IVT1: TXN0006675 | IVU1: TXN0006676 | IVV1: TXN0006677 | IVW1: TXN0006678 | IVX1: TXN0006679 | IVY1: TXN0006680 | IVZ1: TXN0006681 | IWA1: TXN0006682 | IWB1: TXN0006683 | IWC1: TXN0006684 | IWD1: TXN0006685 | IWE1: TXN0006686 | IWF1: TXN0006687 | IWG1: TXN0006688 | IWH1: TXN0006689 | IWI1: TXN0006690 | IWJ1: TXN0006691 | IWK1: TXN0006692 | IWL1: TXN0006693 | IWM1: TXN0006694 | IWN1: TXN0006695 | IWO1: TXN0006696 | IWP1: TXN0006697 | IWQ1: TXN0006698 | IWR1: TXN0006699 | IWS1: TXN0006700 | IWT1: TXN0006701 | IWU1: TXN0006702 | IWV1: TXN0006703 | IWW1: TXN0006704 | IWX1: TXN0006705 | IWY1: TXN0006706 | IWZ1: TXN0006707 | IXA1: TXN0006708 | IXB1: TXN0006709 | IXC1: TXN0006710 | IXD1: TXN0006711 | IXE1: TXN0006712 | IXF1: TXN0006713 | IXG1: TXN0006714 | IXH1: TXN0006715 | IXI1: TXN0006716 | IXJ1: TXN0006717 | IXK1: TXN0006718 | IXL1: TXN0006719 | IXM1: TXN0006720 | IXN1: TXN0006721 | IXO1: TXN0006722 | IXP1: TXN0006723 | IXQ1: TXN0006724 | IXR1: TXN0006725 | IXS1: TXN0006726 | IXT1: TXN0006727 | IXU1: TXN0006728 | IXV1: TXN0006729 | IXW1: TXN0006730 | IXX1: TXN0006731 | IXY1: TXN0006732 | IXZ1: TXN0006733 | IYA1: TXN0006734 | IYB1: TXN0006735 | IYC1: TXN0006736 | IYD1: TXN0006737 | IYE1: TXN0006738 | IYF1: TXN0006739 | IYG1: TXN0006740 | IYH1: TXN0006741 | IYI1: TXN0006742 | IYJ1: TXN0006743 | IYK1: TXN0006744 | IYL1: TXN0006745 | IYM1: TXN0006746 | IYN1: TXN0006747 | IYO1: TXN0006748 | IYP1: TXN0006749 | IYQ1: TXN0006750 | IYR1: TXN0006751 | IYS1: TXN0006752 | IYT1: TXN0006753 | IYU1: TXN0006754 | IYV1: TXN0006755 | IYW1: TXN0006756 | IYX1: TXN0006757 | IYY1: TXN0006758 | IYZ1: TXN0006759 | IZA1: TXN0006760 | IZB1: TXN0006761 | IZC1: TXN0006762 | IZD1: TXN0006763 | IZE1: TXN0006764 | IZF1: TXN0006765 | IZG1: TXN0006766 | IZH1: TXN0006767 | IZI1: TXN0006768 | IZJ1: TXN0006769 | IZK1: TXN0006770 | IZL1: TXN0006771 | IZM1: TXN0006772 | IZN1: TXN0006773 | IZO1: TXN0006774 | IZP1: TXN0006775 | IZQ1: TXN0006776 | IZR1: TXN0006777 | IZS1: TXN0006778 | IZT1: TXN0006779 | IZU1: TXN0006780 | IZV1: TXN0006781 | IZW1: TXN0006782 | IZX1: TXN0006783 | IZY1: TXN0006784 | IZZ1: TXN0006785 | JAA1: TXN0006786 | JAB1: TXN0006787 | JAC1: TXN0006788 | JAD1: TXN0006789 | JAE1: TXN0006790 | JAF1: TXN0006791 | JAG1: TXN0006792 | JAH1: TXN0006793 | JAI1: TXN0006794 | JAJ1: TXN0006795 | JAK1: TXN0006796 | JAL1: TXN0006797 | JAM1: TXN0006798 | JAN1: TXN0006799 | JAO1: TXN0006800 | JAP1: TXN0006801 | JAQ1: TXN0006802 | JAR1: TXN0006803 | JAS1: TXN0006804 | JAT1: TXN0006805 | JAU1: TXN0006806 | JAV1: TXN0006807 | JAW1: TXN0006808 | JAX1: TXN0006809 | JAY1: TXN0006810 | JAZ1: TXN0006811 | JBA1: TXN0006812 | JBB1: TXN0006813 | JBC1: TXN0006814 | JBD1: TXN0006815 | JBE1: TXN0006816 | JBF1: TXN0006817 | JBG1: TXN0006818 | JBH1: TXN0006819 | JBI1: TXN0006820 | JBJ1: TXN0006821 | JBK1: TXN0006822 | JBL1: TXN0006823 | JBM1: TXN0006824 | JBN1: TXN0006825 | JBO1: TXN0006826 | JBP1: TXN0006827 | JBQ1: TXN0006828 | JBR1: TXN0006829 | JBS1: TXN0006830 | JBT1: TXN0006831 | JBU1: TXN0006832 | JBV1: TXN0006833 | JBW1: TXN0006834 | JBX1: TXN0006835 | JBY1: TXN0006836 | JBZ1: TXN0006837 | JCA1: TXN0006838 | JCB1: TXN0006839 | JCC1: TXN0006840 | JCD1: TXN0006841 | JCE1: TXN0006842 | JCF1: TXN0006843 | JCG1: TXN0006844 | JCH1: TXN0006845 | JCI1: TXN0006846 | JCJ1: TXN0006847 | JCK1: TXN0006848 | JCL1: TXN0006849 | JCM1: TXN0006850 | JCN1: TXN0006851 | JCO1: TXN0006852 | JCP1: TXN0006853 | JCQ1: TXN0006854 | JCR1: TXN0006855 | JCS1: TXN0006856 | JCT1: TXN0006857 | JCU1: TXN0006858 | JCV1: TXN0006859 | JCW1: TXN0006860 | JCX1: TXN0006861 | JCY1: TXN0006862 | JCZ1: TXN0006863 | JDA1: TXN0006864 | JDB1: TXN0006865 | JDC1: TXN0006866 | JDD1: TXN0006867 | JDE1: TXN0006868 | JDF1: TXN0006869 | JDG1: TXN0006870 | JDH1: TXN0006871 | JDI1: TXN0006872 | JDJ1: TXN0006873 | JDK1: TXN0006874 | JDL1: TXN0006875 | JDM1: TXN0006876 | JDN1: TXN0006877 | JDO1: TXN0006878 | JDP1: TXN0006879 | JDQ1: TXN0006880 | JDR1: TXN0006881 | JDS1: TXN0006882 | JDT1: TXN0006883 | JDU1: TXN0006884 | JDV1: TXN0006885 | JDW1: TXN0006886 | JDX1: TXN0006887 | JDY1: TXN0006888 | JDZ1: TXN0006889 | JEA1: TXN0006890 | JEB1: TXN0006891 | JEC1: TXN0006892 | JED1: TXN0006893 | JEE1: TXN0006894 | JEF1: TXN0006895 | JEG1: TXN0006896 | JEH1: TXN0006897 | JEI1: TXN0006898 | JEJ1: TXN0006899 | JEK1: TXN0006900 | JEL1: TXN0006901 | JEM1: TXN0006902 | JEN1: TXN0006903 | JEO1: TXN0006904 | JEP1: TXN0006905 | JEQ1: TXN0006906 | JER1: TXN0006907 | JES1: TXN0006908 | JET1: TXN0006909 | JEU1: TXN0006910 | JEV1: TXN0006911 | JEW1: TXN0006912 | JEX1: TXN0006913 | JEY1: TXN0006914 | JEZ1: TXN0006915 | JFA1: TXN0006916 | JFB1: TXN0006917 | JFC1: TXN0006918 | JFD1: TXN0006919 | JFE1: TXN0006920 | JFF1: TXN0006921 | JFG1: TXN0006922 | JFH1: TXN0006923 | JFI1: TXN0006924 | JFJ1: TXN0006925 | JFK1: TXN0006926 | JFL1: TXN0006927 | JFM1: TXN0006928 | JFN1: TXN0006929 | JFO1: TXN0006930 | JFP1: TXN0006931 | JFQ1: TXN0006932 | JFR1: TXN0006933 | JFS1: TXN0006934 | JFT1: TXN0006935 | JFU1: TXN0006936 | JFV1: TXN0006937 | JFW1: TXN0006938 | JFX1: TXN0006939 | JFY1: TXN0006940 | JFZ1: TXN0006941 | JGA1: TXN0006942 | JGB1: TXN0006943 | JGC1: TXN0006944 | JGD1: TXN0006945 | JGE1: TXN0006946 | JGF1: TXN0006947 | JGG1: TXN0006948 | JGH1: TXN0006949 | JGI1: TXN0006950 | JGJ1: TXN0006951 | JGK1: TXN0006952 | JGL1: TXN0006953 | JGM1: TXN0006954 | JGN1: TXN0006955 | JGO1: TXN0006956 | JGP1: TXN0006957 | JGQ1: TXN0006958 | JGR1: TXN0006959 | JGS1: TXN0006960 | JGT1: TXN0006961 | JGU1: TXN0006962 | JGV1: TXN0006963 | JGW1: TXN0006964 | JGX1: TXN0006965 | JGY1: TXN0006966 | JGZ1: TXN0006967 | JHA1: TXN0006968 | JHB1: TXN0006969 | JHC1: TXN0006970 | JHD1: TXN0006971 | JHE1: TXN0006972 | JHF1: TXN0006973 | JHG1: TXN0006974 | JHH1: TXN0006975 | JHI1: TXN0006976 | JHJ1: TXN0006977 | JHK1: TXN0006978 | JHL1: TXN0006979 | JHM1: TXN0006980 | JHN1: TXN0006981 | JHO1: TXN0006982 | JHP1: TXN0006983 | JHQ1: TXN0006984 | JHR1: TXN0006985 | JHS1: TXN0006986 | JHT1: TXN0006987 | JHU1: TXN0006988 | JHV1: TXN0006989 | JHW1: TXN0006990 | JHX1: TXN0006991 | JHY1: TXN0006992 | JHZ1: TXN0006993 | JIA1: TXN0006994 | JIB1: TXN0006995 | JIC1: TXN0006996 | JID1: TXN0006997 | JIE1: TXN0006998 | JIF1: TXN0006999 | JIG1: TXN0007000 | JIH1: TXN0007001 | JII1: TXN0007002 | JIJ1: TXN0007003 | JIK1: TXN0007004 | JIL1: TXN0007005 | JIM1: TXN0007006 | JIN1: TXN0007007 | JIO1: TXN0007008 | JIP1: TXN0007009 | JIQ1: TXN0007010 | JIR1: TXN0007011 | JIS1: TXN0007012 | JIT1: TXN0007013 | JIU1: TXN0007014 | JIV1: TXN0007015 | JIW1: TXN0007016 | JIX1: TXN0007017 | JIY1: TXN0007018 | JIZ1: TXN0007019 | JJA1: TXN0007020 | JJB1: TXN0007021 | JJC1: TXN0007022 | JJD1: TXN0007023 | JJE1: TXN0007024 | JJF1: TXN0007025 | JJG1: TXN0007026 | JJH1: TXN0007027 | JJI1: TXN0007028 | JJJ1: TXN0007029 | JJK1: TXN0007030 | JJL1: TXN0007031 | JJM1: TXN0007032 | JJN1: TXN0007033 | JJO1: TXN0007034 | JJP1: TXN0007035 | JJQ1: TXN0007036 | JJR1: TXN0007037 | JJS1: TXN0007038 | JJT1: TXN0007039 | JJU1: TXN0007040 | JJV1: TXN0007041 | JJW1: TXN0007042 | JJX1: TXN0007043 | JJY1: TXN0007044 | JJZ1: TXN0007045 | JKA1: TXN0007046 | JKB1: TXN0007047 | JKC1: TXN0007048 | JKD1: TXN0007049 | JKE1: TXN0007050 | JKF1: TXN0007051 | JKG1: TXN0007052 | JKH1: TXN0007053 | JKI1: TXN0007054 | JKJ1: TXN0007055 | JKK1: TXN0007056 | JKL1: TXN0007057 | JKM1: TXN0007058 | JKN1: TXN0007059 | JKO1: TXN0007060 | JKP1: TXN0007061 | JKQ1: TXN0007062 | JKR1: TXN0007063 | JKS1: TXN0007064 | JKT1: TXN0007065 | JKU1: TXN0007066 | JKV1: TXN0007067 | JKW1: TXN0007068 | JKX1: TXN0007069 | JKY1: TXN0007070 | JKZ1: TXN0007071 | JLA1: TXN0007072 | JLB1: TXN0007073 | JLC1: TXN0007074 | JLD1: TXN0007075 | JLE1: TXN0007076 | JLF1: TXN0007077 | JLG1: TXN0007078 | JLH1: TXN0007079 | JLI1: TXN0007080 | JLJ1: TXN0007081 | JLK1: TXN0007082 | JLL1: TXN0007083 | JLM1: TXN0007084 | JLN1: TXN0007085 | JLO1: TXN0007086 | JLP1: TXN0007087 | JLQ1: TXN0007088 | JLR1: TXN0007089 | JLS1: TXN0007090 | JLT1: TXN0007091 | JLU1: TXN0007092 | JLV1: TXN0007093 | JLW1: TXN0007094 | JLX1: TXN0007095 | JLY1: TXN0007096 | JLZ1: TXN0007097 | JMA1: TXN0007098 | JMB1: TXN0007099 | JMC1: TXN0007100 | JMD1: TXN0007101 | JME1: TXN0007102 | JMF1: TXN0007103 | JMG1: TXN0007104 | JMH1: TXN0007105 | JMI1: TXN0007106 | JMJ1: TXN0007107 | JMK1: TXN0007108 | JML1: TXN0007109 | JMM1: TXN0007110 | JMN1: TXN0007111 | JMO1: TXN0007112 | JMP1: TXN0007113 | JMQ1: TXN0007114 | JMR1: TXN0007115 | JMS1: TXN0007116 | JMT1: TXN0007117 | JMU1: TXN0007118 | JMV1: TXN0007119 | JMW1: TXN0007120 | JMX1: TXN0007121 | JMY1: TXN0007122 | JMZ1: TXN0007123 | JNA1: TXN0007124 | JNB1: TXN0007125 | JNC1: TXN0007126 | JND1: TXN0007127 | JNE1: TXN0007128 | JNF1: TXN0007129 | JNG1: TXN0007130 | JNH1: TXN0007131 | JNI1: TXN0007132 | JNJ1: TXN0007133 | JNK1: TXN0007134 | JNL1: TXN0007135 | JNM1: TXN0007136 | JNN1: TXN0007137 | JNO1: TXN0007138 | JNP1: TXN0007139 | JNQ1: TXN0007140 | JNR1: TXN0007141 | JNS1: TXN0007142 | JNT1: TXN0007143 | JNU1: TXN0007144 | JNV1: TXN0007145 | JNW1: TXN0007146 | JNX1: TXN0007147 | JNY1: TXN0007148 | JNZ1: TXN0007149 | JOA1: TXN0007150 | JOB1: TXN0007151 | JOC1: TXN0007152 | JOD1: TXN0007153 | JOE1: TXN0007154 | JOF1: TXN0007155 | JOG1: TXN0007156 | JOH1: TXN0007157 | JOI1: TXN0007158 | JOJ1: TXN0007159 | JOK1: TXN0007160 | JOL1: TXN0007161 | JOM1: TXN0007162 | JON1: TXN0007163 | JOO1: TXN0007164 | JOP1: TXN0007165 | JOQ1: TXN0007166 | JOR1: TXN0007167 | JOS1: TXN0007168 | JOT1: TXN0007169 | JOU1: TXN0007170 | JOV1: TXN0007171 | JOW1: TXN0007172 | JOX1: TXN0007173 | JOY1: TXN0007174 | JOZ1: TXN0007175 | JPA1: TXN0007176 | JPB1: TXN0007177 | JPC1: TXN0007178 | JPD1: TXN0007179 | JPE1: TXN0007180 | JPF1: TXN0007181 | JPG1: TXN0007182 | JPH1: TXN0007183 | JPI1: TXN0007184 | JPJ1: TXN0007185 | JPK1: TXN0007186 | JPL1: TXN0007187 | JPM1: TXN0007188 | JPN1: TXN0007189 | JPO1: TXN0007190 | JPP1: TXN0007191 | JPQ1: TXN0007192 | JPR1: TXN0007193 | JPS1: TXN0007194 | JPT1: TXN0007195 | JPU1: TXN0007196 | JPV1: TXN0007197 | JPW1: TXN0007198 | JPX1: TXN0007199 | JPY1: TXN0007200 | JPZ1: TXN0007201 | JQA1: TXN0007202 | JQB1: TXN0007203 | JQC1: TXN0007204 | JQD1: TXN0007205 | JQE1: TXN0007206 | JQF1: TXN0007207 | JQG1: TXN0007208 | JQH1: TXN0007209 | JQI1: TXN0007210 | JQJ1: TXN0007211 | JQK1: TXN0007212 | JQL1: TXN0007213 | JQM1: TXN0007214 | JQN1: TXN0007215 | JQO1: TXN0007216 | JQP1: TXN0007217 | JQQ1: TXN0007218 | JQR1: TXN0007219 | JQS1: TXN0007220 | JQT1: TXN0007221 | JQU1: TXN0007222 | JQV1: TXN0007223 | JQW1: TXN0007224 | JQX1: TXN0007225 | JQY1: TXN0007226 | JQZ1: TXN0007227 | JRA1: TXN0007228 | JRB1: TXN0007229 | JRC1: TXN0007230 | JRD1: TXN0007231 | JRE1: TXN0007232 | JRF1: TXN0007233 | JRG1: TXN0007234 | JRH1: TXN0007235 | JRI1: TXN0007236 | JRJ1: TXN0007237 | JRK1: TXN0007238 | JRL1: TXN0007239 | JRM1: TXN0007240 | JRN1: TXN0007241 | JRO1: TXN0007242 | JRP1: TXN0007243 | JRQ1: TXN0007244 | JRR1: TXN0007245 | JRS1: TXN0007246 | JRT1: TXN0007247 | JRU1: TXN0007248 | JRV1: TXN0007249 | JRW1: TXN0007250 | JRX1: TXN0007251 | JRY1: TXN0007252 | JRZ1: TXN0007253 | JSA1: TXN0007254 | JSB1: TXN0007255 | JSC1: TXN0007256 | JSD1: TXN0007257 | JSE1: TXN0007258 | JSF1: TXN0007259 | JSG1: TXN0007260 | JSH1: TXN0007261 | JSI1: TXN0007262 | JSJ1: TXN0007263 | JSK1: TXN0007264 | JSL1: TXN0007265 | JSM1: TXN0007266 | JSN1: TXN0007267 | JSO1: TXN0007268 | JSP1: TXN0007269 | JSQ1: TXN0007270 | JSR1: TXN0007271 | JSS1: TXN0007272 | JST1: TXN0007273 | JSU1: TXN0007274 | JSV1: TXN0007275 | JSW1: TXN0007276 | JSX1: TXN0007277 | JSY1: TXN0007278 | JSZ1: TXN0007279 | JTA1: TXN0007280 | JTB1: TXN0007281 | JTC1: TXN0007282 | JTD1: TXN0007283 | JTE1: TXN0007284 | JTF1: TXN0007285 | JTG1: TXN0007286 | JTH1: TXN0007287 | JTI1: TXN0007288 | JTJ1: TXN0007289 | JTK1: TXN0007290 | JTL1: TXN0007291 | JTM1: TXN0007292 | JTN1: TXN0007293 | JTO1: TXN0007294 | JTP1: TXN0007295 | JTQ1: TXN0007296 | JTR1: TXN0007297 | JTS1: TXN0007298 | JTT1: TXN0007299 | JTU1: TXN0007300 | JTV1: TXN0007301 | JTW1: TXN0007302 | JTX1: TXN0007303 | JTY1: TXN0007304 | JTZ1: TXN0007305 | JUA1: TXN0007306 | JUB1: TXN0007307 | JUC1: TXN0007308 | JUD1: TXN0007309 | JUE1: TXN0007310 | JUF1: TXN0007311 | JUG1: TXN0007312 | JUH1: TXN0007313 | JUI1: TXN0007314 | JUJ1: TXN0007315 | JUK1: TXN0007316 | JUL1: TXN0007317 | JUM1: TXN0007318 | JUN1: TXN0007319 | JUO1: TXN0007320 | JUP1: TXN0007321 | JUQ1: TXN0007322 | JUR1: TXN0007323 | JUS1: TXN0007324 | JUT1: TXN0007325 | JUU1: TXN0007326 | JUV1: TXN0007327 | JUW1: TXN0007328 | JUX1: TXN0007329 | JUY1: TXN0007330 | JUZ1: TXN0007331 | JVA1: TXN0007332 | JVB1: TXN0007333 | JVC1: TXN0007334 | JVD1: TXN0007335 | JVE1: TXN0007336 | JVF1: TXN0007337 | JVG1: TXN0007338 | JVH1: TXN0007339 | JVI1: TXN0007340 | JVJ1: TXN0007341 | JVK1: TXN0007342 | JVL1: TXN0007343 | JVM1: TXN0007344 | JVN1: TXN0007345 | JVO1: TXN0007346 | JVP1: TXN0007347 | JVQ1: TXN0007348 | JVR1: TXN0007349 | JVS1: TXN0007350 | JVT1: TXN0007351 | JVU1: TXN0007352 | JVV1: TXN0007353 | JVW1: TXN0007354 | JVX1: TXN0007355 | JVY1: TXN0007356 | JVZ1: TXN0007357 | JWA1: TXN0007358 | JWB1: TXN0007359 | JWC1: TXN0007360 | JWD1: TXN0007361 | JWE1: TXN0007362 | JWF1: TXN0007363 | JWG1: TXN0007364 | JWH1: TXN0007365 | JWI1: TXN0007366 | JWJ1: TXN0007367 | JWK1: TXN0007368 | JWL1: TXN0007369 | JWM1: TXN0007370 | JWN1: TXN0007371 | JWO1: TXN0007372 | JWP1: TXN0007373 | JWQ1: TXN0007374 | JWR1: TXN0007375 | JWS1: TXN0007376 | JWT1: TXN0007377 | JWU1: TXN0007378 | JWV1: TXN0007379 | JWW1: TXN0007380 | JWX1: TXN0007381 | JWY1: TXN0007382 | JWZ1: TXN0007383 | JXA1: TXN0007384 | JXB1: TXN0007385 | JXC1: TXN0007386 | JXD1: TXN0007387 | JXE1: TXN0007388 | JXF1: TXN0007389 | JXG1: TXN0007390 | JXH1: TXN0007391 | JXI1: TXN0007392 | JXJ1: TXN0007393 | JXK1: TXN0007394 | JXL1: TXN0007395 | JXM1: TXN0007396 | JXN1: TXN0007397 | JXO1: TXN0007398 | JXP1: TXN0007399 | JXQ1: TXN0007400 | JXR1: TXN0007401 | JXS1: TXN0007402 | JXT1: TXN0007403 | JXU1: TXN0007404 | JXV1: TXN0007405 | JXW1: TXN0007406 | JXX1: TXN0007407 | JXY1: TXN0007408 | JXZ1: TXN0007409 | JYA1: TXN0007410 | JYB1: TXN0007411 | JYC1: TXN0007412 | JYD1: TXN0007413 | JYE1: TXN0007414 | JYF1: TXN0007415 | JYG1: TXN0007416 | JYH1: TXN0007417 | JYI1: TXN0007418 | JYJ1: TXN0007419 | JYK1: TXN0007420 | JYL1: TXN0007421 | JYM1: TXN0007422 | JYN1: TXN0007423 | JYO1: TXN0007424 | JYP1: TXN0007425 | JYQ1: TXN0007426 | JYR1: TXN0007427 | JYS1: TXN0007428 | JYT1: TXN0007429 | JYU1: TXN0007430 | JYV1: TXN0007431 | JYW1: TXN0007432 | JYX1: TXN0007433 | JYY1: TXN0007434 | JYZ1: TXN0007435 | JZA1: TXN0007436 | JZB1: TXN0007437 | JZC1: TXN0007438 | JZD1: TXN0007439 | JZE1: TXN0007440 | JZF1: TXN0007441 | JZG1: TXN0007442 | JZH1: TXN0007443 | JZI1: TXN0007444 | JZJ1: TXN0007445 | JZK1: TXN0007446 | JZL1: TXN0007447 | JZM1: TXN0007448 | JZN1: TXN0007449 | JZO1: TXN0007450 | JZP1: TXN0007451 | JZQ1: TXN0007452 | JZR1: TXN0007453 | JZS1: TXN0007454 | JZT1: TXN0007455 | JZU1: TXN0007456 | JZV1: TXN0007457 | JZW1: TXN0007458 | JZX1: TXN0007459 | JZY1: TXN0007460 | JZZ1: TXN0007461 | KAA1: TXN0007462 | KAB1: TXN0007463 | KAC1: TXN0007464 | KAD1: TXN0007465 | KAE1: TXN0007466 | KAF1: TXN0007467 | KAG1: TXN0007468 | KAH1: TXN0007469 | KAI1: TXN0007470 | KAJ1: TXN0007471 | KAK1: TXN0007472 | KAL1: TXN0007473 | KAM1: TXN0007474 | KAN1: TXN0007475 | KAO1: TXN0007476 | KAP1: TXN0007477 | KAQ1: TXN0007478 | KAR1: TXN0007479 | KAS1: TXN0007480 | KAT1: TXN0007481 | KAU1: TXN0007482 | KAV1: TXN0007483 | KAW1: TXN0007484 | KAX1: TXN0007485 | KAY1: TXN0007486 | KAZ1: TXN0007487 | KBA1: TXN0007488 | KBB1: TXN0007489 | KBC1: TXN0007490 | KBD1: TXN0007491 | KBE1: TXN0007492 | KBF1: TXN0007493 | KBG1: TXN0007494 | KBH1: TXN0007495 | KBI1: TXN0007496 | KBJ1: TXN0007497 | KBK1: TXN0007498 | KBL1: TXN0007499 | KBM1: TXN0007500 | KBN1: TXN0007501 | KBO1: TXN0007502 | KBP1: TXN0007503 | KBQ1: TXN0007504 | KBR1: TXN0007505 | KBS1: TXN0007506 | KBT1: TXN0007507 | KBU1: TXN0007508 | KBV1: TXN0007509 | KBW1: TXN0007510 | KBX1: TXN0007511 | KBY1: TXN0007512 | KBZ1: TXN0007513 | KCA1: TXN0007514 | KCB1: TXN0007515 | KCC1: TXN0007516 | KCD1: TXN0007517 | KCE1: TXN0007518 | KCF1: TXN0007519 | KCG1: TXN0007520 | KCH1: TXN0007521 | KCI1: TXN0007522 | KCJ1: TXN0007523 | KCK1: TXN0007524 | KCL1: TXN0007525 | KCM1: TXN0007526 | KCN1: TXN0007527 | KCO1: TXN0007528 | KCP1: TXN0007529 | KCQ1: TXN0007530 | KCR1: TXN0007531 | KCS1: TXN0007532 | KCT1: TXN0007533 | KCU1: TXN0007534 | KCV1: TXN0007535 | KCW1: TXN0007536 | KCX1: TXN0007537 | KCY1: TXN0007538 | KCZ1: TXN0007539 | KDA1: TXN0007540 | KDB1: TXN0007541 | KDC1: TXN0007542 | KDD1: TXN0007543 | KDE1: TXN0007544 | KDF1: TXN0007545 | KDG1: TXN0007546 | KDH1: TXN0007547 | KDI1: TXN0007548 | KDJ1: TXN0007549 | KDK1: TXN0007550 | KDL1: TXN0007551 | KDM1: TXN0007552 | KDN1: TXN0007553 | KDO1: TXN0007554 | KDP1: TXN0007555 | KDQ1: TXN0007556 | KDR1: TXN0007557 | KDS1: TXN0007558 | KDT1: TXN0007559 | KDU1: TXN0007560 | KDV1: TXN0007561 | KDW1: TXN0007562 | KDX1: TXN0007563 | KDY1: TXN0007564 | KDZ1: TXN0007565 | KEA1: TXN0007566 | KEB1: TXN0007567 | KEC1: TXN0007568 | KED1: TXN0007569 | KEE1: TXN0007570 | KEF1: TXN0007571 | KEG1: TXN0007572 | KEH1: TXN0007573 | KEI1: TXN0007574 | KEJ1: TXN0007575 | KEK1: TXN0007576 | KEL1: TXN0007577 | KEM1: TXN0007578 | KEN1: TXN0007579 | KEO1: TXN0007580 | KEP1: TXN0007581 | KEQ1: TXN0007582 | KER1: TXN0007583 | KES1: TXN0007584 | KET1: TXN0007585 | KEU1: TXN0007586 | KEV1: TXN0007587 | KEW1: TXN0007588 | KEX1: TXN0007589 | KEY1: TXN0007590 | KEZ1: TXN0007591 | KFA1: TXN0007592 | KFB1: TXN0007593 | KFC1: TXN0007594 | KFD1: TXN0007595 | KFE1: TXN0007596 | KFF1: TXN0007597 | KFG1: TXN0007598 | KFH1: TXN0007599 | KFI1: TXN0007600 | KFJ1: TXN0007601 | KFK1: TXN0007602 | KFL1: TXN0007603 | KFM1: TXN0007604 | KFN1: TXN0007605 | KFO1: TXN0007606 | KFP1: TXN0007607 | KFQ1: TXN0007608 | KFR1: TXN0007609 | KFS1: TXN0007610 | KFT1: TXN0007611 | KFU1: TXN0007612 | KFV1: TXN0007613 | KFW1: TXN0007614 | KFX1: TXN0007615 | KFY1: TXN0007616 | KFZ1: TXN0007617 | KGA1: TXN0007618 | KGB1: TXN0007619 | KGC1: TXN0007620 | KGD1: TXN0007621 | KGE1: TXN0007622 | KGF1: TXN0007623 | KGG1: TXN0007624 | KGH1: TXN0007625 | KGI1: TXN0007626 | KGJ1: TXN0007627 | KGK1: TXN0007628 | KGL1: TXN0007629 | KGM1: TXN0007630 | KGN1: TXN0007631 | KGO1: TXN0007632 | KGP1: TXN0007633 | KGQ1: TXN0007634 | KGR1: TXN0007635 | KGS1: TXN0007636 | KGT1: TXN0007637 | KGU1: TXN0007638 | KGV1: TXN0007639 | KGW1: TXN0007640 | KGX1: TXN0007641 | KGY1: TXN0007642 | KGZ1: TXN0007643 | KHA1: TXN0007644 | KHB1: TXN0007645 | KHC1: TXN0007646 | KHD1: TXN0007647 | KHE1: TXN0007648 | KHF1: TXN0007649 | KHG1: TXN0007650 | KHH1: TXN0007651 | KHI1: TXN0007652 | KHJ1: TXN0007653 | KHK1: TXN0007654 | KHL1: TXN0007655 | KHM1: TXN0007656 | KHN1: TXN0007657 | KHO1: TXN0007658 | KHP1: TXN0007659 | KHQ1: TXN0007660 | KHR1: TXN0007661 | KHS1: TXN0007662 | KHT1: TXN0007663 | KHU1: TXN0007664 | KHV1: TXN0007665 | KHW1: TXN0007666 | KHX1: TXN0007667 | KHY1: TXN0007668 | KHZ1: TXN0007669 | KIA1: TXN0007670 | KIB1: TXN0007671 | KIC1: TXN0007672 | KID1: TXN0007673 | KIE1: TXN0007674 | KIF1: TXN0007675 | KIG1: TXN0007676 | KIH1: TXN0007677 | KII1: TXN0007678 | KIJ1: TXN0007679 | KIK1: TXN0007680 | KIL1: TXN0007681 | KIM1: TXN0007682 | KIN1: TXN0007683 | KIO1: TXN0007684 | KIP1: TXN0007685 | KIQ1: TXN0007686 | KIR1: TXN0007687 | KIS1: TXN0007688 | KIT1: TXN0007689 | KIU1: TXN0007690 | KIV1: TXN0007691 | KIW1: TXN0007692 | KIX1: TXN0007693 | KIY1: TXN0007694 | KIZ1: TXN0007695 | KJA1: TXN0007696 | KJB1: TXN0007697 | KJC1: TXN0007698 | KJD1: TXN0007699 | KJE1: TXN0007700 | KJF1: TXN0007701 | KJG1: TXN0007702 | KJH1: TXN0007703 | KJI1: TXN0007704 | KJJ1: TXN0007705 | KJK1: TXN0007706 | KJL1: TXN0007707 | KJM1: TXN0007708 | KJN1: TXN0007709 | KJO1: TXN0007710 | KJP1: TXN0007711 | KJQ1: TXN0007712 | KJR1: TXN0007713 | KJS1: TXN0007714 | KJT1: TXN0007715 | KJU1: TXN0007716 | KJV1: TXN0007717 | KJW1: TXN0007718 | KJX1: TXN0007719 | KJY1: TXN0007720 | KJZ1: TXN0007721 | KKA1: TXN0007722 | KKB1: TXN0007723 | KKC1: TXN0007724 | KKD1: TXN0007725 | KKE1: TXN0007726 | KKF1: TXN0007727 | KKG1: TXN0007728 | KKH1: TXN0007729 | KKI1: TXN0007730 | KKJ1: TXN0007731 | KKK1: TXN0007732 | KKL1: TXN0007733 | KKM1: TXN0007734 | KKN1: TXN0007735 | KKO1: TXN0007736 | KKP1: TXN0007737 | KKQ1: TXN0007738 | KKR1: TXN0007739 | KKS1: TXN0007740 | KKT1: TXN0007741 | KKU1: TXN0007742 | KKV1: TXN0007743 | KKW1: TXN0007744 | KKX1: TXN0007745 | KKY1: TXN0007746 | KKZ1: TXN0007747 | KLA1: TXN0007748 | KLB1: TXN0007749 | KLC1: TXN0007750 | KLD1: TXN0007751 | KLE1: TXN0007752 | KLF1: TXN0007753 | KLG1: TXN0007754 | KLH1: TXN0007755 | KLI1: TXN0007756 | KLJ1: TXN0007757 | KLK1: TXN0007758 | KLL1: TXN0007759 | KLM1: TXN0007760 | KLN1: TXN0007761 | KLO1: TXN0007762 | KLP1: TXN0007763 | KLQ1: TXN0007764 | KLR1: TXN0007765 | KLS1: TXN0007766 | KLT1: TXN0007767 | KLU1: TXN0007768 | KLV1: TXN0007769 | KLW1: TXN0007770 | KLX1: TXN0007771 | KLY1: TXN0007772 | KLZ1: TXN0007773 | KMA1: TXN0007774 | KMB1: TXN0007775 | KMC1: TXN0007776 | KMD1: TXN0007777 | KME1: TXN0007778 | KMF1: TXN0007779 | KMG1: TXN0007780 | KMH1: TXN0007781 | KMI1: TXN0007782 | KMJ1: TXN0007783 | KMK1: TXN0007784 | KML1: TXN0007785 | KMM1: TXN0007786 | KMN1: TXN0007787 | KMO1: TXN0007788 | KMP1: TXN0007789 | KMQ1: TXN0007790 | KMR1: TXN0007791 | KMS1: TXN0007792 | KMT1: TXN0007793 | KMU1: TXN0007794 | KMV1: TXN0007795 | KMW1: TXN0007796 | KMX1: TXN0007797 | KMY1: TXN0007798 | KMZ1: TXN0007799 | KNA1: TXN0007800 | KNB1: TXN0007801 | KNC1: TXN0007802 | KND1: TXN0007803 | KNE1: TXN0007804 | KNF1: TXN0007805 | KNG1: TXN0007806 | KNH1: TXN0007807 | KNI1: TXN0007808 | KNJ1: TXN0007809 | KNK1: TXN0007810 | KNL1: TXN0007811 | KNM1: TXN0007812 | KNN1: TXN0007813 | KNO1: TXN0007814 | KNP1: TXN0007815 | KNQ1: TXN0007816 | KNR1: TXN0007817 | KNS1: TXN0007818 | KNT1: TXN0007819 | KNU1: TXN0007820 | KNV1: TXN0007821 | KNW1: TXN0007822 | KNX1: TXN0007823 | KNY1: TXN0007824 | KNZ1: TXN0007825 | KOA1: TXN0007826 | KOB1: TXN0007827 | KOC1: TXN0007828 | KOD1: TXN0007829 | KOE1: TXN0007830 | KOF1: TXN0007831 | KOG1: TXN0007832 | KOH1: TXN0007833 | KOI1: TXN0007834 | KOJ1: TXN0007835 | KOK1: TXN0007836 | KOL1: TXN0007837 | KOM1: TXN0007838 | KON1: TXN0007839 | KOO1: TXN0007840 | KOP1: TXN0007841 | KOQ1: TXN0007842 | KOR1: TXN0007843 | KOS1: TXN0007844 | KOT1: TXN0007845 | KOU1: TXN0007846 | KOV1: TXN0007847 | KOW1: TXN0007848 | KOX1: TXN0007849 | KOY1: TXN0007850 | KOZ1: TXN0007851 | KPA1: TXN0007852 | KPB1: TXN0007853 | KPC1: TXN0007854 | KPD1: TXN0007855 | KPE1: TXN0007856 | KPF1: TXN0007857 | KPG1: TXN0007858 | KPH1: TXN0007859 | KPI1: TXN0007860 | KPJ1: TXN0007861 | KPK1: TXN0007862 | KPL1: TXN0007863 | KPM1: TXN0007864 | KPN1: TXN0007865 | KPO1: TXN0007866 | KPP1: TXN0007867 | KPQ1: TXN0007868 | KPR1: TXN0007869 | KPS1: TXN0007870 | KPT1: TXN0007871 | KPU1: TXN0007872 | KPV1: TXN0007873 | KPW1: TXN0007874 | KPX1: TXN0007875 | KPY1: TXN0007876 | KPZ1: TXN0007877 | KQA1: TXN0007878 | KQB1: TXN0007879 | KQC1: TXN0007880 | KQD1: TXN0007881 | KQE1: TXN0007882 | KQF1: TXN0007883 | KQG1: TXN0007884 | KQH1: TXN0007885 | KQI1: TXN0007886 | KQJ1: TXN0007887 | KQK1: TXN0007888 | KQL1: TXN0007889 | KQM1: TXN0007890 | KQN1: TXN0007891 | KQO1: TXN0007892 | KQP1: TXN0007893 | KQQ1: TXN0007894 | KQR1: TXN0007895 | KQS1: TXN0007896 | KQT1: TXN0007897 | KQU1: TXN0007898 | KQV1: TXN0007899 | KQW1: TXN0007900 | KQX1: TXN0007901 | KQY1: TXN0007902 | KQZ1: TXN0007903 | KRA1: TXN0007904 | KRB1: TXN0007905 | KRC1: TXN0007906 | KRD1: TXN0007907 | KRE1: TXN0007908 | KRF1: TXN0007909 | KRG1: TXN0007910 | KRH1: TXN0007911 | KRI1: TXN0007912 | KRJ1: TXN0007913 | KRK1: TXN0007914 | KRL1: TXN0007915 | KRM1: TXN0007916 | KRN1: TXN0007917 | KRO1: TXN0007918 | KRP1: TXN0007919 | KRQ1: TXN0007920 | KRR1: TXN0007921 | KRS1: TXN0007922 | KRT1: TXN0007923 | KRU1: TXN0007924 | KRV1: TXN0007925 | KRW1: TXN0007926 | KRX1: TXN0007927 | KRY1: TXN0007928 | KRZ1: TXN0007929 | KSA1: TXN0007930 | KSB1: TXN0007931 | KSC1: TXN0007932 | KSD1: TXN0007933 | KSE1: TXN0007934 | KSF1: TXN0007935 | KSG1: TXN0007936 | KSH1: TXN0007937 | KSI1: TXN0007938 | KSJ1: TXN0007939 | KSK1: TXN0007940 | KSL1: TXN0007941 | KSM1: TXN0007942 | KSN1: TXN0007943 | KSO1: TXN0007944 | KSP1: TXN0007945 | KSQ1: TXN0007946 | KSR1: TXN0007947 | KSS1: TXN0007948 | KST1: TXN0007949 | KSU1: TXN0007950 | KSV1: TXN0007951 | KSW1: TXN0007952 | KSX1: TXN0007953 | KSY1: TXN0007954 | KSZ1: TXN0007955 | KTA1: TXN0007956 | KTB1: TXN0007957 | KTC1: TXN0007958 | KTD1: TXN0007959 | KTE1: TXN0007960 | KTF1: TXN0007961 | KTG1: TXN0007962 | KTH1: TXN0007963 | KTI1: TXN0007964 | KTJ1: TXN0007965 | KTK1: TXN0007966 | KTL1: TXN0007967 | KTM1: TXN0007968 | KTN1: TXN0007969 | KTO1: TXN0007970 | KTP1: TXN0007971 | KTQ1: TXN0007972 | KTR1: TXN0007973 | KTS1: TXN0007974 | KTT1: TXN0007975 | KTU1: TXN0007976 | KTV1: TXN0007977 | KTW1: TXN0007978 | KTX1: TXN0007979 | KTY1: TXN0007980 | KTZ1: TXN0007981 | KUA1: TXN0007982 | KUB1: TXN0007983 | KUC1: TXN0007984 | KUD1: TXN0007985 | KUE1: TXN0007986 | KUF1: TXN0007987 | KUG1: TXN0007988 | KUH1: TXN0007989 | KUI1: TXN0007990 | KUJ1: TXN0007991 | KUK1: TXN0007992 | KUL1: TXN0007993 | KUM1: TXN0007994 | KUN1: TXN0007995 | KUO1: TXN0007996 | KUP1: TXN0007997 | KUQ1: TXN0007998 | KUR1: TXN0007999 | KUS1: TXN0008000 | KUT1: TXN0008001 | KUU1: TXN0008002 | KUV1: TXN0008003 | KUW1: TXN0008004 | KUX1: TXN0008005 | KUY1: TXN0008006 | KUZ1: TXN0008007 | KVA1: TXN0008008 | KVB1: TXN0008009 | KVC1: TXN0008010 | KVD1: TXN0008011 | KVE1: TXN0008012 | KVF1: TXN0008013 | KVG1: TXN0008014 | KVH1: TXN0008015 | KVI1: TXN0008016 | KVJ1: TXN0008017 | KVK1: TXN0008018 | KVL1: TXN0008019 | KVM1: TXN0008020 | KVN1: TXN0008021 | KVO1: TXN0008022 | KVP1: TXN0008023 | KVQ1: TXN0008024 | KVR1: TXN0008025 | KVS1: TXN0008026 | KVT1: TXN0008027 | KVU1: TXN0008028 | KVV1: TXN0008029 | KVW1: TXN0008030 | KVX1: TXN0008031 | KVY1: TXN0008032 | KVZ1: TXN0008033 | KWA1: TXN0008034 | KWB1: TXN0008035 | KWC1: TXN0008036 | KWD1: TXN0008037 | KWE1: TXN0008038 | KWF1: TXN0008039 | KWG1: TXN0008040 | KWH1: TXN0008041 | KWI1: TXN0008042 | KWJ1: TXN0008043 | KWK1: TXN0008044 | KWL1: TXN0008045 | KWM1: TXN0008046 | KWN1: TXN0008047 | KWO1: TXN0008048 | KWP1: TXN0008049 | KWQ1: TXN0008050 | KWR1: TXN0008051 | KWS1: TXN0008052 | KWT1: TXN0008053 | KWU1: TXN0008054 | KWV1: TXN0008055 | KWW1: TXN0008056 | KWX1: TXN0008057 | KWY1: TXN0008058 | KWZ1: TXN0008059 | KXA1: TXN0008060 | KXB1: TXN0008061 | KXC1: TXN0008062 | KXD1: TXN0008063 | KXE1: TXN0008064 | KXF1: TXN0008065 | KXG1: TXN0008066 | KXH1: TXN0008067 | KXI1: TXN0008068 | KXJ1: TXN0008069 | KXK1: TXN0008070 | KXL1: TXN0008071 | KXM1: TXN0008072 | KXN1: TXN0008073 | KXO1: TXN0008074 | KXP1: TXN0008075 | KXQ1: TXN0008076 | KXR1: TXN0008077 | KXS1: TXN0008078 | KXT1: TXN0008079 | KXU1: TXN0008080 | KXV1: TXN0008081 | KXW1: TXN0008082 | KXX1: TXN0008083 | KXY1: TXN0008084 | KXZ1: TXN0008085 | KYA1: TXN0008086 | KYB1: TXN0008087 | KYC1: TXN0008088 | KYD1: TXN0008089 | KYE1: TXN0008090 | KYF1: TXN0008091 | KYG1: TXN0008092 | KYH1: TXN0008093 | KYI1: TXN0008094 | KYJ1: TXN0008095 | KYK1: TXN0008096 | KYL1: TXN0008097 | KYM1: TXN0008098 | KYN1: TXN0008099 | KYO1: TXN0008100 | KYP1: TXN0008101 | KYQ1: TXN0008102 | KYR1: TXN0008103 | KYS1: TXN0008104 | KYT1: TXN0008105 | KYU1: TXN0008106 | KYV1: TXN0008107 | KYW1: TXN0008108 | KYX1: TXN0008109 | KYY1: TXN0008110 | KYZ1: TXN0008111 | KZA1: TXN0008112 | KZB1: TXN0008113 | KZC1: TXN0008114 | KZD1: TXN0008115 | KZE1: TXN0008116 | KZF1: TXN0008117 | KZG1: TXN0008118 | KZH1: TXN0008119 | KZI1: TXN0008120 | KZJ1: TXN0008121 | KZK1: TXN0008122 | KZL1: TXN0008123 | KZM1: TXN0008124 | KZN1: TXN0008125 | KZO1: TXN0008126 | KZP1: TXN0008127 | KZQ1: TXN0008128 | KZR1: TXN0008129 | KZS1: TXN0008130 | KZT1: TXN0008131 | KZU1: TXN0008132 | KZV1: TXN0008133 | KZW1: TXN0008134 | KZX1: TXN0008135 | KZY1: TXN0008136 | KZZ1: TXN0008137 | LAA1: TXN0008138 | LAB1: TXN0008139 | LAC1: TXN0008140 | LAD1: TXN0008141 | LAE1: TXN0008142 | LAF1: TXN0008143 | LAG1: TXN0008144 | LAH1: TXN0008145 | LAI1: TXN0008146 | LAJ1: TXN0008147 | LAK1: TXN0008148 | LAL1: TXN0008149 | LAM1: TXN0008150 | LAN1: TXN0008151 | LAO1: TXN0008152 | LAP1: TXN0008153 | LAQ1: TXN0008154 | LAR1: TXN0008155 | LAS1: TXN0008156 | LAT1: TXN0008157 | LAU1: TXN0008158 | LAV1: TXN0008159 | LAW1: TXN0008160 | LAX1: TXN0008161 | LAY1: TXN0008162 | LAZ1: TXN0008163 | LBA1: TXN0008164 | LBB1: TXN0008165 | LBC1: TXN0008166 | LBD1: TXN0008167 | LBE1: TXN0008168 | LBF1: TXN0008169 | LBG1: TXN0008170 | LBH1: TXN0008171 | LBI1: TXN0008172 | LBJ1: TXN0008173 | LBK1: TXN0008174 | LBL1: TXN0008175 | LBM1: TXN0008176 | LBN1: TXN0008177 | LBO1: TXN0008178 | LBP1: TXN0008179 | LBQ1: TXN0008180 | LBR1: TXN0008181 | LBS1: TXN0008182 | LBT1: TXN0008183 | LBU1: TXN0008184 | LBV1: TXN0008185 | LBW1: TXN0008186 | LBX1: TXN0008187 | LBY1: TXN0008188 | LBZ1: TXN0008189 | LCA1: TXN0008190 | LCB1: TXN0008191 | LCC1: TXN0008192 | LCD1: TXN0008193 | LCE1: TXN0008194 | LCF1: TXN0008195 | LCG1: TXN0008196 | LCH1: TXN0008197 | LCI1: TXN0008198 | LCJ1: TXN0008199 | LCK1: TXN0008200 | LCL1: TXN0008201 | LCM1: TXN0008202 | LCN1: TXN0008203 | LCO1: TXN0008204 | LCP1: TXN0008205 | LCQ1: TXN0008206 | LCR1: TXN0008207 | LCS1: TXN0008208 | LCT1: TXN0008209 | LCU1: TXN0008210 | LCV1: TXN0008211 | LCW1: TXN0008212 | LCX1: TXN0008213 | LCY1: TXN0008214 | LCZ1: TXN0008215 | LDA1: TXN0008216 | LDB1: TXN0008217 | LDC1: TXN0008218 | LDD1: TXN0008219 | LDE1: TXN0008220 | LDF1: TXN0008221 | LDG1: TXN0008222 | LDH1: TXN0008223 | LDI1: TXN0008224 | LDJ1: TXN0008225 | LDK1: TXN0008226 | LDL1: TXN0008227 | LDM1: TXN0008228 | LDN1: TXN0008229 | LDO1: TXN0008230 | LDP1: TXN0008231 | LDQ1: TXN0008232 | LDR1: TXN0008233 | LDS1: TXN0008234 | LDT1: TXN0008235 | LDU1: TXN0008236 | LDV1: TXN0008237 | LDW1: TXN0008238 | LDX1: TXN0008239 | LDY1: TXN0008240 | LDZ1: TXN0008241 | LEA1: TXN0008242 | LEB1: TXN0008243 | LEC1: TXN0008244 | LED1: TXN0008245 | LEE1: TXN0008246 | LEF1: TXN0008247 | LEG1: TXN0008248 | LEH1: TXN0008249 | LEI1: TXN0008250 | LEJ1: TXN0008251 | LEK1: TXN0008252 | LEL1: TXN0008253 | LEM1: TXN0008254 | LEN1: TXN0008255 | LEO1: TXN0008256 | LEP1: TXN0008257 | LEQ1: TXN0008258 | LER1: TXN0008259 | LES1: TXN0008260 | LET1: TXN0008261 | LEU1: TXN0008262 | LEV1: TXN0008263 | LEW1: TXN0008264 | LEX1: TXN0008265 | LEY1: TXN0008266 | LEZ1: TXN0008267 | LFA1: TXN0008268 | LFB1: TXN0008269 | LFC1: TXN0008270 | LFD1: TXN0008271 | LFE1: TXN0008272 | LFF1: TXN0008273 | LFG1: TXN0008274 | LFH1: TXN0008275 | LFI1: TXN0008276 | LFJ1: TXN0008277 | LFK1: TXN0008278 | LFL1: TXN0008279 | LFM1: TXN0008280 | LFN1: TXN0008281 | LFO1: TXN0008282 | LFP1: TXN0008283 | LFQ1: TXN0008284 | LFR1: TXN0008285 | LFS1: TXN0008286 | LFT1: TXN0008287 | LFU1: TXN0008288 | LFV1: TXN0008289 | LFW1: TXN0008290 | LFX1: TXN0008291 | LFY1: TXN0008292 | LFZ1: TXN0008293 | LGA1: TXN0008294 | LGB1: TXN0008295 | LGC1: TXN0008296 | LGD1: TXN0008297 | LGE1: TXN0008298 | LGF1: TXN0008299 | LGG1: TXN0008300 | LGH1: TXN0008301 | LGI1: TXN0008302 | LGJ1: TXN0008303 | LGK1: TXN0008304 | LGL1: TXN0008305 | LGM1: TXN0008306 | LGN1: TXN0008307 | LGO1: TXN0008308 | LGP1: TXN0008309 | LGQ1: TXN0008310 | LGR1: TXN0008311 | LGS1: TXN0008312 | LGT1: TXN0008313 | LGU1: TXN0008314 | LGV1: TXN0008315 | LGW1: TXN0008316 | LGX1: TXN0008317 | LGY1: TXN0008318 | LGZ1: TXN0008319 | LHA1: TXN0008320 | LHB1: TXN0008321 | LHC1: TXN0008322 | LHD1: TXN0008323 | LHE1: TXN0008324 | LHF1: TXN0008325 | LHG1: TXN0008326 | LHH1: TXN0008327 | LHI1: TXN0008328 | LHJ1: TXN0008329 | LHK1: TXN0008330 | LHL1: TXN0008331 | LHM1: TXN0008332 | LHN1: TXN0008333 | LHO1: TXN0008334 | LHP1: TXN0008335 | LHQ1: TXN0008336 | LHR1: TXN0008337 | LHS1: TXN0008338 | LHT1: TXN0008339 | LHU1: TXN0008340 | LHV1: TXN0008341 | LHW1: TXN0008342 | LHX1: TXN0008343 | LHY1: TXN0008344 | LHZ1: TXN0008345 | LIA1: TXN0008346 | LIB1: TXN0008347 | LIC1: TXN0008348 | LID1: TXN0008349 | LIE1: TXN0008350 | LIF1: TXN0008351 | LIG1: TXN0008352 | LIH1: TXN0008353 | LII1: TXN0008354 | LIJ1: TXN0008355 | LIK1: TXN0008356 | LIL1: TXN0008357 | LIM1: TXN0008358 | LIN1: TXN0008359 | LIO1: TXN0008360 | LIP1: TXN0008361 | LIQ1: TXN0008362 | LIR1: TXN0008363 | LIS1: TXN0008364 | LIT1: TXN0008365 | LIU1: TXN0008366 | LIV1: TXN0008367 | LIW1: TXN0008368 | LIX1: TXN0008369 | LIY1: TXN0008370 | LIZ1: TXN0008371 | LJA1: TXN0008372 | LJB1: TXN0008373 | LJC1: TXN0008374 | LJD1: TXN0008375 | LJE1: TXN0008376 | LJF1: TXN0008377 | LJG1: TXN0008378 | LJH1: TXN0008379 | LJI1: TXN0008380 | LJJ1: TXN0008381 | LJK1: TXN0008382 | LJL1: TXN0008383 | LJM1: TXN0008384 | LJN1: TXN0008385 | LJO1: TXN0008386 | LJP1: TXN0008387 | LJQ1: TXN0008388 | LJR1: TXN0008389 | LJS1: TXN0008390 | LJT1: TXN0008391 | LJU1: TXN0008392 | LJV1: TXN0008393 | LJW1: TXN0008394 | LJX1: TXN0008395 | LJY1: TXN0008396 | LJZ1: TXN0008397 | LKA1: TXN0008398 | LKB1: TXN0008399 | LKC1: TXN0008400 | LKD1: TXN0008401 | LKE1: TXN0008402 | LKF1: TXN0008403 | LKG1: TXN0008404 | LKH1: TXN0008405 | LKI1: TXN0008406 | LKJ1: TXN0008407 | LKK1: TXN0008408 | LKL1: TXN0008409 | LKM1: TXN0008410 | LKN1: TXN0008411 | LKO1: TXN0008412 | LKP1: TXN0008413 | LKQ1: TXN0008414 | LKR1: TXN0008415 | LKS1: TXN0008416 | LKT1: TXN0008417 | LKU1: TXN0008418 | LKV1: TXN0008419 | LKW1: TXN0008420 | LKX1: TXN0008421 | LKY1: TXN0008422 | LKZ1: TXN0008423 | LLA1: TXN0008424 | LLB1: TXN0008425 | LLC1: TXN0008426 | LLD1: TXN0008427 | LLE1: TXN0008428 | LLF1: TXN0008429 | LLG1: TXN0008430 | LLH1: TXN0008431 | LLI1: TXN0008432 | LLJ1: TXN0008433 | LLK1: TXN0008434 | LLL1: TXN0008435 | LLM1: TXN0008436 | LLN1: TXN0008437 | LLO1: TXN0008438 | LLP1: TXN0008439 | LLQ1: TXN0008440 | LLR1: TXN0008441 | LLS1: TXN0008442 | LLT1: TXN0008443 | LLU1: TXN0008444 | LLV1: TXN0008445 | LLW1: TXN0008446 | LLX1: TXN0008447 | LLY1: TXN0008448 | LLZ1: TXN0008449 | LMA1: TXN0008450 | LMB1: TXN0008451 | LMC1: TXN0008452 | LMD1: TXN0008453 | LME1: TXN0008454 | LMF1: TXN0008455 | LMG1: TXN0008456 | LMH1: TXN0008457 | LMI1: TXN0008458 | LMJ1: TXN0008459 | LMK1: TXN0008460 | LML1: TXN0008461 | LMM1: TXN0008462 | LMN1: TXN0008463 | LMO1: TXN0008464 | LMP1: TXN0008465 | LMQ1: TXN0008466 | LMR1: TXN0008467 | LMS1: TXN0008468 | LMT1: TXN0008469 | LMU1: TXN0008470 | LMV1: TXN0008471 | LMW1: TXN0008472 | LMX1: TXN0008473 | LMY1: TXN0008474 | LMZ1: TXN0008475 | LNA1: TXN0008476 | LNB1: TXN0008477 | LNC1: TXN0008478 | LND1: TXN0008479 | LNE1: TXN0008480 | LNF1: TXN0008481 | LNG1: TXN0008482 | LNH1: TXN0008483 | LNI1: TXN0008484 | LNJ1: TXN0008485 | LNK1: TXN0008486 | LNL1: TXN0008487 | LNM1: TXN0008488 | LNN1: TXN0008489 | LNO1: TXN0008490 | LNP1: TXN0008491 | LNQ1: TXN0008492 | LNR1: TXN0008493 | LNS1: TXN0008494 | LNT1: TXN0008495 | LNU1: TXN0008496 | LNV1: TXN0008497 | LNW1: TXN0008498 | LNX1: TXN0008499 | LNY1: TXN0008500 | LNZ1: TXN0008501 | LOA1: TXN0008502 | LOB1: TXN0008503 | LOC1: TXN0008504 | LOD1: TXN0008505 | LOE1: TXN0008506 | LOF1: TXN0008507 | LOG1: TXN0008508 | LOH1: TXN0008509 | LOI1: TXN0008510 | LOJ1: TXN0008511 | LOK1: TXN0008512 | LOL1: TXN0008513 | LOM1: TXN0008514 | LON1: TXN0008515 | LOO1: TXN0008516 | LOP1: TXN0008517 | LOQ1: TXN0008518 | LOR1: TXN0008519 | LOS1: TXN0008520 | LOT1: TXN0008521 | LOU1: TXN0008522 | LOV1: TXN0008523 | LOW1: TXN0008524 | LOX1: TXN0008525 | LOY1: TXN0008526 | LOZ1: TXN0008527 | LPA1: TXN0008528 | LPB1: TXN0008529 | LPC1: TXN0008530 | LPD1: TXN0008531 | LPE1: TXN0008532 | LPF1: TXN0008533 | LPG1: TXN0008534 | LPH1: TXN0008535 | LPI1: TXN0008536 | LPJ1: TXN0008537 | LPK1: TXN0008538 | LPL1: TXN0008539 | LPM1: TXN0008540 | LPN1: TXN0008541 | LPO1: TXN0008542 | LPP1: TXN0008543 | LPQ1: TXN0008544 | LPR1: TXN0008545 | LPS1: TXN0008546 | LPT1: TXN0008547 | LPU1: TXN0008548 | LPV1: TXN0008549 | LPW1: TXN0008550 | LPX1: TXN0008551 | LPY1: TXN0008552 | LPZ1: TXN0008553 | LQA1: TXN0008554 | LQB1: TXN0008555 | LQC1: TXN0008556 | LQD1: TXN0008557 | LQE1: TXN0008558 | LQF1: TXN0008559 | LQG1: TXN0008560 | LQH1: TXN0008561 | LQI1: TXN0008562 | LQJ1: TXN0008563 | LQK1: TXN0008564 | LQL1: TXN0008565 | LQM1: TXN0008566 | LQN1: TXN0008567 | LQO1: TXN0008568 | LQP1: TXN0008569 | LQQ1: TXN0008570 | LQR1: TXN0008571 | LQS1: TXN0008572 | LQT1: TXN0008573 | LQU1: TXN0008574 | LQV1: TXN0008575 | LQW1: TXN0008576 | LQX1: TXN0008577 | LQY1: TXN0008578 | LQZ1: TXN0008579 | LRA1: TXN0008580 | LRB1: TXN0008581 | LRC1: TXN0008582 | LRD1: TXN0008583 | LRE1: TXN0008584 | LRF1: TXN0008585 | LRG1: TXN0008586 | LRH1: TXN0008587 | LRI1: TXN0008588 | LRJ1: TXN0008589 | LRK1: TXN0008590 | LRL1: TXN0008591 | LRM1: TXN0008592 | LRN1: TXN0008593 | LRO1: TXN0008594 | LRP1: TXN0008595 | LRQ1: TXN0008596 | LRR1: TXN0008597 | LRS1: TXN0008598 | LRT1: TXN0008599 | LRU1: TXN0008600 | LRV1: TXN0008601 | LRW1: TXN0008602 | LRX1: TXN0008603 | LRY1: TXN0008604 | LRZ1: TXN0008605 | LSA1: TXN0008606 | LSB1: TXN0008607 | LSC1: TXN0008608 | LSD1: TXN0008609 | LSE1: TXN0008610 | LSF1: TXN0008611 | LSG1: TXN0008612 | LSH1: TXN0008613 | LSI1: TXN0008614 | LSJ1: TXN0008615 | LSK1: TXN0008616 | LSL1: TXN0008617 | LSM1: TXN0008618 | LSN1: TXN0008619 | LSO1: TXN0008620 | LSP1: TXN0008621 | LSQ1: TXN0008622 | LSR1: TXN0008623 | LSS1: TXN0008624 | LST1: TXN0008625 | LSU1: TXN0008626 | LSV1: TXN0008627 | LSW1: TXN0008628 | LSX1: TXN0008629 | LSY1: TXN0008630 | LSZ1: TXN0008631 | LTA1: TXN0008632 | LTB1: TXN0008633 | LTC1: TXN0008634 | LTD1: TXN0008635 | LTE1: TXN0008636 | LTF1: TXN0008637 | LTG1: TXN0008638 | LTH1: TXN0008639 | LTI1: TXN0008640 | LTJ1: TXN0008641 | LTK1: TXN0008642 | LTL1: TXN0008643 | LTM1: TXN0008644 | LTN1: TXN0008645 | LTO1: TXN0008646 | LTP1: TXN0008647 | LTQ1: TXN0008648 | LTR1: TXN0008649 | LTS1: TXN0008650 | LTT1: TXN0008651 | LTU1: TXN0008652 | LTV1: TXN0008653 | LTW1: TXN0008654 | LTX1: TXN0008655 | LTY1: TXN0008656 | LTZ1: TXN0008657 | LUA1: TXN0008658 | LUB1: TXN0008659 | LUC1: TXN0008660 | LUD1: TXN0008661 | LUE1: TXN0008662 | LUF1: TXN0008663 | LUG1: TXN0008664 | LUH1: TXN0008665 | LUI1: TXN0008666 | LUJ1: TXN0008667 | LUK1: TXN0008668 | LUL1: TXN0008669 | LUM1: TXN0008670 | LUN1: TXN0008671 | LUO1: TXN0008672 | LUP1: TXN0008673 | LUQ1: TXN0008674 | LUR1: TXN0008675 | LUS1: TXN0008676 | LUT1: TXN0008677 | LUU1: TXN0008678 | LUV1: TXN0008679 | LUW1: TXN0008680 | LUX1: TXN0008681 | LUY1: TXN0008682 | LUZ1: TXN0008683 | LVA1: TXN0008684 | LVB1: TXN0008685 | LVC1: TXN0008686 | LVD1: TXN0008687 | LVE1: TXN0008688 | LVF1: TXN0008689 | LVG1: TXN0008690 | LVH1: TXN0008691 | LVI1: TXN0008692 | LVJ1: TXN0008693 | LVK1: TXN0008694 | LVL1: TXN0008695 | LVM1: TXN0008696 | LVN1: TXN0008697 | LVO1: TXN0008698 | LVP1: TXN0008699 | LVQ1: TXN0008700 | LVR1: TXN0008701 | LVS1: TXN0008702 | LVT1: TXN0008703 | LVU1: TXN0008704 | LVV1: TXN0008705 | LVW1: TXN0008706 | LVX1: TXN0008707 | LVY1: TXN0008708 | LVZ1: TXN0008709 | LWA1: TXN0008710 | LWB1: TXN0008711 | LWC1: TXN0008712 | LWD1: TXN0008713 | LWE1: TXN0008714 | LWF1: TXN0008715 | LWG1: TXN0008716 | LWH1: TXN0008717 | LWI1: TXN0008718 | LWJ1: TXN0008719 | LWK1: TXN0008720 | LWL1: TXN0008721 | LWM1: TXN0008722 | LWN1: TXN0008723 | LWO1: TXN0008724 | LWP1: TXN0008725 | LWQ1: TXN0008726 | LWR1: TXN0008727 | LWS1: TXN0008728 | LWT1: TXN0008729 | LWU1: TXN0008730 | LWV1: TXN0008731 | LWW1: TXN0008732 | LWX1: TXN0008733 | LWY1: TXN0008734 | LWZ1: TXN0008735 | LXA1: TXN0008736 | LXB1: TXN0008737 | LXC1: TXN0008738 | LXD1: TXN0008739 | LXE1: TXN0008740 | LXF1: TXN0008741 | LXG1: TXN0008742 | LXH1: TXN0008743 | LXI1: TXN0008744 | LXJ1: TXN0008745 | LXK1: TXN0008746 | LXL1: TXN0008747 | LXM1: TXN0008748 | LXN1: TXN0008749 | LXO1: TXN0008750 | LXP1: TXN0008751 | LXQ1: TXN0008752 | LXR1: TXN0008753 | LXS1: TXN0008754 | LXT1: TXN0008755 | LXU1: TXN0008756 | LXV1: TXN0008757 | LXW1: TXN0008758 | LXX1: TXN0008759 | LXY1: TXN0008760 | LXZ1: TXN0008761 | LYA1: TXN0008762 | LYB1: TXN0008763 | LYC1: TXN0008764 | LYD1: TXN0008765 | LYE1: TXN0008766 | LYF1: TXN0008767 | LYG1: TXN0008768 | LYH1: TXN0008769 | LYI1: TXN0008770 | LYJ1: TXN0008771 | LYK1: TXN0008772 | LYL1: TXN0008773 | LYM1: TXN0008774 | LYN1: TXN0008775 | LYO1: TXN0008776 | LYP1: TXN0008777 | LYQ1: TXN0008778 | LYR1: TXN0008779 | LYS1: TXN0008780 | LYT1: TXN0008781 | LYU1: TXN0008782 | LYV1: TXN0008783 | LYW1: TXN0008784 | LYX1: TXN0008785 | LYY1: TXN0008786 | LYZ1: TXN0008787 | LZA1: TXN0008788 | LZB1: TXN0008789 | LZC1: TXN0008790 | LZD1: TXN0008791 | LZE1: TXN0008792 | LZF1: TXN0008793 | LZG1: TXN0008794 | LZH1: TXN0008795 | LZI1: TXN0008796 | LZJ1: TXN0008797 | LZK1: TXN0008798 | LZL1: TXN0008799 | LZM1: TXN0008800 | LZN1: TXN0008801 | LZO1: TXN0008802 | LZP1: TXN0008803 | LZQ1: TXN0008804 | LZR1: TXN0008805 | LZS1: TXN0008806 | LZT1: TXN0008807 | LZU1: TXN0008808 | LZV1: TXN0008809 | LZW1: TXN0008810 | LZX1: TXN0008811 | LZY1: TXN0008812 | LZZ1: TXN0008813 | MAA1: TXN0008814 | MAB1: TXN0008815 | MAC1: TXN0008816 | MAD1: TXN0008817 | MAE1: TXN0008818 | MAF1: TXN0008819 | MAG1: TXN0008820 | MAH1: TXN0008821 | MAI1: TXN0008822 | MAJ1: TXN0008823 | MAK1: TXN0008824 | MAL1: TXN0008825 | MAM1: TXN0008826 | MAN1: TXN0008827 | MAO1: TXN0008828 | MAP1: TXN0008829 | MAQ1: TXN0008830 | MAR1: TXN0008831 | MAS1: TXN0008832 | MAT1: TXN0008833 | MAU1: TXN0008834 | MAV1: TXN0008835 | MAW1: TXN0008836 | MAX1: TXN0008837 | MAY1: TXN0008838 | MAZ1: TXN0008839 | MBA1: TXN0008840 | MBB1: TXN0008841 | MBC1: TXN0008842 | MBD1: TXN0008843 | MBE1: TXN0008844 | MBF1: TXN0008845 | MBG1: TXN0008846 | MBH1: TXN0008847 | MBI1: TXN0008848 | MBJ1: TXN0008849 | MBK1: TXN0008850 | MBL1: TXN0008851 | MBM1: TXN0008852 | MBN1: TXN0008853 | MBO1: TXN0008854 | MBP1: TXN0008855 | MBQ1: TXN0008856 | MBR1: TXN0008857 | MBS1: TXN0008858 | MBT1: TXN0008859 | MBU1: TXN0008860 | MBV1: TXN0008861 | MBW1: TXN0008862 | MBX1: TXN0008863 | MBY1: TXN0008864 | MBZ1: TXN0008865 | MCA1: TXN0008866 | MCB1: TXN0008867 | MCC1: TXN0008868 | MCD1: TXN0008869 | MCE1: TXN0008870 | MCF1: TXN0008871 | MCG1: TXN0008872 | MCH1: TXN0008873 | MCI1: TXN0008874 | MCJ1: TXN0008875 | MCK1: TXN0008876 | MCL1: TXN0008877 | MCM1: TXN0008878 | MCN1: TXN0008879 | MCO1: TXN0008880 | MCP1: TXN0008881 | MCQ1: TXN0008882 | MCR1: TXN0008883 | MCS1: TXN0008884 | MCT1: TXN0008885 | MCU1: TXN0008886 | MCV1: TXN0008887 | MCW1: TXN0008888 | MCX1: TXN0008889 | MCY1: TXN0008890 | MCZ1: TXN0008891 | MDA1: TXN0008892 | MDB1: TXN0008893 | MDC1: TXN0008894 | MDD1: TXN0008895 | MDE1: TXN0008896 | MDF1: TXN0008897 | MDG1: TXN0008898 | MDH1: TXN0008899 | MDI1: TXN0008900 | MDJ1: TXN0008901 | MDK1: TXN0008902 | MDL1: TXN0008903 | MDM1: TXN0008904 | MDN1: TXN0008905 | MDO1: TXN0008906 | MDP1: TXN0008907 | MDQ1: TXN0008908 | MDR1: TXN0008909 | MDS1: TXN0008910 | MDT1: TXN0008911 | MDU1: TXN0008912 | MDV1: TXN0008913 | MDW1: TXN0008914 | MDX1: TXN0008915 | MDY1: TXN0008916 | MDZ1: TXN0008917 | MEA1: TXN0008918 | MEB1: TXN0008919 | MEC1: TXN0008920 | MED1: TXN0008921 | MEE1: TXN0008922 | MEF1: TXN0008923 | MEG1: TXN0008924 | MEH1: TXN0008925 | MEI1: TXN0008926 | MEJ1: TXN0008927 | MEK1: TXN0008928 | MEL1: TXN0008929 | MEM1: TXN0008930 | MEN1: TXN0008931 | MEO1: TXN0008932 | MEP1: TXN0008933 | MEQ1: TXN0008934 | MER1: TXN0008935 | MES1: TXN0008936 | MET1: TXN0008937 | MEU1: TXN0008938 | MEV1: TXN0008939 | MEW1: TXN0008940 | MEX1: TXN0008941 | MEY1: TXN0008942 | MEZ1: TXN0008943 | MFA1: TXN0008944 | MFB1: TXN0008945 | MFC1: TXN0008946 | MFD1: TXN0008947 | MFE1: TXN0008948 | MFF1: TXN0008949 | MFG1: TXN0008950 | MFH1: TXN0008951 | MFI1: TXN0008952 | MFJ1: TXN0008953 | MFK1: TXN0008954 | MFL1: TXN0008955 | MFM1: TXN0008956 | MFN1: TXN0008957 | MFO1: TXN0008958 | MFP1: TXN0008959 | MFQ1: TXN0008960 | MFR1: TXN0008961 | MFS1: TXN0008962 | MFT1: TXN0008963 | MFU1: TXN0008964 | MFV1: TXN0008965 | MFW1: TXN0008966 | MFX1: TXN0008967 | MFY1: TXN0008968 | MFZ1: TXN0008969 | MGA1: TXN0008970 | MGB1: TXN0008971 | MGC1: TXN0008972 | MGD1: TXN0008973 | MGE1: TXN0008974 | MGF1: TXN0008975 | MGG1: TXN0008976 | MGH1: TXN0008977 | MGI1: TXN0008978 | MGJ1: TXN0008979 | MGK1: TXN0008980 | MGL1: TXN0008981 | MGM1: TXN0008982 | MGN1: TXN0008983 | MGO1: TXN0008984 | MGP1: TXN0008985 | MGQ1: TXN0008986 | MGR1: TXN0008987 | MGS1: TXN0008988 | MGT1: TXN0008989 | MGU1: TXN0008990 | MGV1: TXN0008991 | MGW1: TXN0008992 | MGX1: TXN0008993 | MGY1: TXN0008994 | MGZ1: TXN0008995 | MHA1: TXN0008996 | MHB1: TXN0008997 | MHC1: TXN0008998 | MHD1: TXN0008999 | MHE1: TXN0009000 | MHF1: TXN0009001 | MHG1: TXN0009002 | MHH1: TXN0009003 | MHI1: TXN0009004 | MHJ1: TXN0009005 | MHK1: TXN0009006 | MHL1: TXN0009007 | MHM1: TXN0009008 | MHN1: TXN0009009 | MHO1: TXN0009010 | MHP1: TXN0009011 | MHQ1: TXN0009012 | MHR1: TXN0009013 | MHS1: TXN0009014 | MHT1: TXN0009015 | MHU1: TXN0009016 | MHV1: TXN0009017 | MHW1: TXN0009018 | MHX1: TXN0009019 | MHY1: TXN0009020 | MHZ1: TXN0009021 | MIA1: TXN0009022 | MIB1: TXN0009023 | MIC1: TXN0009024 | MID1: TXN0009025 | MIE1: TXN0009026 | MIF1: TXN0009027 | MIG1: TXN0009028 | MIH1: TXN0009029 | MII1: TXN0009030 | MIJ1: TXN0009031 | MIK1: TXN0009032 | MIL1: TXN0009033 | MIM1: TXN0009034 | MIN1: TXN0009035 | MIO1: TXN0009036 | MIP1: TXN0009037 | MIQ1: TXN0009038 | MIR1: TXN0009039 | MIS1: TXN0009040 | MIT1: TXN0009041 | MIU1: TXN0009042 | MIV1: TXN0009043 | MIW1: TXN0009044 | MIX1: TXN0009045 | MIY1: TXN0009046 | MIZ1: TXN0009047 | MJA1: TXN0009048 | MJB1: TXN0009049 | MJC1: TXN0009050 | MJD1: TXN0009051 | MJE1: TXN0009052 | MJF1: TXN0009053 | MJG1: TXN0009054 | MJH1: TXN0009055 | MJI1: TXN0009056 | MJJ1: TXN0009057 | MJK1: TXN0009058 | MJL1: TXN0009059 | MJM1: TXN0009060 | MJN1: TXN0009061 | MJO1: TXN0009062 | MJP1: TXN0009063 | MJQ1: TXN0009064 | MJR1: TXN0009065 | MJS1: TXN0009066 | MJT1: TXN0009067 | MJU1: TXN0009068 | MJV1: TXN0009069 | MJW1: TXN0009070 | MJX1: TXN0009071 | MJY1: TXN0009072 | MJZ1: TXN0009073 | MKA1: TXN0009074 | MKB1: TXN0009075 | MKC1: TXN0009076 | MKD1: TXN0009077 | MKE1: TXN0009078 | MKF1: TXN0009079 | MKG1: TXN0009080 | MKH1: TXN0009081 | MKI1: TXN0009082 | MKJ1: TXN0009083 | MKK1: TXN0009084 | MKL1: TXN0009085 | MKM1: TXN0009086 | MKN1: TXN0009087 | MKO1: TXN0009088 | MKP1: TXN0009089 | MKQ1: TXN0009090 | MKR1: TXN0009091 | MKS1: TXN0009092 | MKT1: TXN0009093 | MKU1: TXN0009094 | MKV1: TXN0009095 | MKW1: TXN0009096 | MKX1: TXN0009097 | MKY1: TXN0009098 | MKZ1: TXN0009099 | MLA1: TXN0009100 | MLB1: TXN0009101 | MLC1: TXN0009102 | MLD1: TXN0009103 | MLE1: TXN0009104 | MLF1: TXN0009105 | MLG1: TXN0009106 | MLH1: TXN0009107 | MLI1: TXN0009108 | MLJ1: TXN0009109 | MLK1: TXN0009110 | MLL1: TXN0009111 | MLM1: TXN0009112 | MLN1: TXN0009113 | MLO1: TXN0009114 | MLP1: TXN0009115 | MLQ1: TXN0009116 | MLR1: TXN0009117 | MLS1: TXN0009118 | MLT1: TXN0009119 | MLU1: TXN0009120 | MLV1: TXN0009121 | MLW1: TXN0009122 | MLX1: TXN0009123 | MLY1: TXN0009124 | MLZ1: TXN0009125 | MMA1: TXN0009126 | MMB1: TXN0009127 | MMC1: TXN0009128 | MMD1: TXN0009129 | MME1: TXN0009130 | MMF1: TXN0009131 | MMG1: TXN0009132 | MMH1: TXN0009133 | MMI1: TXN0009134 | MMJ1: TXN0009135 | MMK1: TXN0009136 | MML1: TXN0009137 | MMM1: TXN0009138 | MMN1: TXN0009139 | MMO1: TXN0009140 | MMP1: TXN0009141 | MMQ1: TXN0009142 | MMR1: TXN0009143 | MMS1: TXN0009144 | MMT1: TXN0009145 | MMU1: TXN0009146 | MMV1: TXN0009147 | MMW1: TXN0009148 | MMX1: TXN0009149 | MMY1: TXN0009150 | MMZ1: TXN0009151 | MNA1: TXN0009152 | MNB1: TXN0009153 | MNC1: TXN0009154 | MND1: TXN0009155 | MNE1: TXN0009156 | MNF1: TXN0009157 | MNG1: TXN0009158 | MNH1: TXN0009159 | MNI1: TXN0009160 | MNJ1: TXN0009161 | MNK1: TXN0009162 | MNL1: TXN0009163 | MNM1: TXN0009164 | MNN1: TXN0009165 | MNO1: TXN0009166 | MNP1: TXN0009167 | MNQ1: TXN0009168 | MNR1: TXN0009169 | MNS1: TXN0009170 | MNT1: TXN0009171 | MNU1: TXN0009172 | MNV1: TXN0009173 | MNW1: TXN0009174 | MNX1: TXN0009175 | MNY1: TXN0009176 | MNZ1: TXN0009177 | MOA1: TXN0009178 | MOB1: TXN0009179 | MOC1: TXN0009180 | MOD1: TXN0009181 | MOE1: TXN0009182 | MOF1: TXN0009183 | MOG1: TXN0009184 | MOH1: TXN0009185 | MOI1: TXN0009186 | MOJ1: TXN0009187 | MOK1: TXN0009188 | MOL1: TXN0009189 | MOM1: TXN0009190 | MON1: TXN0009191 | MOO1: TXN0009192 | MOP1: TXN0009193 | MOQ1: TXN0009194 | MOR1: TXN0009195 | MOS1: TXN0009196 | MOT1: TXN0009197 | MOU1: TXN0009198 | MOV1: TXN0009199 | MOW1: TXN0009200 | MOX1: TXN0009201 | MOY1: TXN0009202 | MOZ1: TXN0009203 | MPA1: TXN0009204 | MPB1: TXN0009205 | MPC1: TXN0009206 | MPD1: TXN0009207 | MPE1: TXN0009208 | MPF1: TXN0009209 | MPG1: TXN0009210 | MPH1: TXN0009211 | MPI1: TXN0009212 | MPJ1: TXN0009213 | MPK1: TXN0009214 | MPL1: TXN0009215 | MPM1: TXN0009216 | MPN1: TXN0009217 | MPO1: TXN0009218 | MPP1: TXN0009219 | MPQ1: TXN0009220 | MPR1: TXN0009221 | MPS1: TXN0009222 | MPT1: TXN0009223 | MPU1: TXN0009224 | MPV1: TXN0009225 | MPW1: TXN0009226 | MPX1: TXN0009227 | MPY1: TXN0009228 | MPZ1: TXN0009229 | MQA1: TXN0009230 | MQB1: TXN0009231 | MQC1: TXN0009232 | MQD1: TXN0009233 | MQE1: TXN0009234 | MQF1: TXN0009235 | MQG1: TXN0009236 | MQH1: TXN0009237 | MQI1: TXN0009238 | MQJ1: TXN0009239 | MQK1: TXN0009240 | MQL1: TXN0009241 | MQM1: TXN0009242 | MQN1: TXN0009243 | MQO1: TXN0009244 | MQP1: TXN0009245 | MQQ1: TXN0009246 | MQR1: TXN0009247 | MQS1: TXN0009248 | MQT1: TXN0009249 | MQU1: TXN0009250 | MQV1: TXN0009251 | MQW1: TXN0009252 | MQX1: TXN0009253 | MQY1: TXN0009254 | MQZ1: TXN0009255 | MRA1: TXN0009256 | MRB1: TXN0009257 | MRC1: TXN0009258 | MRD1: TXN0009259 | MRE1: TXN0009260 | MRF1: TXN0009261 | MRG1: TXN0009262 | MRH1: TXN0009263 | MRI1: TXN0009264 | MRJ1: TXN0009265 | MRK1: TXN0009266 | MRL1: TXN0009267 | MRM1: TXN0009268 | MRN1: TXN0009269 | MRO1: TXN0009270 | MRP1: TXN0009271 | MRQ1: TXN0009272 | MRR1: TXN0009273 | MRS1: TXN0009274 | MRT1: TXN0009275 | MRU1: TXN0009276 | MRV1: TXN0009277 | MRW1: TXN0009278 | MRX1: TXN0009279 | MRY1: TXN0009280 | MRZ1: TXN0009281 | MSA1: TXN0009282 | MSB1: TXN0009283 | MSC1: TXN0009284 | MSD1: TXN0009285 | MSE1: TXN0009286 | MSF1: TXN0009287 | MSG1: TXN0009288 | MSH1: TXN0009289 | MSI1: TXN0009290 | MSJ1: TXN0009291 | MSK1: TXN0009292 | MSL1: TXN0009293 | MSM1: TXN0009294 | MSN1: TXN0009295 | MSO1: TXN0009296 | MSP1: TXN0009297 | MSQ1: TXN0009298 | MSR1: TXN0009299 | MSS1: TXN0009300 | MST1: TXN0009301 | MSU1: TXN0009302 | MSV1: TXN0009303 | MSW1: TXN0009304 | MSX1: TXN0009305 | MSY1: TXN0009306 | MSZ1: TXN0009307 | MTA1: TXN0009308 | MTB1: TXN0009309 | MTC1: TXN0009310 | MTD1: TXN0009311 | MTE1: TXN0009312 | MTF1: TXN0009313 | MTG1: TXN0009314 | MTH1: TXN0009315 | MTI1: TXN0009316 | MTJ1: TXN0009317 | MTK1: TXN0009318 | MTL1: TXN0009319 | MTM1: TXN0009320 | MTN1: TXN0009321 | MTO1: TXN0009322 | MTP1: TXN0009323 | MTQ1: TXN0009324 | MTR1: TXN0009325 | MTS1: TXN0009326 | MTT1: TXN0009327 | MTU1: TXN0009328 | MTV1: TXN0009329 | MTW1: TXN0009330 | MTX1: TXN0009331 | MTY1: TXN0009332 | MTZ1: TXN0009333 | MUA1: TXN0009334 | MUB1: TXN0009335 | MUC1: TXN0009336 | MUD1: TXN0009337 | MUE1: TXN0009338 | MUF1: TXN0009339 | MUG1: TXN0009340 | MUH1: TXN0009341 | MUI1: TXN0009342 | MUJ1: TXN0009343 | MUK1: TXN0009344 | MUL1: TXN0009345 | MUM1: TXN0009346 | MUN1: TXN0009347 | MUO1: TXN0009348 | MUP1: TXN0009349 | MUQ1: TXN0009350 | MUR1: TXN0009351 | MUS1: TXN0009352 | MUT1: TXN0009353 | MUU1: TXN0009354 | MUV1: TXN0009355 | MUW1: TXN0009356 | MUX1: TXN0009357 | MUY1: TXN0009358 | MUZ1: TXN0009359 | MVA1: TXN0009360 | MVB1: TXN0009361 | MVC1: TXN0009362 | MVD1: TXN0009363 | MVE1: TXN0009364 | MVF1: TXN0009365 | MVG1: TXN0009366 | MVH1: TXN0009367 | MVI1: TXN0009368 | MVJ1: TXN0009369 | MVK1: TXN0009370 | MVL1: TXN0009371 | MVM1: TXN0009372 | MVN1: TXN0009373 | MVO1: TXN0009374 | MVP1: TXN0009375 | MVQ1: TXN0009376 | MVR1: TXN0009377 | MVS1: TXN0009378 | MVT1: TXN0009379 | MVU1: TXN0009380 | MVV1: TXN0009381 | MVW1: TXN0009382 | MVX1: TXN0009383 | MVY1: TXN0009384 | MVZ1: TXN0009385 | MWA1: TXN0009386 | MWB1: TXN0009387 | MWC1: TXN0009388 | MWD1: TXN0009389 | MWE1: TXN0009390 | MWF1: TXN0009391 | MWG1: TXN0009392 | MWH1: TXN0009393 | MWI1: TXN0009394 | MWJ1: TXN0009395 | MWK1: TXN0009396 | MWL1: TXN0009397 | MWM1: TXN0009398 | MWN1: TXN0009399 | MWO1: TXN0009400 | MWP1: TXN0009401 | MWQ1: TXN0009402 | MWR1: TXN0009403 | MWS1: TXN0009404 | MWT1: TXN0009405 | MWU1: TXN0009406 | MWV1: TXN0009407 | MWW1: TXN0009408 | MWX1: TXN0009409 | MWY1: TXN0009410 | MWZ1: TXN0009411 | MXA1: TXN0009412 | MXB1: TXN0009413 | MXC1: TXN0009414 | MXD1: TXN0009415 | MXE1: TXN0009416 | MXF1: TXN0009417 | MXG1: TXN0009418 | MXH1: TXN0009419 | MXI1: TXN0009420 | MXJ1: TXN0009421 | MXK1: TXN0009422 | MXL1: TXN0009423 | MXM1: TXN0009424 | MXN1: TXN0009425 | MXO1: TXN0009426 | MXP1: TXN0009427 | MXQ1: TXN0009428 | MXR1: TXN0009429 | MXS1: TXN0009430 | MXT1: TXN0009431 | MXU1: TXN0009432 | MXV1: TXN0009433 | MXW1: TXN0009434 | MXX1: TXN0009435 | MXY1: TXN0009436 | MXZ1: TXN0009437 | MYA1: TXN0009438 | MYB1: TXN0009439 | MYC1: TXN0009440 | MYD1: TXN0009441 | MYE1: TXN0009442 | MYF1: TXN0009443 | MYG1: TXN0009444 | MYH1: TXN0009445 | MYI1: TXN0009446 | MYJ1: TXN0009447 | MYK1: TXN0009448 | MYL1: TXN0009449 | MYM1: TXN0009450 | MYN1: TXN0009451 | MYO1: TXN0009452 | MYP1: TXN0009453 | MYQ1: TXN0009454 | MYR1: TXN0009455 | MYS1: TXN0009456 | MYT1: TXN0009457 | MYU1: TXN0009458 | MYV1: TXN0009459 | MYW1: TXN0009460 | MYX1: TXN0009461 | MYY1: TXN0009462 | MYZ1: TXN0009463 | MZA1: TXN0009464 | MZB1: TXN0009465 | MZC1: TXN0009466 | MZD1: TXN0009467 | MZE1: TXN0009468 | MZF1: TXN0009469 | MZG1: TXN0009470 | MZH1: TXN0009471 | MZI1: TXN0009472 | MZJ1: TXN0009473 | MZK1: TXN0009474 | MZL1: TXN0009475 | MZM1: TXN0009476 | MZN1: TXN0009477 | MZO1: TXN0009478 | MZP1: TXN0009479 | MZQ1: TXN0009480 | MZR1: TXN0009481 | MZS1: TXN0009482 | MZT1: TXN0009483 | MZU1: TXN0009484 | MZV1: TXN0009485 | MZW1: TXN0009486 | MZX1: TXN0009487 | MZY1: TXN0009488 | MZZ1: TXN0009489 | NAA1: TXN0009490 | NAB1: TXN0009491 | NAC1: TXN0009492 | NAD1: TXN0009493 | NAE1: TXN0009494 | NAF1: TXN0009495 | NAG1: TXN0009496 | NAH1: TXN0009497 | NAI1: TXN0009498 | NAJ1: TXN0009499 | NAK1: TXN0009500 | NAL1: TXN0009501 | NAM1: TXN0009502 | NAN1: TXN0009503 | NAO1: TXN0009504 | NAP1: TXN0009505 | NAQ1: TXN0009506 | NAR1: TXN0009507 | NAS1: TXN0009508 | NAT1: TXN0009509 | NAU1: TXN0009510 | NAV1: TXN0009511 | NAW1: TXN0009512 | NAX1: TXN0009513 | NAY1: TXN0009514 | NAZ1: TXN0009515 | NBA1: TXN0009516 | NBB1: TXN0009517 | NBC1: TXN0009518 | NBD1: TXN0009519 | NBE1: TXN0009520 | NBF1: TXN0009521 | NBG1: TXN0009522 | NBH1: TXN0009523 | NBI1: TXN0009524 | NBJ1: TXN0009525 | NBK1: TXN0009526 | NBL1: TXN0009527 | NBM1: TXN0009528 | NBN1: TXN0009529 | NBO1: TXN0009530 | NBP1: TXN0009531 | NBQ1: TXN0009532 | NBR1: TXN0009533 | NBS1: TXN0009534 | NBT1: TXN0009535 | NBU1: TXN0009536 | NBV1: TXN0009537 | NBW1: TXN0009538 | NBX1: TXN0009539 | NBY1: TXN0009540 | NBZ1: TXN0009541 | NCA1: TXN0009542 | NCB1: TXN0009543 | NCC1: TXN0009544 | NCD1: TXN0009545 | NCE1: TXN0009546 | NCF1: TXN0009547 | NCG1: TXN0009548 | NCH1: TXN0009549 | NCI1: TXN0009550 | NCJ1: TXN0009551 | NCK1: TXN0009552 | NCL1: TXN0009553 | NCM1: TXN0009554 | NCN1: TXN0009555 | NCO1: TXN0009556 | NCP1: TXN0009557 | NCQ1: TXN0009558 | NCR1: TXN0009559 | NCS1: TXN0009560 | NCT1: TXN0009561 | NCU1: TXN0009562 | NCV1: TXN0009563 | NCW1: TXN0009564 | NCX1: TXN0009565 | NCY1: TXN0009566 | NCZ1: TXN0009567 | NDA1: TXN0009568 | NDB1: TXN0009569 | NDC1: TXN0009570 | NDD1: TXN0009571 | NDE1: TXN0009572 | NDF1: TXN0009573 | NDG1: TXN0009574 | NDH1: TXN0009575 | NDI1: TXN0009576 | NDJ1: TXN0009577 | NDK1: TXN0009578 | NDL1: TXN0009579 | NDM1: TXN0009580 | NDN1: TXN0009581 | NDO1: TXN0009582 | NDP1: TXN0009583 | NDQ1: TXN0009584 | NDR1: TXN0009585 | NDS1: TXN0009586 | NDT1: TXN0009587 | NDU1: TXN0009588 | NDV1: TXN0009589 | NDW1: TXN0009590 | NDX1: TXN0009591 | NDY1: TXN0009592 | NDZ1: TXN0009593 | NEA1: TXN0009594 | NEB1: TXN0009595 | NEC1: TXN0009596 | NED1: TXN0009597 | NEE1: TXN0009598 | NEF1: TXN0009599 | NEG1: TXN0009600 | NEH1: TXN0009601 | NEI1: TXN0009602 | NEJ1: TXN0009603 | NEK1: TXN0009604 | NEL1: TXN0009605 | NEM1: TXN0009606 | NEN1: TXN0009607 | NEO1: TXN0009608 | NEP1: TXN0009609 | NEQ1: TXN0009610 | NER1: TXN0009611 | NES1: TXN0009612 | NET1: TXN0009613 | NEU1: TXN0009614 | NEV1: TXN0009615 | NEW1: TXN0009616 | NEX1: TXN0009617 | NEY1: TXN0009618 | NEZ1: TXN0009619 | NFA1: TXN0009620 | NFB1: TXN0009621 | NFC1: TXN0009622 | NFD1: TXN0009623 | NFE1: TXN0009624 | NFF1: TXN0009625 | NFG1: TXN0009626 | NFH1: TXN0009627 | NFI1: TXN0009628 | NFJ1: TXN0009629 | NFK1: TXN0009630 | NFL1: TXN0009631 | NFM1: TXN0009632 | NFN1: TXN0009633 | NFO1: TXN0009634 | NFP1: TXN0009635 | NFQ1: TXN0009636 | NFR1: TXN0009637 | NFS1: TXN0009638 | NFT1: TXN0009639 | NFU1: TXN0009640 | NFV1: TXN0009641 | NFW1: TXN0009642 | NFX1: TXN0009643 | NFY1: TXN0009644 | NFZ1: TXN0009645 | NGA1: TXN0009646 | NGB1: TXN0009647 | NGC1: TXN0009648 | NGD1: TXN0009649 | NGE1: TXN0009650 | NGF1: TXN0009651 | NGG1: TXN0009652 | NGH1: TXN0009653 | NGI1: TXN0009654 | NGJ1: TXN0009655 | NGK1: TXN0009656 | NGL1: TXN0009657 | NGM1: TXN0009658 | NGN1: TXN0009659 | NGO1: TXN0009660 | NGP1: TXN0009661 | NGQ1: TXN0009662 | NGR1: TXN0009663 | NGS1: TXN0009664 | NGT1: TXN0009665 | NGU1: TXN0009666 | NGV1: TXN0009667 | NGW1: TXN0009668 | NGX1: TXN0009669 | NGY1: TXN0009670 | NGZ1: TXN0009671 | NHA1: TXN0009672 | NHB1: TXN0009673 | NHC1: TXN0009674 | NHD1: TXN0009675 | NHE1: TXN0009676 | NHF1: TXN0009677 | NHG1: TXN0009678 | NHH1: TXN0009679 | NHI1: TXN0009680 | NHJ1: TXN0009681 | NHK1: TXN0009682 | NHL1: TXN0009683 | NHM1: TXN0009684 | NHN1: TXN0009685 | NHO1: TXN0009686 | NHP1: TXN0009687 | NHQ1: TXN0009688 | NHR1: TXN0009689 | NHS1: TXN0009690 | NHT1: TXN0009691 | NHU1: TXN0009692 | NHV1: TXN0009693 | NHW1: TXN0009694 | NHX1: TXN0009695 | NHY1: TXN0009696 | NHZ1: TXN0009697 | NIA1: TXN0009698 | NIB1: TXN0009699 | NIC1: TXN0009700 | NID1: TXN0009701 | NIE1: TXN0009702 | NIF1: TXN0009703 | NIG1: TXN0009704 | NIH1: TXN0009705 | NII1: TXN0009706 | NIJ1: TXN0009707 | NIK1: TXN0009708 | NIL1: TXN0009709 | NIM1: TXN0009710 | NIN1: TXN0009711 | NIO1: TXN0009712 | NIP1: TXN0009713 | NIQ1: TXN0009714 | NIR1: TXN0009715 | NIS1: TXN0009716 | NIT1: TXN0009717 | NIU1: TXN0009718 | NIV1: TXN0009719 | NIW1: TXN0009720 | NIX1: TXN0009721 | NIY1: TXN0009722 | NIZ1: TXN0009723 | NJA1: TXN0009724 | NJB1: TXN0009725 | NJC1: TXN0009726 | NJD1: TXN0009727 | NJE1: TXN0009728 | NJF1: TXN0009729 | NJG1: TXN0009730 | NJH1: TXN0009731 | NJI1: TXN0009732 | NJJ1: TXN0009733 | NJK1: TXN0009734 | NJL1: TXN0009735 | NJM1: TXN0009736 | NJN1: TXN0009737 | NJO1: TXN0009738 | NJP1: TXN0009739 | NJQ1: TXN0009740 | NJR1: TXN0009741 | NJS1: TXN0009742 | NJT1: TXN0009743 | NJU1: TXN0009744 | NJV1: TXN0009745 | NJW1: TXN0009746 | NJX1: TXN0009747 | NJY1: TXN0009748 | NJZ1: TXN0009749 | NKA1: TXN0009750 | NKB1: TXN0009751 | NKC1: TXN0009752 | NKD1: TXN0009753 | NKE1: TXN0009754 | NKF1: TXN0009755 | NKG1: TXN0009756 | NKH1: TXN0009757 | NKI1: TXN0009758 | NKJ1: TXN0009759 | NKK1: TXN0009760 | NKL1: TXN0009761 | NKM1: TXN0009762 | NKN1: TXN0009763 | NKO1: TXN0009764 | NKP1: TXN0009765 | NKQ1: TXN0009766 | NKR1: TXN0009767 | NKS1: TXN0009768 | NKT1: TXN0009769 | NKU1: TXN0009770 | NKV1: TXN0009771 | NKW1: TXN0009772 | NKX1: TXN0009773 | NKY1: TXN0009774 | NKZ1: TXN0009775 | NLA1: TXN0009776 | NLB1: TXN0009777 | NLC1: TXN0009778 | NLD1: TXN0009779 | NLE1: TXN0009780 | NLF1: TXN0009781 | NLG1: TXN0009782 | NLH1: TXN0009783 | NLI1: TXN0009784 | NLJ1: TXN0009785 | NLK1: TXN0009786 | NLL1: TXN0009787 | NLM1: TXN0009788 | NLN1: TXN0009789 | NLO1: TXN0009790 | NLP1: TXN0009791 | NLQ1: TXN0009792 | NLR1: TXN0009793 | NLS1: TXN0009794 | NLT1: TXN0009795 | NLU1: TXN0009796 | NLV1: TXN0009797 | NLW1: TXN0009798 | NLX1: TXN0009799 | NLY1: TXN0009800 | NLZ1: TXN0009801 | NMA1: TXN0009802 | NMB1: TXN0009803 | NMC1: TXN0009804 | NMD1: TXN0009805 | NME1: TXN0009806 | NMF1: TXN0009807 | NMG1: TXN0009808 | NMH1: TXN0009809 | NMI1: TXN0009810 | NMJ1: TXN0009811 | NMK1: TXN0009812 | NML1: TXN0009813 | NMM1: TXN0009814 | NMN1: TXN0009815 | NMO1: TXN0009816 | NMP1: TXN0009817 | NMQ1: TXN0009818 | NMR1: TXN0009819 | NMS1: TXN0009820 | NMT1: TXN0009821 | NMU1: TXN0009822 | NMV1: TXN0009823 | NMW1: TXN0009824 | NMX1: TXN0009825 | NMY1: TXN0009826 | NMZ1: TXN0009827 | NNA1: TXN0009828 | NNB1: TXN0009829 | NNC1: TXN0009830 | NND1: TXN0009831 | NNE1: TXN0009832 | NNF1: TXN0009833 | NNG1: TXN0009834 | NNH1: TXN0009835 | NNI1: TXN0009836 | NNJ1: TXN0009837 | NNK1: TXN0009838 | NNL1: TXN0009839 | NNM1: TXN0009840 | NNN1: TXN0009841 | NNO1: TXN0009842 | NNP1: TXN0009843 | NNQ1: TXN0009844 | NNR1: TXN0009845 | NNS1: TXN0009846 | NNT1: TXN0009847 | NNU1: TXN0009848 | NNV1: TXN0009849 | NNW1: TXN0009850 | NNX1: TXN0009851 | NNY1: TXN0009852 | NNZ1: TXN0009853 | NOA1: TXN0009854 | NOB1: TXN0009855 | NOC1: TXN0009856 | NOD1: TXN0009857 | NOE1: TXN0009858 | NOF1: TXN0009859 | NOG1: TXN0009860 | NOH1: TXN0009861 | NOI1: TXN0009862 | NOJ1: TXN0009863 | NOK1: TXN0009864 | NOL1: TXN0009865 | NOM1: TXN0009866 | NON1: TXN0009867 | NOO1: TXN0009868 | NOP1: TXN0009869 | NOQ1: TXN0009870 | NOR1: TXN0009871 | NOS1: TXN0009872 | NOT1: TXN0009873 | NOU1: TXN0009874 | NOV1: TXN0009875 | NOW1: TXN0009876 | NOX1: TXN0009877 | NOY1: TXN0009878 | NOZ1: TXN0009879 | NPA1: TXN0009880 | NPB1: TXN0009881 | NPC1: TXN0009882 | NPD1: TXN0009883 | NPE1: TXN0009884 | NPF1: TXN0009885 | NPG1: TXN0009886 | NPH1: TXN0009887 | NPI1: TXN0009888 | NPJ1: TXN0009889 | NPK1: TXN0009890 | NPL1: TXN0009891 | NPM1: TXN0009892 | NPN1: TXN0009893 | NPO1: TXN0009894 | NPP1: TXN0009895 | NPQ1: TXN0009896 | NPR1: TXN0009897 | NPS1: TXN0009898 | NPT1: TXN0009899 | NPU1: TXN0009900 | NPV1: TXN0009901 | NPW1: TXN0009902 | NPX1: TXN0009903 | NPY1: TXN0009904 | NPZ1: TXN0009905 | NQA1: TXN0009906 | NQB1: TXN0009907 | NQC1: TXN0009908 | NQD1: TXN0009909 | NQE1: TXN0009910 | NQF1: TXN0009911 | NQG1: TXN0009912 | NQH1: TXN0009913 | NQI1: TXN0009914 | NQJ1: TXN0009915 | NQK1: TXN0009916 | NQL1: TXN0009917 | NQM1: TXN0009918 | NQN1: TXN0009919 | NQO1: TXN0009920 | NQP1: TXN0009921 | NQQ1: TXN0009922 | NQR1: TXN0009923 | NQS1: TXN0009924 | NQT1: TXN0009925 | NQU1: TXN0009926 | NQV1: TXN0009927 | NQW1: TXN0009928 | NQX1: TXN0009929 | NQY1: TXN0009930 | NQZ1: TXN0009931 | NRA1: TXN0009932 | NRB1: TXN0009933 | NRC1: TXN0009934 | NRD1: TXN0009935 | NRE1: TXN0009936 | NRF1: TXN0009937 | NRG1: TXN0009938 | NRH1: TXN0009939 | NRI1: TXN0009940 | NRJ1: TXN0009941 | NRK1: TXN0009942 | NRL1: TXN0009943 | NRM1: TXN0009944 | NRN1: TXN0009945 | NRO1: TXN0009946 | NRP1: TXN0009947 | NRQ1: TXN0009948 | NRR1: TXN0009949 | NRS1: TXN0009950 | NRT1: TXN0009951 | NRU1: TXN0009952 | NRV1: TXN0009953 | NRW1: TXN0009954 | NRX1: TXN0009955 | NRY1: TXN0009956 | NRZ1: TXN0009957 | NSA1: TXN0009958 | NSB1: TXN0009959 | NSC1: TXN0009960 | NSD1: TXN0009961 | NSE1: TXN0009962 | NSF1: TXN0009963 | NSG1: TXN0009964 | NSH1: TXN0009965 | NSI1: TXN0009966 | NSJ1: TXN0009967 | NSK1: TXN0009968 | NSL1: TXN0009969 | NSM1: TXN0009970 | NSN1: TXN0009971 | NSO1: TXN0009972 | NSP1: TXN0009973 | NSQ1: TXN0009974 | NSR1: TXN0009975 | NSS1: TXN0009976 | NST1: TXN0009977 | NSU1: TXN0009978 | NSV1: TXN0009979 | NSW1: TXN0009980 | NSX1: TXN0009981 | NSY1: TXN0009982 | NSZ1: TXN0009983 | NTA1: TXN0009984 | NTB1: TXN0009985 | NTC1: TXN0009986 | NTD1: TXN0009987 | NTE1: TXN0009988 | NTF1: TXN0009989 | NTG1: TXN0009990 | NTH1: TXN0009991 | NTI1: TXN0009992 | NTJ1: TXN0009993 | NTK1: TXN0009994 | NTL1: TXN0009995 | NTM1: TXN0009996 | NTN1: TXN0009997 | NTO1: TXN0009998 | NTP1: TXN0009999 | NTQ1: TXN0010000
